01_Boolean_Logic/Mux.v
/** 
 * Multiplexor:
 * out = a if sel == 0
 *       b otherwise
 */

`default_nettype none
module Mux(
  input a,
  input b,
  input sel,
  output out
);

  assign out = sel ? b : a ;

endmodule

01_Boolean_Logic/Mux16.v
/**
 * 16-bit multiplexor: 
 * for i = 0..15 out[i] = a[i] if sel == 0 
 *                        b[i] if sel == 1
 */

`default_nettype none
module Mux16(
  input [15:0] a,
  input [15:0] b,
  input sel,
  output [15:0] out
);

  // assign out = sel ? b : a ;

  genvar i;
  generate
    for(i = 0; i < 16; i++) begin : gen_mux
      Mux mux_inst(.a(a[i]),.b(b[i]),.sel(sel),.out(out[i]));
    end
  endgenerate

endmodule

01_Boolean_Logic/Mux4Way16.v
/**
 * 16-bit multiplexor:
 * for i = 0..15 out[i] = a[i] if sel == 0
 *                        b[i] if sel == 1
 00 a
 01 b
 10 c
 11 d
 */

`default_nettype none
module Mux4Way16(
  input [15:0] a,
  input [15:0] b,
  input [15:0] c,
  input [15:0] d,
  input [1:0] sel,
  output [15:0] out
);

  wire [15:0] upper2,lower2;


  // assign out = sel == 2'b00 ? a : (sel == 2'b01 ? b : (sel == 2'b10 ? c : d));
  Mux16 m1(.a(a),.b(b),.sel(sel[0]),.out(upper2));
  Mux16 m2(.a(c),.b(d),.sel(sel[0]),.out(lower2));

  Mux16 m3(.a(upper2),.b(lower2),.sel(sel[1]),.out(out));

endmodule

01_Boolean_Logic/Mux8Way16.v
/**
 * 16-bit multiplexor:
 * for i = 0..15 out[i] = a[i] if sel == 0
 *                        b[i] if sel == 1
 */

`default_nettype none
module Mux8Way16(
  input [15:0] a,
  input [15:0] b,
  input [15:0] c,
  input [15:0] d,
  input [15:0] e,
  input [15:0] f,
  input [15:0] g,
  input [15:0] h,
    input [2:0] sel,
  output [15:0] out
);
/*
  assign out =  (sel == 3'b000) ? a :
          (sel == 3'b001) ? b :
          (sel == 3'b010) ? c :
          (sel == 3'b011) ? d :
          (sel == 3'b100) ? e :
          (sel == 3'b101) ? f :
          (sel == 3'b110) ? g : h;
*/

    wire [15:0] upper4,lower4;

    Mux4Way16 m1(.a(a),.b(b),.c(c),.d(d),.sel(sel[1:0]),.out(upper4));
    Mux4Way16 m2(.a(e),.b(f),.c(g),.d(h),.sel(sel[1:0]),.out(lower4));

    Mux16 m3(.a(upper4),.b(lower4),.sel(sel[2]),.out(out));

endmodule

01_Boolean_Logic/15_Mux8Way16/Mux8Way16_tb.v
`default_nettype none
module Mux8Way16_tb();

	// IN,OUT
	reg [15:0] a,b,c,d,e,f,g,h;
	reg [2:0] sel;
	wire [15:0] out;

	// PART
	Mux8Way16 MUX8WAY16(
		.a(a),
		.b(b),
		.c(c),
		.d(d),
		.e(e),
		.f(f),
		.g(g),
		.h(h),
		.sel(sel),
		.out(out)
	);
	
	// Compare
	wire [15:0] out_cmp;
	assign out_cmp = (sel[2]?(sel[1]? (sel[0]?h:g):(sel[0]?f:e)):
							 (sel[1]? (sel[0]?d:c):(sel[0]?b:a)));

	reg fail = 0;
	reg [15:0] n = 0;
	task check;
		#1
		if (out != out_cmp)
			begin
				$display("FAIL: a=%16b, b=%16b, c=%16b, d=%16b, e=%16b, f=%16b, g=%16b, h=%16b, sel=%3b, out=%16b",a,b,c,d,e,f,g,h,sel,out);
				fail=1;
			end
	endtask
	  
  	initial begin
  		$dumpvars(0, Mux8Way16_tb);
		
		$display("------------------------");
		$display("Testbench: Mux8Way16");
		
		for (n=0; n<100;n=n+1) 
			begin
				a=$random;
				b=$random;
				c=$random;
				d=$random;
				e=$random;
				f=$random;
				g=$random;
				h=$random;
				sel=0;check();
				sel=1;check();
				sel=2;check();
				sel=3;check();
				sel=4;check();
				sel=5;check();
				sel=6;check();
				sel=7;check();
			end
		
		if (fail==0) $display("passed");
		$display("------------------------");
		$finish;
	end

endmodule

01_Boolean_Logic/15_Mux8Way16/_build/default/Mux8Way16_tb.vcd
$date
	Wed Aug  5 02:33:54 2026
$end
$version
	Icarus Verilog
$end
$timescale
	1ps
$end
$scope module Mux8Way16_tb $end
$var wire 16 ! out_cmp [15:0] $end
$var wire 16 " out [15:0] $end
$var reg 16 # a [15:0] $end
$var reg 16 $ b [15:0] $end
$var reg 16 % c [15:0] $end
$var reg 16 & d [15:0] $end
$var reg 16 ' e [15:0] $end
$var reg 16 ( f [15:0] $end
$var reg 1 ) fail $end
$var reg 16 * g [15:0] $end
$var reg 16 + h [15:0] $end
$var reg 16 , n [15:0] $end
$var reg 3 - sel [2:0] $end
$scope module MUX8WAY16 $end
$var wire 16 . a [15:0] $end
$var wire 16 / b [15:0] $end
$var wire 16 0 c [15:0] $end
$var wire 16 1 d [15:0] $end
$var wire 16 2 e [15:0] $end
$var wire 16 3 f [15:0] $end
$var wire 16 4 g [15:0] $end
$var wire 16 5 h [15:0] $end
$var wire 3 6 sel [2:0] $end
$var wire 16 7 upper4 [15:0] $end
$var wire 16 8 out [15:0] $end
$var wire 16 9 lower4 [15:0] $end
$scope module m1 $end
$var wire 16 : a [15:0] $end
$var wire 16 ; b [15:0] $end
$var wire 16 < c [15:0] $end
$var wire 16 = d [15:0] $end
$var wire 2 > sel [1:0] $end
$var wire 16 ? upper2 [15:0] $end
$var wire 16 @ out [15:0] $end
$var wire 16 A lower2 [15:0] $end
$scope module m1 $end
$var wire 16 B a [15:0] $end
$var wire 16 C b [15:0] $end
$var wire 1 D sel $end
$var wire 16 E out [15:0] $end
$upscope $end
$scope module m2 $end
$var wire 16 F a [15:0] $end
$var wire 16 G b [15:0] $end
$var wire 1 H sel $end
$var wire 16 I out [15:0] $end
$upscope $end
$scope module m3 $end
$var wire 16 J a [15:0] $end
$var wire 16 K b [15:0] $end
$var wire 1 L sel $end
$var wire 16 M out [15:0] $end
$upscope $end
$upscope $end
$scope module m2 $end
$var wire 16 N a [15:0] $end
$var wire 16 O b [15:0] $end
$var wire 16 P c [15:0] $end
$var wire 16 Q d [15:0] $end
$var wire 2 R sel [1:0] $end
$var wire 16 S upper2 [15:0] $end
$var wire 16 T out [15:0] $end
$var wire 16 U lower2 [15:0] $end
$scope module m1 $end
$var wire 16 V a [15:0] $end
$var wire 16 W b [15:0] $end
$var wire 1 X sel $end
$var wire 16 Y out [15:0] $end
$upscope $end
$scope module m2 $end
$var wire 16 Z a [15:0] $end
$var wire 16 [ b [15:0] $end
$var wire 1 \ sel $end
$var wire 16 ] out [15:0] $end
$upscope $end
$scope module m3 $end
$var wire 16 ^ a [15:0] $end
$var wire 16 _ b [15:0] $end
$var wire 1 ` sel $end
$var wire 16 a out [15:0] $end
$upscope $end
$upscope $end
$scope module m3 $end
$var wire 16 b a [15:0] $end
$var wire 16 c b [15:0] $end
$var wire 1 d sel $end
$var wire 16 e out [15:0] $end
$upscope $end
$upscope $end
$scope task check $end
$upscope $end
$upscope $end
$enddefinitions $end
$comment Show the parameter values. $end
$dumpall
$end
#0
$dumpvars
b11010100100100 e
0d
b111101100001101 c
b11010100100100 b
b111101100001101 a
0`
b1000010001100101 _
b111101100001101 ^
b1000010001100101 ]
0\
b101001000010010 [
b1000010001100101 Z
b111101100001101 Y
0X
b1001100110001101 W
b111101100001101 V
b1000010001100101 U
b111101100001101 T
b111101100001101 S
b0 R
b101001000010010 Q
b1000010001100101 P
b1001100110001101 O
b111101100001101 N
b11010100100100 M
0L
b1101011000001001 K
b11010100100100 J
b1101011000001001 I
0H
b101011001100011 G
b1101011000001001 F
b11010100100100 E
0D
b101111010000001 C
b11010100100100 B
b1101011000001001 A
b11010100100100 @
b11010100100100 ?
b0 >
b101011001100011 =
b1101011000001001 <
b101111010000001 ;
b11010100100100 :
b111101100001101 9
b11010100100100 8
b11010100100100 7
b0 6
b101001000010010 5
b1000010001100101 4
b1001100110001101 3
b111101100001101 2
b101011001100011 1
b1101011000001001 0
b101111010000001 /
b11010100100100 .
b0 -
b0 ,
b101001000010010 +
b1000010001100101 *
0)
b1001100110001101 (
b111101100001101 '
b101011001100011 &
b1101011000001001 %
b101111010000001 $
b11010100100100 #
b11010100100100 "
b11010100100100 !
$end
#1
b101111010000001 "
b101111010000001 8
b101111010000001 e
b101111010000001 !
b101111010000001 7
b101111010000001 @
b101111010000001 M
b101111010000001 b
b1001100110001101 9
b1001100110001101 T
b1001100110001101 a
b1001100110001101 c
b101111010000001 ?
b101111010000001 E
b101111010000001 J
b101011001100011 A
b101011001100011 I
b101011001100011 K
b1001100110001101 S
b1001100110001101 Y
b1001100110001101 ^
b101001000010010 U
b101001000010010 ]
b101001000010010 _
1D
1H
1X
1\
b1 >
b1 R
b1 -
b1 6
#2
b1101011000001001 "
b1101011000001001 8
b1101011000001001 e
b1101011000001001 !
b11010100100100 ?
b11010100100100 E
b11010100100100 J
b1101011000001001 A
b1101011000001001 I
b1101011000001001 K
b1101011000001001 7
b1101011000001001 @
b1101011000001001 M
b1101011000001001 b
b111101100001101 S
b111101100001101 Y
b111101100001101 ^
b1000010001100101 U
b1000010001100101 ]
b1000010001100101 _
b1000010001100101 9
b1000010001100101 T
b1000010001100101 a
b1000010001100101 c
0D
0H
1L
0X
0\
1`
b10 >
b10 R
b10 -
b10 6
#3
b101011001100011 "
b101011001100011 8
b101011001100011 e
b101011001100011 !
b101011001100011 7
b101011001100011 @
b101011001100011 M
b101011001100011 b
b101001000010010 9
b101001000010010 T
b101001000010010 a
b101001000010010 c
b101111010000001 ?
b101111010000001 E
b101111010000001 J
b101011001100011 A
b101011001100011 I
b101011001100011 K
b1001100110001101 S
b1001100110001101 Y
b1001100110001101 ^
b101001000010010 U
b101001000010010 ]
b101001000010010 _
1D
1H
1X
1\
b11 >
b11 R
b11 -
b11 6
#4
b11010100100100 ?
b11010100100100 E
b11010100100100 J
b1101011000001001 A
b1101011000001001 I
b1101011000001001 K
b11010100100100 7
b11010100100100 @
b11010100100100 M
b11010100100100 b
b111101100001101 S
b111101100001101 Y
b111101100001101 ^
b1000010001100101 U
b1000010001100101 ]
b1000010001100101 _
b111101100001101 9
b111101100001101 T
b111101100001101 a
b111101100001101 c
b111101100001101 !
0D
0H
0L
0X
0\
0`
b111101100001101 "
b111101100001101 8
b111101100001101 e
b0 >
b0 R
1d
b100 -
b100 6
#5
b1001100110001101 "
b1001100110001101 8
b1001100110001101 e
b1001100110001101 !
b101111010000001 7
b101111010000001 @
b101111010000001 M
b101111010000001 b
b1001100110001101 9
b1001100110001101 T
b1001100110001101 a
b1001100110001101 c
b101111010000001 ?
b101111010000001 E
b101111010000001 J
b101011001100011 A
b101011001100011 I
b101011001100011 K
b1001100110001101 S
b1001100110001101 Y
b1001100110001101 ^
b101001000010010 U
b101001000010010 ]
b101001000010010 _
1D
1H
1X
1\
b1 >
b1 R
b101 -
b101 6
#6
b1000010001100101 "
b1000010001100101 8
b1000010001100101 e
b1000010001100101 !
b11010100100100 ?
b11010100100100 E
b11010100100100 J
b1101011000001001 A
b1101011000001001 I
b1101011000001001 K
b1101011000001001 7
b1101011000001001 @
b1101011000001001 M
b1101011000001001 b
b111101100001101 S
b111101100001101 Y
b111101100001101 ^
b1000010001100101 U
b1000010001100101 ]
b1000010001100101 _
b1000010001100101 9
b1000010001100101 T
b1000010001100101 a
b1000010001100101 c
0D
0H
1L
0X
0\
1`
b10 >
b10 R
b110 -
b110 6
#7
b101001000010010 "
b101001000010010 8
b101001000010010 e
b101001000010010 !
b101011001100011 7
b101011001100011 @
b101011001100011 M
b101011001100011 b
b101001000010010 9
b101001000010010 T
b101001000010010 a
b101001000010010 c
b101111010000001 ?
b101111010000001 E
b101111010000001 J
b101011001100011 A
b101011001100011 I
b101011001100011 K
b1001100110001101 S
b1001100110001101 Y
b1001100110001101 ^
b101001000010010 U
b101001000010010 ]
b101001000010010 _
1D
1H
1X
1\
b11 >
b11 R
b111 -
b111 6
#8
b1110001100000001 !
0D
0H
0L
0X
0\
0`
b1110001100000001 "
b1110001100000001 8
b1110001100000001 e
b101011111101101 9
b101011111101101 T
b101011111101101 a
b101011111101101 c
b1110001100000001 7
b1110001100000001 @
b1110001100000001 M
b1110001100000001 b
b0 >
b0 R
0d
b1110100111111001 U
b1110100111111001 ]
b1110100111111001 _
b101011111101101 S
b101011111101101 Y
b101011111101101 ^
b1111000101110110 A
b1111000101110110 I
b1111000101110110 K
b1110001100000001 ?
b1110001100000001 E
b1110001100000001 J
b0 -
b0 6
b10010011000110 +
b10010011000110 5
b10010011000110 Q
b10010011000110 [
b1110100111111001 *
b1110100111111001 4
b1110100111111001 P
b1110100111111001 Z
b1111011110001100 (
b1111011110001100 3
b1111011110001100 O
b1111011110001100 W
b101011111101101 '
b101011111101101 2
b101011111101101 N
b101011111101101 V
b1100110100111101 &
b1100110100111101 1
b1100110100111101 =
b1100110100111101 G
b1111000101110110 %
b1111000101110110 0
b1111000101110110 <
b1111000101110110 F
b1100110100001101 $
b1100110100001101 /
b1100110100001101 ;
b1100110100001101 C
b1110001100000001 #
b1110001100000001 .
b1110001100000001 :
b1110001100000001 B
b1 ,
#9
b1100110100001101 "
b1100110100001101 8
b1100110100001101 e
b1100110100001101 !
b1100110100001101 7
b1100110100001101 @
b1100110100001101 M
b1100110100001101 b
b1111011110001100 9
b1111011110001100 T
b1111011110001100 a
b1111011110001100 c
b1100110100001101 ?
b1100110100001101 E
b1100110100001101 J
b1100110100111101 A
b1100110100111101 I
b1100110100111101 K
b1111011110001100 S
b1111011110001100 Y
b1111011110001100 ^
b10010011000110 U
b10010011000110 ]
b10010011000110 _
1D
1H
1X
1\
b1 >
b1 R
b1 -
b1 6
#10
b1111000101110110 "
b1111000101110110 8
b1111000101110110 e
b1111000101110110 !
b1110001100000001 ?
b1110001100000001 E
b1110001100000001 J
b1111000101110110 A
b1111000101110110 I
b1111000101110110 K
b1111000101110110 7
b1111000101110110 @
b1111000101110110 M
b1111000101110110 b
b101011111101101 S
b101011111101101 Y
b101011111101101 ^
b1110100111111001 U
b1110100111111001 ]
b1110100111111001 _
b1110100111111001 9
b1110100111111001 T
b1110100111111001 a
b1110100111111001 c
0D
0H
1L
0X
0\
1`
b10 >
b10 R
b10 -
b10 6
#11
b1100110100111101 "
b1100110100111101 8
b1100110100111101 e
b1100110100111101 !
b1100110100111101 7
b1100110100111101 @
b1100110100111101 M
b1100110100111101 b
b10010011000110 9
b10010011000110 T
b10010011000110 a
b10010011000110 c
b1100110100001101 ?
b1100110100001101 E
b1100110100001101 J
b1100110100111101 A
b1100110100111101 I
b1100110100111101 K
b1111011110001100 S
b1111011110001100 Y
b1111011110001100 ^
b10010011000110 U
b10010011000110 ]
b10010011000110 _
1D
1H
1X
1\
b11 >
b11 R
b11 -
b11 6
#12
b1110001100000001 ?
b1110001100000001 E
b1110001100000001 J
b1111000101110110 A
b1111000101110110 I
b1111000101110110 K
b1110001100000001 7
b1110001100000001 @
b1110001100000001 M
b1110001100000001 b
b101011111101101 S
b101011111101101 Y
b101011111101101 ^
b1110100111111001 U
b1110100111111001 ]
b1110100111111001 _
b101011111101101 9
b101011111101101 T
b101011111101101 a
b101011111101101 c
b101011111101101 !
0D
0H
0L
0X
0\
0`
b101011111101101 "
b101011111101101 8
b101011111101101 e
b0 >
b0 R
1d
b100 -
b100 6
#13
b1111011110001100 "
b1111011110001100 8
b1111011110001100 e
b1111011110001100 !
b1100110100001101 7
b1100110100001101 @
b1100110100001101 M
b1100110100001101 b
b1111011110001100 9
b1111011110001100 T
b1111011110001100 a
b1111011110001100 c
b1100110100001101 ?
b1100110100001101 E
b1100110100001101 J
b1100110100111101 A
b1100110100111101 I
b1100110100111101 K
b1111011110001100 S
b1111011110001100 Y
b1111011110001100 ^
b10010011000110 U
b10010011000110 ]
b10010011000110 _
1D
1H
1X
1\
b1 >
b1 R
b101 -
b101 6
#14
b1110100111111001 "
b1110100111111001 8
b1110100111111001 e
b1110100111111001 !
b1110001100000001 ?
b1110001100000001 E
b1110001100000001 J
b1111000101110110 A
b1111000101110110 I
b1111000101110110 K
b1111000101110110 7
b1111000101110110 @
b1111000101110110 M
b1111000101110110 b
b101011111101101 S
b101011111101101 Y
b101011111101101 ^
b1110100111111001 U
b1110100111111001 ]
b1110100111111001 _
b1110100111111001 9
b1110100111111001 T
b1110100111111001 a
b1110100111111001 c
0D
0H
1L
0X
0\
1`
b10 >
b10 R
b110 -
b110 6
#15
b10010011000110 "
b10010011000110 8
b10010011000110 e
b10010011000110 !
b1100110100111101 7
b1100110100111101 @
b1100110100111101 M
b1100110100111101 b
b10010011000110 9
b10010011000110 T
b10010011000110 a
b10010011000110 c
b1100110100001101 ?
b1100110100001101 E
b1100110100001101 J
b1100110100111101 A
b1100110100111101 I
b1100110100111101 K
b1111011110001100 S
b1111011110001100 Y
b1111011110001100 ^
b10010011000110 U
b10010011000110 ]
b10010011000110 _
1D
1H
1X
1\
b11 >
b11 R
b111 -
b111 6
#16
b1000010011000101 !
0D
0H
0L
0X
0\
0`
b1000010011000101 "
b1000010011000101 8
b1000010011000101 e
b1101011000010010 9
b1101011000010010 T
b1101011000010010 a
b1101011000010010 c
b1000010011000101 7
b1000010011000101 @
b1000010011000101 M
b1000010011000101 b
b0 >
b0 R
0d
b110100111110010 U
b110100111110010 ]
b110100111110010 _
b1101011000010010 S
b1101011000010010 Y
b1101011000010010 ^
b1111011111100101 A
b1111011111100101 I
b1111011111100101 K
b1000010011000101 ?
b1000010011000101 E
b1000010011000101 J
b0 -
b0 6
b1001011011001110 +
b1001011011001110 5
b1001011011001110 Q
b1001011011001110 [
b110100111110010 *
b110100111110010 4
b110100111110010 P
b110100111110010 Z
b1101101110001111 (
b1101101110001111 3
b1101101110001111 O
b1101101110001111 W
b1101011000010010 '
b1101011000010010 2
b1101011000010010 N
b1101011000010010 V
b111001001110111 &
b111001001110111 1
b111001001110111 =
b111001001110111 G
b1111011111100101 %
b1111011111100101 0
b1111011111100101 <
b1111011111100101 F
b1101001010101010 $
b1101001010101010 /
b1101001010101010 ;
b1101001010101010 C
b1000010011000101 #
b1000010011000101 .
b1000010011000101 :
b1000010011000101 B
b10 ,
#17
b1101001010101010 "
b1101001010101010 8
b1101001010101010 e
b1101001010101010 !
b1101001010101010 7
b1101001010101010 @
b1101001010101010 M
b1101001010101010 b
b1101101110001111 9
b1101101110001111 T
b1101101110001111 a
b1101101110001111 c
b1101001010101010 ?
b1101001010101010 E
b1101001010101010 J
b111001001110111 A
b111001001110111 I
b111001001110111 K
b1101101110001111 S
b1101101110001111 Y
b1101101110001111 ^
b1001011011001110 U
b1001011011001110 ]
b1001011011001110 _
1D
1H
1X
1\
b1 >
b1 R
b1 -
b1 6
#18
b1111011111100101 "
b1111011111100101 8
b1111011111100101 e
b1111011111100101 !
b1000010011000101 ?
b1000010011000101 E
b1000010011000101 J
b1111011111100101 A
b1111011111100101 I
b1111011111100101 K
b1111011111100101 7
b1111011111100101 @
b1111011111100101 M
b1111011111100101 b
b1101011000010010 S
b1101011000010010 Y
b1101011000010010 ^
b110100111110010 U
b110100111110010 ]
b110100111110010 _
b110100111110010 9
b110100111110010 T
b110100111110010 a
b110100111110010 c
0D
0H
1L
0X
0\
1`
b10 >
b10 R
b10 -
b10 6
#19
b111001001110111 "
b111001001110111 8
b111001001110111 e
b111001001110111 !
b111001001110111 7
b111001001110111 @
b111001001110111 M
b111001001110111 b
b1001011011001110 9
b1001011011001110 T
b1001011011001110 a
b1001011011001110 c
b1101001010101010 ?
b1101001010101010 E
b1101001010101010 J
b111001001110111 A
b111001001110111 I
b111001001110111 K
b1101101110001111 S
b1101101110001111 Y
b1101101110001111 ^
b1001011011001110 U
b1001011011001110 ]
b1001011011001110 _
1D
1H
1X
1\
b11 >
b11 R
b11 -
b11 6
#20
b1000010011000101 ?
b1000010011000101 E
b1000010011000101 J
b1111011111100101 A
b1111011111100101 I
b1111011111100101 K
b1000010011000101 7
b1000010011000101 @
b1000010011000101 M
b1000010011000101 b
b1101011000010010 S
b1101011000010010 Y
b1101011000010010 ^
b110100111110010 U
b110100111110010 ]
b110100111110010 _
b1101011000010010 9
b1101011000010010 T
b1101011000010010 a
b1101011000010010 c
b1101011000010010 !
0D
0H
0L
0X
0\
0`
b1101011000010010 "
b1101011000010010 8
b1101011000010010 e
b0 >
b0 R
1d
b100 -
b100 6
#21
b1101101110001111 "
b1101101110001111 8
b1101101110001111 e
b1101101110001111 !
b1101001010101010 7
b1101001010101010 @
b1101001010101010 M
b1101001010101010 b
b1101101110001111 9
b1101101110001111 T
b1101101110001111 a
b1101101110001111 c
b1101001010101010 ?
b1101001010101010 E
b1101001010101010 J
b111001001110111 A
b111001001110111 I
b111001001110111 K
b1101101110001111 S
b1101101110001111 Y
b1101101110001111 ^
b1001011011001110 U
b1001011011001110 ]
b1001011011001110 _
1D
1H
1X
1\
b1 >
b1 R
b101 -
b101 6
#22
b110100111110010 "
b110100111110010 8
b110100111110010 e
b110100111110010 !
b1000010011000101 ?
b1000010011000101 E
b1000010011000101 J
b1111011111100101 A
b1111011111100101 I
b1111011111100101 K
b1111011111100101 7
b1111011111100101 @
b1111011111100101 M
b1111011111100101 b
b1101011000010010 S
b1101011000010010 Y
b1101011000010010 ^
b110100111110010 U
b110100111110010 ]
b110100111110010 _
b110100111110010 9
b110100111110010 T
b110100111110010 a
b110100111110010 c
0D
0H
1L
0X
0\
1`
b10 >
b10 R
b110 -
b110 6
#23
b1001011011001110 "
b1001011011001110 8
b1001011011001110 e
b1001011011001110 !
b111001001110111 7
b111001001110111 @
b111001001110111 M
b111001001110111 b
b1001011011001110 9
b1001011011001110 T
b1001011011001110 a
b1001011011001110 c
b1101001010101010 ?
b1101001010101010 E
b1101001010101010 J
b111001001110111 A
b111001001110111 I
b111001001110111 K
b1101101110001111 S
b1101101110001111 Y
b1101101110001111 ^
b1001011011001110 U
b1001011011001110 ]
b1001011011001110 _
1D
1H
1X
1\
b11 >
b11 R
b111 -
b111 6
#24
b111101011101000 !
0D
0H
0L
0X
0\
0`
b111101011101000 "
b111101011101000 8
b111101011101000 e
b101100000101101 9
b101100000101101 T
b101100000101101 a
b101100000101101 c
b111101011101000 7
b111101011101000 @
b111101011101000 M
b111101011101000 b
b0 >
b0 R
0d
b110001001100011 U
b110001001100011 ]
b110001001100011 _
b101100000101101 S
b101100000101101 Y
b101100000101101 ^
b100100101011100 A
b100100101011100 I
b100100101011100 K
b111101011101000 ?
b111101011101000 E
b111101011101000 J
b0 -
b0 6
b1000011100001010 +
b1000011100001010 5
b1000011100001010 Q
b1000011100001010 [
b110001001100011 *
b110001001100011 4
b110001001100011 P
b110001001100011 Z
b10011001100101 (
b10011001100101 3
b10011001100101 O
b10011001100101 W
b101100000101101 '
b101100000101101 2
b101100000101101 N
b101100000101101 V
b10100010111101 &
b10100010111101 1
b10100010111101 =
b10100010111101 G
b100100101011100 %
b100100101011100 0
b100100101011100 <
b100100101011100 F
b100111011000101 $
b100111011000101 /
b100111011000101 ;
b100111011000101 C
b111101011101000 #
b111101011101000 .
b111101011101000 :
b111101011101000 B
b11 ,
#25
b100111011000101 "
b100111011000101 8
b100111011000101 e
b100111011000101 !
b100111011000101 7
b100111011000101 @
b100111011000101 M
b100111011000101 b
b10011001100101 9
b10011001100101 T
b10011001100101 a
b10011001100101 c
b100111011000101 ?
b100111011000101 E
b100111011000101 J
b10100010111101 A
b10100010111101 I
b10100010111101 K
b10011001100101 S
b10011001100101 Y
b10011001100101 ^
b1000011100001010 U
b1000011100001010 ]
b1000011100001010 _
1D
1H
1X
1\
b1 >
b1 R
b1 -
b1 6
#26
b100100101011100 "
b100100101011100 8
b100100101011100 e
b100100101011100 !
b111101011101000 ?
b111101011101000 E
b111101011101000 J
b100100101011100 A
b100100101011100 I
b100100101011100 K
b100100101011100 7
b100100101011100 @
b100100101011100 M
b100100101011100 b
b101100000101101 S
b101100000101101 Y
b101100000101101 ^
b110001001100011 U
b110001001100011 ]
b110001001100011 _
b110001001100011 9
b110001001100011 T
b110001001100011 a
b110001001100011 c
0D
0H
1L
0X
0\
1`
b10 >
b10 R
b10 -
b10 6
#27
b10100010111101 "
b10100010111101 8
b10100010111101 e
b10100010111101 !
b10100010111101 7
b10100010111101 @
b10100010111101 M
b10100010111101 b
b1000011100001010 9
b1000011100001010 T
b1000011100001010 a
b1000011100001010 c
b100111011000101 ?
b100111011000101 E
b100111011000101 J
b10100010111101 A
b10100010111101 I
b10100010111101 K
b10011001100101 S
b10011001100101 Y
b10011001100101 ^
b1000011100001010 U
b1000011100001010 ]
b1000011100001010 _
1D
1H
1X
1\
b11 >
b11 R
b11 -
b11 6
#28
b111101011101000 ?
b111101011101000 E
b111101011101000 J
b100100101011100 A
b100100101011100 I
b100100101011100 K
b111101011101000 7
b111101011101000 @
b111101011101000 M
b111101011101000 b
b101100000101101 S
b101100000101101 Y
b101100000101101 ^
b110001001100011 U
b110001001100011 ]
b110001001100011 _
b101100000101101 9
b101100000101101 T
b101100000101101 a
b101100000101101 c
b101100000101101 !
0D
0H
0L
0X
0\
0`
b101100000101101 "
b101100000101101 8
b101100000101101 e
b0 >
b0 R
1d
b100 -
b100 6
#29
b10011001100101 "
b10011001100101 8
b10011001100101 e
b10011001100101 !
b100111011000101 7
b100111011000101 @
b100111011000101 M
b100111011000101 b
b10011001100101 9
b10011001100101 T
b10011001100101 a
b10011001100101 c
b100111011000101 ?
b100111011000101 E
b100111011000101 J
b10100010111101 A
b10100010111101 I
b10100010111101 K
b10011001100101 S
b10011001100101 Y
b10011001100101 ^
b1000011100001010 U
b1000011100001010 ]
b1000011100001010 _
1D
1H
1X
1\
b1 >
b1 R
b101 -
b101 6
#30
b110001001100011 "
b110001001100011 8
b110001001100011 e
b110001001100011 !
b111101011101000 ?
b111101011101000 E
b111101011101000 J
b100100101011100 A
b100100101011100 I
b100100101011100 K
b100100101011100 7
b100100101011100 @
b100100101011100 M
b100100101011100 b
b101100000101101 S
b101100000101101 Y
b101100000101101 ^
b110001001100011 U
b110001001100011 ]
b110001001100011 _
b110001001100011 9
b110001001100011 T
b110001001100011 a
b110001001100011 c
0D
0H
1L
0X
0\
1`
b10 >
b10 R
b110 -
b110 6
#31
b1000011100001010 "
b1000011100001010 8
b1000011100001010 e
b1000011100001010 !
b10100010111101 7
b10100010111101 @
b10100010111101 M
b10100010111101 b
b1000011100001010 9
b1000011100001010 T
b1000011100001010 a
b1000011100001010 c
b100111011000101 ?
b100111011000101 E
b100111011000101 J
b10100010111101 A
b10100010111101 I
b10100010111101 K
b10011001100101 S
b10011001100101 Y
b10011001100101 ^
b1000011100001010 U
b1000011100001010 ]
b1000011100001010 _
1D
1H
1X
1\
b11 >
b11 R
b111 -
b111 6
#32
b10001010000000 !
0D
0H
0L
0X
0\
0`
b10001010000000 "
b10001010000000 8
b10001010000000 e
b11111010010110 9
b11111010010110 T
b11111010010110 a
b11111010010110 c
b10001010000000 7
b10001010000000 @
b10001010000000 M
b10001010000000 b
b0 >
b0 R
0d
b11100000001101 U
b11100000001101 ]
b11100000001101 _
b11111010010110 S
b11111010010110 Y
b11111010010110 ^
b100010110101010 A
b100010110101010 I
b100010110101010 K
b10001010000000 ?
b10001010000000 E
b10001010000000 J
b0 -
b0 6
b1101011001010011 +
b1101011001010011 5
b1101011001010011 Q
b1101011001010011 [
b11100000001101 *
b11100000001101 4
b11100000001101 P
b11100000001101 Z
b1011100000010011 (
b1011100000010011 3
b1011100000010011 O
b1011100000010011 W
b11111010010110 '
b11111010010110 2
b11111010010110 N
b11111010010110 V
b1100110010011101 &
b1100110010011101 1
b1100110010011101 =
b1100110010011101 G
b100010110101010 %
b100010110101010 0
b100010110101010 <
b100010110101010 F
b10000100100000 $
b10000100100000 /
b10000100100000 ;
b10000100100000 C
b10001010000000 #
b10001010000000 .
b10001010000000 :
b10001010000000 B
b100 ,
#33
b10000100100000 "
b10000100100000 8
b10000100100000 e
b10000100100000 !
b10000100100000 7
b10000100100000 @
b10000100100000 M
b10000100100000 b
b1011100000010011 9
b1011100000010011 T
b1011100000010011 a
b1011100000010011 c
b10000100100000 ?
b10000100100000 E
b10000100100000 J
b1100110010011101 A
b1100110010011101 I
b1100110010011101 K
b1011100000010011 S
b1011100000010011 Y
b1011100000010011 ^
b1101011001010011 U
b1101011001010011 ]
b1101011001010011 _
1D
1H
1X
1\
b1 >
b1 R
b1 -
b1 6
#34
b100010110101010 "
b100010110101010 8
b100010110101010 e
b100010110101010 !
b10001010000000 ?
b10001010000000 E
b10001010000000 J
b100010110101010 A
b100010110101010 I
b100010110101010 K
b100010110101010 7
b100010110101010 @
b100010110101010 M
b100010110101010 b
b11111010010110 S
b11111010010110 Y
b11111010010110 ^
b11100000001101 U
b11100000001101 ]
b11100000001101 _
b11100000001101 9
b11100000001101 T
b11100000001101 a
b11100000001101 c
0D
0H
1L
0X
0\
1`
b10 >
b10 R
b10 -
b10 6
#35
b1100110010011101 "
b1100110010011101 8
b1100110010011101 e
b1100110010011101 !
b1100110010011101 7
b1100110010011101 @
b1100110010011101 M
b1100110010011101 b
b1101011001010011 9
b1101011001010011 T
b1101011001010011 a
b1101011001010011 c
b10000100100000 ?
b10000100100000 E
b10000100100000 J
b1100110010011101 A
b1100110010011101 I
b1100110010011101 K
b1011100000010011 S
b1011100000010011 Y
b1011100000010011 ^
b1101011001010011 U
b1101011001010011 ]
b1101011001010011 _
1D
1H
1X
1\
b11 >
b11 R
b11 -
b11 6
