02_Boolean_Arithmetic/ALU.v
/**
 * The ALU (Arithmetic Logic Unit).
 * Computes one of the following functions:
 * x+y, x-y, y-x, 0, 1, -1, x, y, -x, -y, !x, !y,
 * x+1, y+1, x-1, y-1, x&y, x|y on two 16-bit inputs,
 * according to 6 input bits denoted zx,nx,zy,ny,f,no.
 * In addition, the ALU computes two 1-bit outputs:
 * if the ALU output == 0, zr is set to 1; otherwise zr is set to 0;
 * if the ALU output < 0, ng is set to 1; otherwise ng is set to 0.
 */

// Implementation: the ALU logic manipulates the x and y inputs
// and operates on the resulting values, as follows:
// if (zx == 1) set x = 0        // 16-bit constant
// if (nx == 1) set x = !x       // bitwise not
// if (zy == 1) set y = 0        // 16-bit constant
// if (ny == 1) set y = !y       // bitwise not
// if (f == 1)  set out = x + y  // integer 2's complement addition
// if (f == 0)  set out = x & y  // bitwise and
// if (no == 1) set out = !out   // bitwise not
// if (out == 0) set zr = 1
// if (out < 0) set ng = 1

`default_nettype none
module ALU(
	input [15:0] x,		// input x (16 bit)
	input [15:0] y,		// input y (16 bit)
    input zx, 				// zero the x input?
    input nx, 				// negate the x input?
    input zy, 				// zero the y input?
    input ny, 				// negate the y input?
    input f,  				// compute out = x + y (if 1) or x & y (if 0)
    input no, 				// negate the out output?
    output [15:0] out, 			// 16-bit output
    output zr, 				// 1 if (out == 0), 0 otherwise
    output ng 				// 1 if (out < 0),  0 otherwise
);

	wire [15:0] x1 = zx ? 16'b0000000000000000 : x;
    wire [15:0] x2 = nx ? ~x1 : x1;
    wire [15:0] y1 = zy ? 16'b0000000000000000 : y;
    wire [15:0] y2 = ny ? ~y1 : y1;

    wire [15:0] out_f = f ? (x2 + y2) : (x2 & y2);
    wire [15:0] out1 = no ? ~out_f : out_f;

    assign out = out1;
    assign zr  = (out1 == 16'b0000000000000000);
    assign ng  = out1[15];

    // here the 2nd time, nothin to change actually
endmodule

02_Boolean_Arithmetic/05_ALU/ALU_tb.v
`default_nettype none
module ALU_tb();

	// IN,OUT
	reg [15:0] x,y;
	reg zx,nx,zy,ny,f,no;
	wire [15:0] out;
	wire zr,ng;

	// Part	
	ALU ALU(
		.x(x),
		.y(y),
		.zx(zx),
		.nx(nx),
		.zy(zy),
		.ny(ny),
		.f(f),
		.no(no),
		.out(out),
		.zr(zr),
		.ng(ng)
	);
	
	// Compare
	wire [15:0] xx,yy,out_cmp;
	wire zr_cmp,ng_cmp;
	assign xx = nx?(zx?~0:~x):(zx?0:x);
	assign yy = ny?(zy?~0:~y):(zy?0:y);
	assign out_cmp= no?(f?~(xx+yy):~(xx&yy)):(f?(xx+yy):(xx&yy));
	assign zr_cmp = (out==0);
	assign ng_cmp = out[15];
	
	reg fail = 0;
	reg [15:0] n = 0;
	task check;
		#1
		if ((out != out_cmp) || (zr != zr_cmp) || (ng != ng_cmp)) 
			begin
				$display("FAIL: x=%16b, y=%16b, zx=%1b, nx=%1b, zy=%1b, ny=%1b, f=%1b, no=%1b, out=%16b, zr=%1b, ng=%1b",x,y,zx,nx,zy,ny,f,no,out,zr,ng);
				fail=1;
			end
	endtask
	  
  	initial begin
  		$dumpvars(0, ALU_tb);
		
		$display("------------------------");
		$display("Testbench: ALU");
		
		for (n=0; n<100;n=n+1) 
			begin
				x=$random;
				y=$random;
				zx=1;nx=0;zy=1;ny=0;f=1;no=0;check();// 0
				zx=1;nx=1;zy=1;ny=1;f=1;no=1;check();// 1
				zx=1;nx=1;zy=1;ny=0;f=1;no=0;check();// -1
				zx=0;nx=0;zy=1;ny=1;f=0;no=0;check();// x
				zx=1;nx=1;zy=0;ny=0;f=0;no=0;check();// y
				zx=0;nx=0;zy=1;ny=1;f=0;no=1;check();// !x
				zx=1;nx=1;zy=0;ny=0;f=0;no=1;check();// !y
				zx=0;nx=0;zy=1;ny=1;f=1;no=1;check();// -x
				zx=1;nx=1;zy=0;ny=0;f=1;no=1;check();// -y
				zx=0;nx=1;zy=1;ny=1;f=1;no=1;check();// x+1
				zx=1;nx=1;zy=0;ny=1;f=1;no=1;check();// y+1
				zx=0;nx=0;zy=1;ny=1;f=1;no=0;check();// x-1
				zx=1;nx=1;zy=0;ny=0;f=1;no=0;check();// y-1
				zx=0;nx=0;zy=0;ny=0;f=1;no=0;check();// x+y
				zx=0;nx=1;zy=0;ny=0;f=1;no=1;check();// x-y
				zx=0;nx=0;zy=0;ny=1;f=1;no=1;check();// y-x
				zx=0;nx=0;zy=0;ny=0;f=0;no=0;check();// x&y
				zx=0;nx=1;zy=0;ny=1;f=0;no=1;check();// x|y
			end
		
		if (fail==0) $display("passed");
		$display("------------------------");
		$finish;
	end

endmodule

02_Boolean_Arithmetic/05_ALU/_build/default/ALU_tb.vcd
$date
	Sun Apr 19 00:24:51 2026
$end
$version
	Icarus Verilog
$end
$timescale
	1ps
$end
$scope module ALU_tb $end
$var wire 1 ! zr_cmp $end
$var wire 1 " zr $end
$var wire 16 # yy [15:0] $end
$var wire 16 $ xx [15:0] $end
$var wire 16 % out_cmp [15:0] $end
$var wire 16 & out [15:0] $end
$var wire 1 ' ng_cmp $end
$var wire 1 ( ng $end
$var reg 1 ) f $end
$var reg 1 * fail $end
$var reg 16 + n [15:0] $end
$var reg 1 , no $end
$var reg 1 - nx $end
$var reg 1 . ny $end
$var reg 16 / x [15:0] $end
$var reg 16 0 y [15:0] $end
$var reg 1 1 zx $end
$var reg 1 2 zy $end
$scope module ALU $end
$var wire 1 ) f $end
$var wire 1 , no $end
$var wire 1 - nx $end
$var wire 1 . ny $end
$var wire 16 3 out [15:0] $end
$var wire 16 4 x [15:0] $end
$var wire 16 5 y [15:0] $end
$var wire 1 1 zx $end
$var wire 1 2 zy $end
$var wire 1 " zr $end
$var wire 16 6 y2 [15:0] $end
$var wire 16 7 y1 [15:0] $end
$var wire 16 8 x2 [15:0] $end
$var wire 16 9 x1 [15:0] $end
$var wire 16 : out_f [15:0] $end
$var wire 16 ; out1 [15:0] $end
$var wire 1 ( ng $end
$upscope $end
$scope task check $end
$upscope $end
$upscope $end
$enddefinitions $end
$comment Show the parameter values. $end
$dumpall
$end
#0
$dumpvars
b0 ;
b0 :
b0 9
b0 8
b0 7
b0 6
b101111010000001 5
b11010100100100 4
b0 3
12
11
b101111010000001 0
b11010100100100 /
0.
0-
0,
b0 +
0*
1)
0(
0'
b0 &
b0 %
b0 $
b0 #
1"
1!
$end
#1
0(
0'
0!
b1111111111111110 :
b1 %
0"
b1 &
b1 3
b1 ;
b1111111111111111 #
b1111111111111111 6
b1111111111111111 $
b1111111111111111 8
1,
1.
1-
#2
1(
1'
b1111111111111111 :
b1111111111111111 %
b1111111111111111 &
b1111111111111111 3
b1111111111111111 ;
b0 #
b0 6
0,
0.
#3
0(
0'
0!
b11010100100100 %
0"
b11010100100100 &
b11010100100100 3
b11010100100100 ;
b11010100100100 :
b1111111111111111 #
b1111111111111111 6
b11010100100100 $
b11010100100100 8
b11010100100100 9
0)
1.
0-
01
#4
b101111010000001 %
b101111010000001 &
b101111010000001 3
b101111010000001 ;
b101111010000001 :
b101111010000001 #
b101111010000001 6
b101111010000001 7
b1111111111111111 $
b1111111111111111 8
b0 9
0.
02
1-
11
#5
b11010100100100 :
1(
1'
b1100101011011011 %
b1100101011011011 &
b1100101011011011 3
b1100101011011011 ;
b1111111111111111 #
b1111111111111111 6
b0 7
b11010100100100 $
b11010100100100 8
b11010100100100 9
1,
1.
12
0-
01
#6
b1010000101111110 %
b1010000101111110 &
b1010000101111110 3
b1010000101111110 ;
b101111010000001 :
b101111010000001 #
b101111010000001 6
b101111010000001 7
b1111111111111111 $
b1111111111111111 8
b0 9
0.
02
1-
11
#7
1(
1'
b1100101011011100 &
b1100101011011100 3
b1100101011011100 ;
b1100101011011100 %
b11010100100011 :
b1111111111111111 #
b1111111111111111 6
b0 7
b11010100100100 $
b11010100100100 8
b11010100100100 9
1)
1.
12
0-
01
#8
b1010000101111111 %
b1010000101111111 &
b1010000101111111 3
b1010000101111111 ;
b101111010000000 :
b101111010000001 #
b101111010000001 6
b101111010000001 7
b1111111111111111 $
b1111111111111111 8
b0 9
0.
02
1-
11
#9
0(
0'
b11010100100101 %
b11010100100101 &
b11010100100101 3
b11010100100101 ;
b1100101011011011 8
b1100101011011010 :
b1100101011011011 $
b1111111111111111 #
b1111111111111111 6
b0 7
b11010100100100 9
1.
12
01
#10
b101111010000010 &
b101111010000010 3
b101111010000010 ;
b101111010000010 %
b1010000101111101 :
b1010000101111110 6
b1111111111111111 8
b1010000101111110 #
b1111111111111111 $
b101111010000001 7
b0 9
02
11
#11
b1111111111111111 6
0(
0'
b1111111111111111 #
b11010100100011 :
b11010100100011 %
b11010100100011 &
b11010100100011 3
b11010100100011 ;
b0 7
b11010100100100 $
b11010100100100 8
b11010100100100 9
0,
12
0-
01
#12
b101111010000000 %
b101111010000000 &
b101111010000000 3
b101111010000000 ;
b101111010000000 :
b101111010000001 #
b101111010000001 6
b101111010000001 7
b1111111111111111 $
b1111111111111111 8
b0 9
0.
02
1-
11
#13
1(
1'
b1001001110100101 %
b1001001110100101 &
b1001001110100101 3
b1001001110100101 ;
b1001001110100101 :
b11010100100100 $
b11010100100100 8
b11010100100100 9
0-
01
#14
1(
1'
b10100101011100 :
b1101011010100011 %
b1101011010100011 &
b1101011010100011 3
b1101011010100011 ;
b1100101011011011 $
b1100101011011011 8
1,
1-
#15
0(
0'
b10100101011101 %
b10100101011101 &
b10100101011101 3
b10100101011101 ;
b1101011010100010 :
b1010000101111110 #
b1010000101111110 6
b11010100100100 $
b11010100100100 8
1.
0-
#16
b1010000000000 %
b1010000000000 &
b1010000000000 3
b1010000000000 ;
b1010000000000 :
b101111010000001 #
b101111010000001 6
0,
0)
0.
#17
b1000000001011010 :
0(
0'
b111111110100101 %
b111111110100101 &
b111111110100101 3
b111111110100101 ;
b1010000101111110 #
b1010000101111110 6
b1100101011011011 $
b1100101011011011 8
1,
1.
1-
#18
1!
b0 %
1"
b0 &
b0 3
b0 ;
b0 :
b0 #
b0 6
b0 $
b0 8
b0 7
b0 9
0,
1)
0.
12
0-
11
b101011001100011 0
b101011001100011 5
b1101011000001001 /
b1101011000001001 4
b1 +
#19
0(
0'
0!
b1111111111111110 :
b1 %
0"
b1 &
b1 3
b1 ;
b1111111111111111 #
b1111111111111111 6
b1111111111111111 $
b1111111111111111 8
1,
1.
1-
#20
1(
1'
b1111111111111111 :
b1111111111111111 %
b1111111111111111 &
b1111111111111111 3
b1111111111111111 ;
b0 #
b0 6
0,
0.
#21
1(
1'
0!
b1101011000001001 %
0"
b1101011000001001 &
b1101011000001001 3
b1101011000001001 ;
b1101011000001001 :
b1111111111111111 #
b1111111111111111 6
b1101011000001001 $
b1101011000001001 8
b1101011000001001 9
0)
1.
0-
01
#22
0(
0'
b101011001100011 %
b101011001100011 &
b101011001100011 3
b101011001100011 ;
b101011001100011 :
b101011001100011 #
b101011001100011 6
b101011001100011 7
b1111111111111111 $
b1111111111111111 8
b0 9
0.
02
1-
11
#23
b1101011000001001 :
0(
0'
b10100111110110 %
b10100111110110 &
b10100111110110 3
b10100111110110 ;
b1111111111111111 #
b1111111111111111 6
b0 7
b1101011000001001 $
b1101011000001001 8
b1101011000001001 9
1,
1.
12
0-
01
#24
1(
1'
b1010100110011100 %
b1010100110011100 &
b1010100110011100 3
b1010100110011100 ;
b101011001100011 :
b101011001100011 #
b101011001100011 6
b101011001100011 7
b1111111111111111 $
b1111111111111111 8
b0 9
0.
02
1-
11
#25
0(
0'
b10100111110111 &
b10100111110111 3
b10100111110111 ;
b10100111110111 %
b1101011000001000 :
b1111111111111111 #
b1111111111111111 6
b0 7
b1101011000001001 $
b1101011000001001 8
b1101011000001001 9
1)
1.
12
0-
01
#26
1(
1'
b1010100110011101 %
b1010100110011101 &
b1010100110011101 3
b1010100110011101 ;
b101011001100010 :
b101011001100011 #
b101011001100011 6
b101011001100011 7
b1111111111111111 $
b1111111111111111 8
b0 9
0.
02
1-
11
#27
1(
1'
b1101011000001010 %
b1101011000001010 &
b1101011000001010 3
b1101011000001010 ;
b10100111110110 8
b10100111110101 :
b10100111110110 $
b1111111111111111 #
b1111111111111111 6
b0 7
b1101011000001001 9
1.
12
01
#28
0(
0'
b101011001100100 &
b101011001100100 3
b101011001100100 ;
b101011001100100 %
b1010100110011011 :
b1010100110011100 6
b1111111111111111 8
b1010100110011100 #
b1111111111111111 $
b101011001100011 7
b0 9
02
11
#29
b1111111111111111 6
1(
1'
b1111111111111111 #
b1101011000001000 :
b1101011000001000 %
b1101011000001000 &
b1101011000001000 3
b1101011000001000 ;
b0 7
b1101011000001001 $
b1101011000001001 8
b1101011000001001 9
0,
12
0-
01
#30
0(
0'
b101011001100010 %
b101011001100010 &
b101011001100010 3
b101011001100010 ;
b101011001100010 :
b101011001100011 #
b101011001100011 6
b101011001100011 7
b1111111111111111 $
b1111111111111111 8
b0 9
0.
02
1-
11
#31
b10110001101100 %
b10110001101100 &
b10110001101100 3
b10110001101100 ;
b10110001101100 :
b1101011000001001 $
b1101011000001001 8
b1101011000001001 9
0-
01
#32
0(
0'
b1000000001011001 :
b111111110100110 %
b111111110100110 &
b111111110100110 3
b111111110100110 ;
b10100111110110 $
b10100111110110 8
1,
1-
#33
1(
1'
b1000000001011010 %
b1000000001011010 &
b1000000001011010 3
b1000000001011010 ;
b111111110100101 :
b1010100110011100 #
b1010100110011100 6
b1101011000001001 $
b1101011000001001 8
1.
0-
#34
0(
0'
b101011000000001 %
b101011000000001 &
b101011000000001 3
b101011000000001 ;
b101011000000001 :
b101011001100011 #
b101011001100011 6
0,
0)
0.
#35
b10100110010100 :
1(
1'
b1101011001101011 %
b1101011001101011 &
b1101011001101011 3
b1101011001101011 ;
b1010100110011100 #
b1010100110011100 6
b10100111110110 $
b10100111110110 8
1,
1.
1-
#36
0(
0'
1!
b0 %
1"
b0 &
b0 3
b0 ;
b0 :
b0 #
b0 6
b0 $
b0 8
b0 7
b0 9
0,
1)
0.
12
0-
11
b1001100110001101 0
b1001100110001101 5
b111101100001101 /
b111101100001101 4
b10 +
#37
0(
0'
0!
b1111111111111110 :
b1 %
0"
b1 &
b1 3
b1 ;
b1111111111111111 #
b1111111111111111 6
b1111111111111111 $
b1111111111111111 8
1,
1.
1-
#38
1(
1'
b1111111111111111 :
b1111111111111111 %
b1111111111111111 &
b1111111111111111 3
b1111111111111111 ;
b0 #
b0 6
0,
0.
#39
0(
0'
0!
b111101100001101 %
0"
b111101100001101 &
b111101100001101 3
b111101100001101 ;
b111101100001101 :
b1111111111111111 #
b1111111111111111 6
b111101100001101 $
b111101100001101 8
b111101100001101 9
0)
1.
0-
01
#40
1(
1'
b1001100110001101 %
b1001100110001101 &
b1001100110001101 3
b1001100110001101 ;
b1001100110001101 :
b1001100110001101 #
b1001100110001101 6
b1001100110001101 7
b1111111111111111 $
b1111111111111111 8
b0 9
0.
02
1-
11
#41
b111101100001101 :
1(
1'
b1000010011110010 %
b1000010011110010 &
b1000010011110010 3
b1000010011110010 ;
b1111111111111111 #
b1111111111111111 6
b0 7
b111101100001101 $
b111101100001101 8
b111101100001101 9
1,
1.
12
0-
01
#42
0(
0'
b110011001110010 %
b110011001110010 &
b110011001110010 3
b110011001110010 ;
b1001100110001101 :
b1001100110001101 #
b1001100110001101 6
b1001100110001101 7
b1111111111111111 $
b1111111111111111 8
b0 9
0.
02
1-
11
#43
1(
1'
b1000010011110011 &
b1000010011110011 3
b1000010011110011 ;
b1000010011110011 %
b111101100001100 :
b1111111111111111 #
b1111111111111111 6
b0 7
b111101100001101 $
b111101100001101 8
b111101100001101 9
1)
1.
12
0-
01
#44
0(
0'
b110011001110011 %
b110011001110011 &
b110011001110011 3
b110011001110011 ;
b1001100110001100 :
b1001100110001101 #
b1001100110001101 6
b1001100110001101 7
b1111111111111111 $
b1111111111111111 8
b0 9
0.
02
1-
11
#45
0(
0'
b111101100001110 %
b111101100001110 &
b111101100001110 3
b111101100001110 ;
b1000010011110010 8
b1000010011110001 :
b1000010011110010 $
b1111111111111111 #
b1111111111111111 6
b0 7
b111101100001101 9
1.
12
01
#46
1(
1'
b1001100110001110 &
b1001100110001110 3
b1001100110001110 ;
b1001100110001110 %
b110011001110001 :
b110011001110010 6
b1111111111111111 8
b110011001110010 #
b1111111111111111 $
b1001100110001101 7
b0 9
02
11
#47
b1111111111111111 6
0(
0'
b1111111111111111 #
b111101100001100 :
b111101100001100 %
b111101100001100 &
b111101100001100 3
b111101100001100 ;
b0 7
b111101100001101 $
b111101100001101 8
b111101100001101 9
0,
12
0-
01
#48
1(
1'
b1001100110001100 %
b1001100110001100 &
b1001100110001100 3
b1001100110001100 ;
b1001100110001100 :
b1001100110001101 #
b1001100110001101 6
b1001100110001101 7
b1111111111111111 $
b1111111111111111 8
b0 9
0.
02
1-
11
#49
0(
0'
b1010010011010 %
b1010010011010 &
b1010010011010 3
b1010010011010 ;
b1010010011010 :
b111101100001101 $
b111101100001101 8
b111101100001101 9
0-
01
#50
1(
1'
b1111001111111 :
b1110000110000000 %
b1110000110000000 &
b1110000110000000 3
b1110000110000000 ;
b1000010011110010 $
b1000010011110010 8
1,
1-
#51
0(
0'
b1111010000000 %
b1111010000000 &
b1111010000000 3
b1111010000000 ;
b1110000101111111 :
b110011001110010 #
b110011001110010 6
b111101100001101 $
b111101100001101 8
1.
0-
#52
b1100100001101 %
b1100100001101 &
b1100100001101 3
b1100100001101 ;
b1100100001101 :
b1001100110001101 #
b1001100110001101 6
0,
0)
0.
#53
b10001110010 :
1(
1'
b1111101110001101 %
b1111101110001101 &
b1111101110001101 3
b1111101110001101 ;
b110011001110010 #
b110011001110010 6
b1000010011110010 $
b1000010011110010 8
1,
1.
1-
#54
0(
0'
1!
b0 %
1"
b0 &
b0 3
b0 ;
b0 :
b0 #
b0 6
b0 $
b0 8
b0 7
b0 9
0,
1)
0.
12
0-
11
b101001000010010 0
b101001000010010 5
b1000010001100101 /
b1000010001100101 4
b11 +
#55
0(
0'
0!
b1111111111111110 :
b1 %
0"
b1 &
b1 3
b1 ;
b1111111111111111 #
b1111111111111111 6
b1111111111111111 $
b1111111111111111 8
1,
1.
1-
#56
1(
1'
b1111111111111111 :
b1111111111111111 %
b1111111111111111 &
b1111111111111111 3
b1111111111111111 ;
b0 #
b0 6
0,
0.
#57
1(
1'
0!
b1000010001100101 %
0"
b1000010001100101 &
b1000010001100101 3
b1000010001100101 ;
b1000010001100101 :
b1111111111111111 #
b1111111111111111 6
b1000010001100101 $
b1000010001100101 8
b1000010001100101 9
0)
1.
0-
01
#58
0(
0'
b101001000010010 %
b101001000010010 &
b101001000010010 3
b101001000010010 ;
b101001000010010 :
b101001000010010 #
b101001000010010 6
b101001000010010 7
b1111111111111111 $
b1111111111111111 8
b0 9
0.
02
1-
11
#59
b1000010001100101 :
0(
0'
b111101110011010 %
b111101110011010 &
b111101110011010 3
b111101110011010 ;
b1111111111111111 #
b1111111111111111 6
b0 7
b1000010001100101 $
b1000010001100101 8
b1000010001100101 9
1,
1.
12
0-
01
#60
1(
1'
b1010110111101101 %
b1010110111101101 &
b1010110111101101 3
b1010110111101101 ;
b101001000010010 :
b101001000010010 #
b101001000010010 6
b101001000010010 7
b1111111111111111 $
b1111111111111111 8
b0 9
0.
02
1-
11
#61
0(
0'
b111101110011011 &
b111101110011011 3
b111101110011011 ;
b111101110011011 %
b1000010001100100 :
b1111111111111111 #
b1111111111111111 6
b0 7
b1000010001100101 $
b1000010001100101 8
b1000010001100101 9
1)
1.
12
0-
01
#62
1(
1'
b1010110111101110 %
b1010110111101110 &
b1010110111101110 3
b1010110111101110 ;
b101001000010001 :
b101001000010010 #
b101001000010010 6
b101001000010010 7
b1111111111111111 $
b1111111111111111 8
b0 9
0.
02
1-
11
#63
1(
1'
b1000010001100110 %
b1000010001100110 &
b1000010001100110 3
b1000010001100110 ;
b111101110011010 8
b111101110011001 :
b111101110011010 $
b1111111111111111 #
b1111111111111111 6
b0 7
b1000010001100101 9
1.
12
01
#64
0(
0'
b101001000010011 &
b101001000010011 3
b101001000010011 ;
b101001000010011 %
b1010110111101100 :
b1010110111101101 6
b1111111111111111 8
b1010110111101101 #
b1111111111111111 $
b101001000010010 7
b0 9
02
11
#65
b1111111111111111 6
1(
1'
b1111111111111111 #
b1000010001100100 :
b1000010001100100 %
b1000010001100100 &
b1000010001100100 3
b1000010001100100 ;
b0 7
b1000010001100101 $
b1000010001100101 8
b1000010001100101 9
0,
12
0-
01
#66
0(
0'
b101001000010001 %
b101001000010001 &
b101001000010001 3
b101001000010001 ;
b101001000010001 :
b101001000010010 #
b101001000010010 6
b101001000010010 7
b1111111111111111 $
b1111111111111111 8
b0 9
0.
02
1-
11
#67
1(
1'
b1101011001110111 %
b1101011001110111 &
b1101011001110111 3
b1101011001110111 ;
b1101011001110111 :
b1000010001100101 $
b1000010001100101 8
b1000010001100101 9
0-
01
#68
0(
0'
b1100110110101100 :
b11001001010011 %
b11001001010011 &
b11001001010011 3
b11001001010011 ;
b111101110011010 $
b111101110011010 8
1,
1-
#69
1(
1'
b1100110110101101 %
b1100110110101101 &
b1100110110101101 3
b1100110110101101 ;
b11001001010010 :
b1010110111101101 #
b1010110111101101 6
b1000010001100101 $
b1000010001100101 8
1.
0-
#70
0(
0'
1!
1"
b0 %
b0 &
b0 3
b0 ;
b0 :
b101001000010010 #
b101001000010010 6
0,
0)
0.
#71
b10100110001000 :
1(
1'
0!
b1101011001110111 %
0"
b1101011001110111 &
b1101011001110111 3
b1101011001110111 ;
b1010110111101101 #
b1010110111101101 6
b111101110011010 $
b111101110011010 8
1,
1.
1-
#72
0(
0'
1!
b0 %
1"
b0 &
b0 3
b0 ;
b0 :
b0 #
b0 6
b0 $
b0 8
b0 7
b0 9
0,
1)
0.
12
0-
11
b1100110100001101 0
b1100110100001101 5
b1110001100000001 /
b1110001100000001 4
b100 +
#73
0(
0'
0!
b1111111111111110 :
b1 %
0"
b1 &
b1 3
b1 ;
b1111111111111111 #
b1111111111111111 6
b1111111111111111 $
b1111111111111111 8
1,
1.
1-
#74
1(
1'
b1111111111111111 :
b1111111111111111 %
b1111111111111111 &
b1111111111111111 3
b1111111111111111 ;
b0 #
b0 6
0,
0.
#75
1(
1'
0!
b1110001100000001 %
0"
b1110001100000001 &
b1110001100000001 3
b1110001100000001 ;
b1110001100000001 :
b1111111111111111 #
b1111111111111111 6
b1110001100000001 $
b1110001100000001 8
b1110001100000001 9
0)
1.
0-
01
#76
1(
1'
b1100110100001101 %
b1100110100001101 &
b1100110100001101 3
b1100110100001101 ;
b1100110100001101 :
b1100110100001101 #
b1100110100001101 6
b1100110100001101 7
b1111111111111111 $
b1111111111111111 8
b0 9
0.
02
1-
11
#77
b1110001100000001 :
0(
0'
b1110011111110 %
b1110011111110 &
b1110011111110 3
b1110011111110 ;
b1111111111111111 #
b1111111111111111 6
b0 7
b1110001100000001 $
b1110001100000001 8
b1110001100000001 9
1,
1.
12
0-
01
#78
0(
0'
b11001011110010 %
b11001011110010 &
b11001011110010 3
b11001011110010 ;
b1100110100001101 :
b1100110100001101 #
b1100110100001101 6
b1100110100001101 7
b1111111111111111 $
b1111111111111111 8
b0 9
0.
02
1-
11
#79
0(
0'
b1110011111111 &
b1110011111111 3
b1110011111111 ;
b1110011111111 %
b1110001100000000 :
b1111111111111111 #
b1111111111111111 6
b0 7
b1110001100000001 $
b1110001100000001 8
b1110001100000001 9
1)
1.
12
0-
01
#80
b11001011110011 %
b11001011110011 &
b11001011110011 3
b11001011110011 ;
b1100110100001100 :
b1100110100001101 #
b1100110100001101 6
b1100110100001101 7
b1111111111111111 $
b1111111111111111 8
b0 9
0.
02
1-
11
#81
1(
1'
b1110001100000010 %
b1110001100000010 &
b1110001100000010 3
b1110001100000010 ;
b1110011111110 8
b1110011111101 :
b1110011111110 $
b1111111111111111 #
b1111111111111111 6
b0 7
b1110001100000001 9
1.
12
01
#82
b1100110100001110 &
b1100110100001110 3
b1100110100001110 ;
b1100110100001110 %
b11001011110001 :
b11001011110010 6
b1111111111111111 8
b11001011110010 #
b1111111111111111 $
b1100110100001101 7
b0 9
02
11
#83
b1111111111111111 6
1(
1'
b1111111111111111 #
b1110001100000000 :
b1110001100000000 %
b1110001100000000 &
b1110001100000000 3
b1110001100000000 ;
b0 7
b1110001100000001 $
b1110001100000001 8
b1110001100000001 9
0,
12
0-
01
#84
b1100110100001100 %
b1100110100001100 &
b1100110100001100 3
b1100110100001100 ;
b1100110100001100 :
b1100110100001101 #
b1100110100001101 6
b1100110100001101 7
b1111111111111111 $
b1111111111111111 8
b0 9
0.
02
1-
11
#85
b1011000000001110 %
b1011000000001110 &
b1011000000001110 3
b1011000000001110 ;
b1011000000001110 :
b1110001100000001 $
b1110001100000001 8
b1110001100000001 9
0-
01
#86
0(
0'
b1110101000001011 :
b1010111110100 %
b1010111110100 &
b1010111110100 3
b1010111110100 ;
b1110011111110 $
b1110011111110 8
1,
1-
#87
1(
1'
b1110101000001100 %
b1110101000001100 &
b1110101000001100 3
b1110101000001100 ;
b1010111110011 :
b11001011110010 #
b11001011110010 6
b1110001100000001 $
b1110001100000001 8
1.
0-
#88
1(
1'
b1100000100000001 %
b1100000100000001 &
b1100000100000001 3
b1100000100000001 ;
b1100000100000001 :
b1100110100001101 #
b1100110100001101 6
0,
0)
0.
#89
b1000011110010 :
1(
1'
b1110111100001101 %
b1110111100001101 &
b1110111100001101 3
b1110111100001101 ;
b11001011110010 #
b11001011110010 6
b1110011111110 $
b1110011111110 8
1,
1.
1-
#90
0(
0'
1!
b0 %
1"
b0 &
b0 3
b0 ;
b0 :
b0 #
b0 6
b0 $
b0 8
b0 7
b0 9
0,
1)
0.
12
0-
11
b1100110100111101 0
b1100110100111101 5
b1111000101110110 /
b1111000101110110 4
b101 +
#91
0(
0'
0!
b1111111111111110 :
b1 %
0"
b1 &
b1 3
b1 ;
b1111111111111111 #
b1111111111111111 6
b1111111111111111 $
b1111111111111111 8
1,
1.
1-
#92
1(
1'
b1111111111111111 :
b1111111111111111 %
b1111111111111111 &
b1111111111111111 3
b1111111111111111 ;
b0 #
b0 6
0,
0.
#93
1(
1'
0!
b1111000101110110 %
0"
b1111000101110110 &
b1111000101110110 3
b1111000101110110 ;
b1111000101110110 :
b1111111111111111 #
b1111111111111111 6
b1111000101110110 $
b1111000101110110 8
b1111000101110110 9
0)
1.
0-
01
#94
1(
1'
b1100110100111101 %
b1100110100111101 &
b1100110100111101 3
b1100110100111101 ;
b1100110100111101 :
b1100110100111101 #
b1100110100111101 6
b1100110100111101 7
b1111111111111111 $
b1111111111111111 8
b0 9
0.
02
1-
11
#95
b1111000101110110 :
0(
0'
b111010001001 %
b111010001001 &
b111010001001 3
b111010001001 ;
b1111111111111111 #
b1111111111111111 6
b0 7
b1111000101110110 $
b1111000101110110 8
b1111000101110110 9
1,
1.
12
0-
01
#96
0(
0'
b11001011000010 %
b11001011000010 &
b11001011000010 3
b11001011000010 ;
b1100110100111101 :
b1100110100111101 #
b1100110100111101 6
b1100110100111101 7
b1111111111111111 $
b1111111111111111 8
b0 9
0.
02
1-
11
#97
0(
0'
b111010001010 &
b111010001010 3
b111010001010 ;
b111010001010 %
b1111000101110101 :
b1111111111111111 #
b1111111111111111 6
b0 7
b1111000101110110 $
b1111000101110110 8
b1111000101110110 9
1)
1.
12
0-
01
#98
b11001011000011 %
b11001011000011 &
b11001011000011 3
b11001011000011 ;
b1100110100111100 :
b1100110100111101 #
b1100110100111101 6
b1100110100111101 7
b1111111111111111 $
b1111111111111111 8
b0 9
0.
02
1-
11
#99
1(
1'
b1111000101110111 %
b1111000101110111 &
b1111000101110111 3
b1111000101110111 ;
b111010001001 8
b111010001000 :
b111010001001 $
b1111111111111111 #
b1111111111111111 6
b0 7
b1111000101110110 9
1.
12
01
#100
b1100110100111110 &
b1100110100111110 3
b1100110100111110 ;
b1100110100111110 %
b11001011000001 :
b11001011000010 6
b1111111111111111 8
b11001011000010 #
b1111111111111111 $
b1100110100111101 7
b0 9
02
11
#101
b1111111111111111 6
1(
1'
b1111111111111111 #
b1111000101110101 :
b1111000101110101 %
b1111000101110101 &
b1111000101110101 3
b1111000101110101 ;
b0 7
b1111000101110110 $
b1111000101110110 8
b1111000101110110 9
0,
12
0-
01
#102
b1100110100111100 %
b1100110100111100 &
b1100110100111100 3
b1100110100111100 ;
b1100110100111100 :
b1100110100111101 #
b1100110100111101 6
b1100110100111101 7
b1111111111111111 $
b1111111111111111 8
b0 9
0.
02
1-
11
#103
b1011111010110011 %
b1011111010110011 &
b1011111010110011 3
b1011111010110011 ;
b1011111010110011 :
b1111000101110110 $
b1111000101110110 8
b1111000101110110 9
0-
01
#104
0(
0'
b1101101111000110 :
b10010000111001 %
b10010000111001 &
b10010000111001 3
b10010000111001 ;
b111010001001 $
b111010001001 8
1,
1-
#105
1(
1'
b1101101111000111 %
b1101101111000111 &
b1101101111000111 3
b1101101111000111 ;
b10010000111000 :
b11001011000010 #
b11001011000010 6
b1111000101110110 $
b1111000101110110 8
1.
0-
#106
1(
1'
b1100000100110100 %
b1100000100110100 &
b1100000100110100 3
b1100000100110100 ;
b1100000100110100 :
b1100110100111101 #
b1100110100111101 6
0,
0)
0.
#107
b1010000000 :
1(
1'
b1111110101111111 %
b1111110101111111 &
b1111110101111111 3
b1111110101111111 ;
b11001011000010 #
b11001011000010 6
b111010001001 $
b111010001001 8
1,
1.
1-
#108
0(
0'
1!
b0 %
1"
b0 &
b0 3
b0 ;
b0 :
b0 #
b0 6
b0 $
b0 8
b0 7
b0 9
0,
1)
0.
12
0-
11
b1111011110001100 0
b1111011110001100 5
b101011111101101 /
b101011111101101 4
b110 +
