02_Boolean_Arithmetic/Inc16.v
/**
 * 16-bit incrementer:
 * out = in + 1 (arithmetic addition)
 */

`default_nettype none
module Inc16(
	input [15:0] in,
	output [15:0] out
);

    // First try
    /**
	wire carry0 = in[0] & 1'b1;
	wire carry1 = in[1] & carry0;
	wire carry2 = in[2] & carry1;
	wire carry3 = in[3] & carry2;
	wire carry4 = in[4] & carry3;
	wire carry5 = in[5] & carry4;
	wire carry6 = in[6] & carry5;
	wire carry7 = in[7] & carry6;
	wire carry8 = in[8] & carry7;
	wire carry9 = in[9] & carry8;
	wire carry10 = in[10] & carry9;
	wire carry11 = in[11] & carry10;
	wire carry12 = in[12] & carry11;
	wire carry13 = in[13] & carry12;
	wire carry14 = in[14] & carry13;

	assign out[0] = in[0] ^ 1'b1;
	assign out[1] = in[1] ^ carry0;
	assign out[2] = in[2] ^ carry1;
	assign out[3] = in[3] ^ carry2;
	assign out[4] = in[4] ^ carry3;
	assign out[5] = in[5] ^ carry4;
	assign out[6] = in[6] ^ carry5;
	assign out[7] = in[7] ^ carry6;
	assign out[8] = in[8] ^ carry7;
	assign out[9] = in[9] ^ carry8;
	assign out[10] = in[10] ^ carry9;
	assign out[11] = in[11] ^ carry10;
	assign out[12] = in[12] ^ carry11;
	assign out[13] = in[13] ^ carry12;
	assign out[14] = in[14] ^ carry13;
	assign out[15] = in[15] ^ carry14;

	**/

	// Second Try : im getting the hand of this (@@), i also feel like this is impacting my ability to think modularly

	/** Add16 inc(in,16'b1,out); **/

	// Lets try to copy that AI cheat
	assign out = in + 1'b1 ;

	// side note : works like magic innit (TT)

endmodule

02_Boolean_Arithmetic/04_Inc16/Inc16_tb.v
`default_nettype none
module Inc16_tb();

	// IN,OUT
	reg [15:0] in;
	wire [15:0] out;

	// Part
	Inc16 INC16(
		.in(in),
		.out(out)
	);

	// Compare
	wire [15:0] out_cmp;
	assign out_cmp = in+1;
	
	reg fail = 0;
	reg [15:0] n=0;
	task check;
		#1
		if (out != out_cmp) 
			begin
				$display("FAIL: in=%16b, out=%16b",in,out);
				fail=1;
			end
	endtask
	  
	// Test
  	initial begin
  		$dumpvars(0, Inc16_tb);
		
		$display("------------------------");
		$display("Testbench: Inc16");

		in=0;check();
		in=16'b1111111111111111;check();
		
		for (n=0; n<1000;n=n+1) 
			begin
				in=$random;
				check();
			end
		
		if (fail==0) $display("passed");
		$display("------------------------");
		$finish;
	end

endmodule

02_Boolean_Arithmetic/04_Inc16/_build/default/Inc16_tb.vcd
$date
	Sun Apr 19 00:19:04 2026
$end
$version
	Icarus Verilog
$end
$timescale
	1ps
$end
$scope module Inc16_tb $end
$var wire 16 ! out_cmp [15:0] $end
$var wire 16 " out [15:0] $end
$var reg 1 # fail $end
$var reg 16 $ in [15:0] $end
$var reg 16 % n [15:0] $end
$scope module INC16 $end
$var wire 16 & in [15:0] $end
$var wire 16 ' out [15:0] $end
$upscope $end
$scope task check $end
$upscope $end
$upscope $end
$enddefinitions $end
$comment Show the parameter values. $end
$dumpall
$end
#0
$dumpvars
b1 '
b0 &
b0 %
b0 $
0#
b1 "
b1 !
$end
#1
b0 !
b0 "
b0 '
b1111111111111111 $
b1111111111111111 &
#2
b11010100100101 !
b11010100100101 "
b11010100100101 '
b11010100100100 $
b11010100100100 &
#3
b101111010000010 !
b101111010000010 "
b101111010000010 '
b101111010000001 $
b101111010000001 &
b1 %
#4
b1101011000001010 !
b1101011000001010 "
b1101011000001010 '
b1101011000001001 $
b1101011000001001 &
b10 %
#5
b101011001100100 !
b101011001100100 "
b101011001100100 '
b101011001100011 $
b101011001100011 &
b11 %
#6
b111101100001110 !
b111101100001110 "
b111101100001110 '
b111101100001101 $
b111101100001101 &
b100 %
#7
b1001100110001110 !
b1001100110001110 "
b1001100110001110 '
b1001100110001101 $
b1001100110001101 &
b101 %
#8
b1000010001100110 !
b1000010001100110 "
b1000010001100110 '
b1000010001100101 $
b1000010001100101 &
b110 %
#9
b101001000010011 !
b101001000010011 "
b101001000010011 '
b101001000010010 $
b101001000010010 &
b111 %
#10
b1110001100000010 !
b1110001100000010 "
b1110001100000010 '
b1110001100000001 $
b1110001100000001 &
b1000 %
#11
b1100110100001110 !
b1100110100001110 "
b1100110100001110 '
b1100110100001101 $
b1100110100001101 &
b1001 %
#12
b1111000101110111 !
b1111000101110111 "
b1111000101110111 '
b1111000101110110 $
b1111000101110110 &
b1010 %
#13
b1100110100111110 !
b1100110100111110 "
b1100110100111110 '
b1100110100111101 $
b1100110100111101 &
b1011 %
#14
b101011111101110 !
b101011111101110 "
b101011111101110 '
b101011111101101 $
b101011111101101 &
b1100 %
#15
b1111011110001101 !
b1111011110001101 "
b1111011110001101 '
b1111011110001100 $
b1111011110001100 &
b1101 %
#16
b1110100111111010 !
b1110100111111010 "
b1110100111111010 '
b1110100111111001 $
b1110100111111001 &
b1110 %
#17
b10010011000111 !
b10010011000111 "
b10010011000111 '
b10010011000110 $
b10010011000110 &
b1111 %
#18
b1000010011000110 !
b1000010011000110 "
b1000010011000110 '
b1000010011000101 $
b1000010011000101 &
b10000 %
#19
b1101001010101011 !
b1101001010101011 "
b1101001010101011 '
b1101001010101010 $
b1101001010101010 &
b10001 %
#20
b1111011111100110 !
b1111011111100110 "
b1111011111100110 '
b1111011111100101 $
b1111011111100101 &
b10010 %
#21
b111001001111000 !
b111001001111000 "
b111001001111000 '
b111001001110111 $
b111001001110111 &
b10011 %
#22
b1101011000010011 !
b1101011000010011 "
b1101011000010011 '
b1101011000010010 $
b1101011000010010 &
b10100 %
#23
b1101101110010000 !
b1101101110010000 "
b1101101110010000 '
b1101101110001111 $
b1101101110001111 &
b10101 %
#24
b110100111110011 !
b110100111110011 "
b110100111110011 '
b110100111110010 $
b110100111110010 &
b10110 %
#25
b1001011011001111 !
b1001011011001111 "
b1001011011001111 '
b1001011011001110 $
b1001011011001110 &
b10111 %
#26
b111101011101001 !
b111101011101001 "
b111101011101001 '
b111101011101000 $
b111101011101000 &
b11000 %
#27
b100111011000110 !
b100111011000110 "
b100111011000110 '
b100111011000101 $
b100111011000101 &
b11001 %
#28
b100100101011101 !
b100100101011101 "
b100100101011101 '
b100100101011100 $
b100100101011100 &
b11010 %
#29
b10100010111110 !
b10100010111110 "
b10100010111110 '
b10100010111101 $
b10100010111101 &
b11011 %
#30
b101100000101110 !
b101100000101110 "
b101100000101110 '
b101100000101101 $
b101100000101101 &
b11100 %
#31
b10011001100110 !
b10011001100110 "
b10011001100110 '
b10011001100101 $
b10011001100101 &
b11101 %
#32
b110001001100100 !
b110001001100100 "
b110001001100100 '
b110001001100011 $
b110001001100011 &
b11110 %
#33
b1000011100001011 !
b1000011100001011 "
b1000011100001011 '
b1000011100001010 $
b1000011100001010 &
b11111 %
#34
b10001010000001 !
b10001010000001 "
b10001010000001 '
b10001010000000 $
b10001010000000 &
b100000 %
#35
b10000100100001 !
b10000100100001 "
b10000100100001 '
b10000100100000 $
b10000100100000 &
b100001 %
#36
b100010110101011 !
b100010110101011 "
b100010110101011 '
b100010110101010 $
b100010110101010 &
b100010 %
#37
b1100110010011110 !
b1100110010011110 "
b1100110010011110 '
b1100110010011101 $
b1100110010011101 &
b100011 %
#38
b11111010010111 !
b11111010010111 "
b11111010010111 '
b11111010010110 $
b11111010010110 &
b100100 %
#39
b1011100000010100 !
b1011100000010100 "
b1011100000010100 '
b1011100000010011 $
b1011100000010011 &
b100101 %
#40
b11100000001110 !
b11100000001110 "
b11100000001110 '
b11100000001101 $
b11100000001101 &
b100110 %
#41
b1101011001010100 !
b1101011001010100 "
b1101011001010100 '
b1101011001010011 $
b1101011001010011 &
b100111 %
#42
b1101110101101100 !
b1101110101101100 "
b1101110101101100 '
b1101110101101011 $
b1101110101101011 &
b101000 %
#43
b10101011010110 !
b10101011010110 "
b10101011010110 '
b10101011010101 $
b10101011010101 &
b101001 %
#44
b100101000000011 !
b100101000000011 "
b100101000000011 '
b100101000000010 $
b100101000000010 &
b101010 %
#45
b11111010101111 !
b11111010101111 "
b11111010101111 '
b11111010101110 $
b11111010101110 &
b101011 %
#46
b1110100100011110 !
b1110100100011110 "
b1110100100011110 '
b1110100100011101 $
b1110100100011101 &
b101100 %
#47
b111001011010000 !
b111001011010000 "
b111001011010000 '
b111001011001111 $
b111001011001111 &
b101101 %
#48
b100100100100100 !
b100100100100100 "
b100100100100100 '
b100100100100011 $
b100100100100011 &
b101110 %
#49
b110010100001011 !
b110010100001011 "
b110010100001011 '
b110010100001010 $
b110010100001010 &
b101111 %
#50
b101011001011 !
b101011001011 "
b101011001011 '
b101011001010 $
b101011001010 &
b110000 %
#51
b100110000111101 !
b100110000111101 "
b100110000111101 '
b100110000111100 $
b100110000111100 &
b110001 %
#52
b1011110111110011 !
b1011110111110011 "
b1011110111110011 '
b1011110111110010 $
b1011110111110010 &
b110010 %
#53
b110000110001011 !
b110000110001011 "
b110000110001011 '
b110000110001010 $
b110000110001010 &
b110011 %
#54
b1011001101000010 !
b1011001101000010 "
b1011001101000010 '
b1011001101000001 $
b1011001101000001 &
b110100 %
#55
b11010011011001 !
b11010011011001 "
b11010011011001 '
b11010011011000 $
b11010011011000 &
b110101 %
#56
b1111001101111001 !
b1111001101111001 "
b1111001101111001 '
b1111001101111000 $
b1111001101111000 &
b110110 %
#57
b1001010001010 !
b1001010001010 "
b1001010001010 '
b1001010001001 $
b1001010001001 &
b110111 %
#58
b110111101100 !
b110111101100 "
b110111101100 '
b110111101011 $
b110111101011 &
b111000 %
#59
b110010110110111 !
b110010110110111 "
b110010110110111 '
b110010110110110 $
b110010110110110 &
b111001 %
#60
b1111100111000111 !
b1111100111000111 "
b1111100111000111 '
b1111100111000110 $
b1111100111000110 &
b111010 %
#61
b1001110101111 !
b1001110101111 "
b1001110101111 '
b1001110101110 $
b1001110101110 &
b111011 %
#62
b1010111101 !
b1010111101 "
b1010111101 '
b1010111100 $
b1010111100 &
b111100 %
#63
b1101110100101011 !
b1101110100101011 "
b1101110100101011 '
b1101110100101010 $
b1101110100101010 &
b111101 %
#64
b1001101000001100 !
b1001101000001100 "
b1001101000001100 '
b1001101000001011 $
b1001101000001011 &
b111110 %
#65
b1011111001110010 !
b1011111001110010 "
b1011111001110010 '
b1011111001110001 $
b1011111001110001 &
b111111 %
#66
b100000110000110 !
b100000110000110 "
b100000110000110 '
b100000110000101 $
b100000110000101 &
b1000000 %
#67
b101010101010000 !
b101010101010000 "
b101010101010000 '
b101010101001111 $
b101010101001111 &
b1000001 %
#68
b110000000111100 !
b110000000111100 "
b110000000111100 '
b110000000111011 $
b110000000111011 &
b1000010 %
#69
b11001100111011 !
b11001100111011 "
b11001100111011 '
b11001100111010 $
b11001100111010 &
b1000011 %
#70
b11001001111111 !
b11001001111111 "
b11001001111111 '
b11001001111110 $
b11001001111110 &
b1000100 %
#71
b100101100010110 !
b100101100010110 "
b100101100010110 '
b100101100010101 $
b100101100010101 &
b1000101 %
#72
b1001101111110010 !
b1001101111110010 "
b1001101111110010 '
b1001101111110001 $
b1001101111110001 &
b1000110 %
#73
b100101111011010 !
b100101111011010 "
b100101111011010 '
b100101111011001 $
b100101111011001 &
b1000111 %
#74
b11101100011 !
b11101100011 "
b11101100011 '
b11101100010 $
b11101100010 &
b1001000 %
#75
b1111101101001101 !
b1111101101001101 "
b1111101101001101 '
b1111101101001100 $
b1111101101001100 &
b1001001 %
#76
b101010110100000 !
b101010110100000 "
b101010110100000 '
b101010110011111 $
b101010110011111 &
b1001010 %
#77
b1010000110010000 !
b1010000110010000 "
b1010000110010000 '
b1010000110001111 $
b1010000110001111 &
b1001011 %
#78
b1010100111111001 !
b1010100111111001 "
b1010100111111001 '
b1010100111111000 $
b1010100111111000 &
b1001100 %
#79
b110000010111000 !
b110000010111000 "
b110000010111000 '
b110000010110111 $
b110000010110111 &
b1001101 %
#80
b101011010100000 !
b101011010100000 "
b101011010100000 '
b101011010011111 $
b101011010011111 &
b1001110 %
#81
b1001010001011101 !
b1001010001011101 "
b1001010001011101 '
b1001010001011100 $
b1001010001011100 &
b1001111 %
#82
b1100000001011100 !
b1100000001011100 "
b1100000001011100 '
b1100000001011011 $
b1100000001011011 &
b1010000 %
#83
b11011110001010 !
b11011110001010 "
b11011110001010 '
b11011110001001 $
b11011110001001 &
b1010001 %
#84
b11001001001010 !
b11001001001010 "
b11001001001010 '
b11001001001001 $
b11001001001001 &
b1010010 %
#85
b11111011010001 !
b11111011010001 "
b11111011010001 '
b11111011010000 $
b11111011010000 &
b1010011 %
#86
b1100000011011000 !
b1100000011011000 "
b1100000011011000 '
b1100000011010111 $
b1100000011010111 &
b1010100 %
#87
b1111110001010010 !
b1111110001010010 "
b1111110001010010 '
b1111110001010001 $
b1111110001010001 &
b1010101 %
#88
b10111110010111 !
b10111110010111 "
b10111110010111 '
b10111110010110 $
b10111110010110 &
b1010110 %
#89
b111111100001101 !
b111111100001101 "
b111111100001101 '
b111111100001100 $
b111111100001100 &
b1010111 %
#90
b1100111011000011 !
b1100111011000011 "
b1100111011000011 '
b1100111011000010 $
b1100111011000010 &
b1011000 %
#91
b1110110111001001 !
b1110110111001001 "
b1110110111001001 '
b1110110111001000 $
b1110110111001000 &
b1011001 %
#92
b101101001111000 !
b101101001111000 "
b101101001111000 '
b101101001110111 $
b101101001110111 &
b1011010 %
#93
b1110110100111110 !
b1110110100111110 "
b1110110100111110 '
b1110110100111101 $
b1110110100111101 &
b1011011 %
#94
b1101101100010011 !
b1101101100010011 "
b1101101100010011 '
b1101101100010010 $
b1101101100010010 &
b1011100 %
#95
b1111111 !
b1111111 "
b1111111 '
b1111110 $
b1111110 &
b1011101 %
#96
b1000000101101110 !
b1000000101101110 "
b1000000101101110 '
b1000000101101101 $
b1000000101101101 &
b1011110 %
#97
b1110011100111010 !
b1110011100111010 "
b1110011100111010 '
b1110011100111001 $
b1110011100111001 &
b1011111 %
#98
b1000111100100000 !
b1000111100100000 "
b1000111100100000 '
b1000111100011111 $
b1000111100011111 &
b1100000 %
#99
b1111011011010100 !
b1111011011010100 "
b1111011011010100 '
b1111011011010011 $
b1111011011010011 &
b1100001 %
#100
b10111110000110 !
b10111110000110 "
b10111110000110 '
b10111110000101 $
b10111110000101 &
b1100010 %
#101
b1000100001111001 !
b1000100001111001 "
b1000100001111001 '
b1000100001111000 $
b1000100001111000 &
b1100011 %
#102
b101100101011100 !
b101100101011100 "
b101100101011100 '
b101100101011011 $
b101100101011011 &
b1100100 %
#103
b100101101001010 !
b100101101001010 "
b100101101001010 '
b100101101001001 $
b100101101001001 &
b1100101 %
#104
b1010111001000000 !
b1010111001000000 "
b1010111001000000 '
b1010111000111111 $
b1010111000111111 &
b1100110 %
#105
b1010111100101011 !
b1010111100101011 "
b1010111100101011 '
b1010111100101010 $
b1010111100101010 &
b1100111 %
#106
b110001101011001 !
b110001101011001 "
b110001101011001 '
b110001101011000 $
b110001101011000 &
b1101000 %
#107
b11100010000111 !
b11100010000111 "
b11100010000111 '
b11100010000110 $
b11100010000110 &
b1101001 %
#108
b110010001111 !
b110010001111 "
b110010001111 '
b110010001110 $
b110010001110 &
b1101010 %
#109
b1111001010011101 !
b1111001010011101 "
b1111001010011101 '
b1111001010011100 $
b1111001010011100 &
b1101011 %
#110
b1001100111111011 !
b1001100111111011 "
b1001100111111011 '
b1001100111111010 $
b1001100111111010 &
b1101100 %
#111
b1011110000100111 !
b1011110000100111 "
b1011110000100111 '
b1011110000100110 $
b1011110000100110 &
b1101101 %
#112
b1011101110100 !
b1011101110100 "
b1011101110100 '
b1011101110011 $
b1011101110011 &
b1101110 %
#113
b1011010010100100 !
b1011010010100100 "
b1011010010100100 '
b1011010010100011 $
b1011010010100011 &
b1101111 %
#114
b1010100000110000 !
b1010100000110000 "
b1010100000110000 '
b1010100000101111 $
b1010100000101111 &
b1110000 %
#115
b1001001010110100 !
b1001001010110100 "
b1001001010110100 '
b1001001010110011 $
b1001001010110011 &
b1110001 %
#116
b101011001100000 !
b101011001100000 "
b101011001100000 '
b101011001011111 $
b101011001011111 &
b1110010 %
#117
b110101000101 !
b110101000101 "
b110101000101 '
b110101000100 $
b110101000100 &
b1110011 %
#118
b1111110111111000 !
b1111110111111000 "
b1111110111111000 '
b1111110111110111 $
b1111110111110111 &
b1110100 %
#119
b11011011001100 !
b11011011001100 "
b11011011001100 '
b11011011001011 $
b11011011001011 &
b1110101 %
#120
b1101011100111 !
b1101011100111 "
b1101011100111 '
b1101011100110 $
b1101011100110 &
b1110110 %
#121
b1101101101011011 !
b1101101101011011 "
b1101101101011011 '
b1101101101011010 $
b1101101101011010 &
b1110111 %
#122
b1100000100101010 !
b1100000100101010 "
b1100000100101010 '
b1100000100101001 $
b1100000100101001 &
b1111000 %
#123
b1110001011101110 !
b1110001011101110 "
b1110001011101110 '
b1110001011101101 $
b1110001011101101 &
b1111001 %
#124
b110110011011011 !
b110110011011011 "
b110110011011011 '
b110110011011010 $
b110110011011010 &
b1111010 %
#125
b1011011001100110 !
b1011011001100110 "
b1011011001100110 '
b1011011001100101 $
b1011011001100101 &
b1111011 %
#126
b1110001010110110 !
b1110001010110110 "
b1110001010110110 '
b1110001010110101 $
b1110001010110101 &
b1111100 %
#127
b1001010011100000 !
b1001010011100000 "
b1001010011100000 '
b1001010011011111 $
b1001010011011111 &
b1111101 %
#128
b1100101111010 !
b1100101111010 "
b1100101111010 '
b1100101111001 $
b1100101111001 &
b1111110 %
#129
b1111111101000101 !
b1111111101000101 "
b1111111101000101 '
b1111111101000100 $
b1111111101000100 &
b1111111 %
#130
b110011010001 !
b110011010001 "
b110011010001 '
b110011010000 $
b110011010000 &
b10000000 %
#131
b101100101011 !
b101100101011 "
b101100101011 '
b101100101010 $
b101100101010 &
b10000001 %
#132
b1010110110101100 !
b1010110110101100 "
b1010110110101100 '
b1010110110101011 $
b1010110110101011 &
b10000010 %
#133
b1100111100001111 !
b1100111100001111 "
b1100111100001111 '
b1100111100001110 $
b1100111100001110 &
b10000011 %
#134
b1010110111011101 !
b1010110111011101 "
b1010110111011101 '
b1010110111011100 $
b1010110111011100 &
b10000100 %
#135
b1011110010011011 !
b1011110010011011 "
b1011110010011011 '
b1011110010011010 $
b1011110010011010 &
b10000101 %
#136
b111001011111110 !
b111001011111110 "
b111001011111110 '
b111001011111101 $
b111001011111101 &
b10000110 %
#137
b1011000100 !
b1011000100 "
b1011000100 '
b1011000011 $
b1011000011 &
b10000111 %
#138
b1110110101010111 !
b1110110101010111 "
b1110110101010111 '
b1110110101010110 $
b1110110101010110 &
b10001000 %
#139
b1110100101001111 !
b1110100101001111 "
b1110100101001111 '
b1110100101001110 $
b1110100101001110 &
b10001001 %
#140
b111011001101000 !
b111011001101000 "
b111011001101000 '
b111011001100111 $
b111011001100111 &
b10001010 %
#141
b11010000001011 !
b11010000001011 "
b11010000001011 '
b11010000001010 $
b11010000001010 &
b10001011 %
#142
b1011100110110111 !
b1011100110110111 "
b1011100110110111 '
b1011100110110110 $
b1011100110110110 &
b10001100 %
#143
b1000101000111001 !
b1000101000111001 "
b1000101000111001 '
b1000101000111000 $
b1000101000111000 &
b10001101 %
#144
b1000011101111010 !
b1000011101111010 "
b1000011101111010 '
b1000011101111001 $
b1000011101111001 &
b10001110 %
#145
b1100010010111001 !
b1100010010111001 "
b1100010010111001 '
b1100010010111000 $
b1100010010111000 &
b10001111 %
#146
b1011111110010101 !
b1011111110010101 "
b1011111110010101 '
b1011111110010100 $
b1011111110010100 &
b10010000 %
#147
b101110110010100 !
b101110110010100 "
b101110110010100 '
b101110110010011 $
b101110110010011 &
b10010001 %
#148
b10110000000101 !
b10110000000101 "
b10110000000101 '
b10110000000100 $
b10110000000100 &
b10010010 %
#149
b1100101001011010 !
b1100101001011010 "
b1100101001011010 '
b1100101001011001 $
b1100101001011001 &
b10010011 %
#150
b110100111011100 !
b110100111011100 "
b110100111011100 '
b110100111011011 $
b110100111011011 &
b10010100 %
#151
b1101111001001110 !
b1101111001001110 "
b1101111001001110 '
b1101111001001101 $
b1101111001001101 &
b10010101 %
#152
b1011011111011010 !
b1011011111011010 "
b1011011111011010 '
b1011011111011001 $
b1011011111011001 &
b10010110 %
#153
b10011001101110 !
b10011001101110 "
b10011001101110 '
b10011001101101 $
b10011001101101 &
b10010111 %
#154
b1110001001110111 !
b1110001001110111 "
b1110001001110111 '
b1110001001110110 $
b1110001001110110 &
b10011000 %
#155
b100100111001011 !
b100100111001011 "
b100100111001011 '
b100100111001010 $
b100100111001010 &
b10011001 %
#156
b10110110110111 !
b10110110110111 "
b10110110110111 '
b10110110110110 $
b10110110110110 &
b10011010 %
#157
b111000110010110 !
b111000110010110 "
b111000110010110 '
b111000110010101 $
b111000110010101 &
b10011011 %
#158
b1101001000111 !
b1101001000111 "
b1101001000111 '
b1101001000110 $
b1101001000110 &
b10011100 %
#159
b1001101100000101 !
b1001101100000101 "
b1001101100000101 '
b1001101100000100 $
b1001101100000100 &
b10011101 %
#160
b110000111111000 !
b110000111111000 "
b110000111111000 '
b110000111110111 $
b110000111110111 &
b10011110 %
#161
b11101101010 !
b11101101010 "
b11101101010 '
b11101101001 $
b11101101001 &
b10011111 %
#162
b1011101010110101 !
b1011101010110101 "
b1011101010110101 '
b1011101010110100 $
b1011101010110100 &
b10100000 %
#163
b1000110110001001 !
b1000110110001001 "
b1000110110001001 '
b1000110110001000 $
b1000110110001000 &
b10100001 %
#164
b1101100100101001 !
b1101100100101001 "
b1101100100101001 '
b1101100100101000 $
b1101100100101000 &
b10100010 %
#165
b10000101110 !
b10000101110 "
b10000101110 '
b10000101101 $
b10000101101 &
b10100011 %
#166
b11000011001000 !
b11000011001000 "
b11000011001000 '
b11000011000111 $
b11000011000111 &
b10100100 %
#167
b1001110000101111 !
b1001110000101111 "
b1001110000101111 '
b1001110000101110 $
b1001110000101110 &
b10100101 %
#168
b1110010000001001 !
b1110010000001001 "
b1110010000001001 '
b1110010000001000 $
b1110010000001000 &
b10100110 %
#169
b100010100011101 !
b100010100011101 "
b100010100011101 '
b100010100011100 $
b100010100011100 &
b10100111 %
#170
b1010011011111110 !
b1010011011111110 "
b1010011011111110 '
b1010011011111101 $
b1010011011111101 &
b10101000 %
#171
b11100101010 !
b11100101010 "
b11100101010 '
b11100101001 $
b11100101001 &
b10101001 %
#172
b1001000000011101 !
b1001000000011101 "
b1001000000011101 '
b1001000000011100 $
b1001000000011100 &
b10101010 %
#173
b110011110000111 !
b110011110000111 "
b110011110000111 '
b110011110000110 $
b110011110000110 &
b10101011 %
#174
b100011011011 !
b100011011011 "
b100011011011 '
b100011011010 $
b100011011010 &
b10101100 %
#175
b1100011000111110 !
b1100011000111110 "
b1100011000111110 '
b1100011000111101 $
b1100011000111101 &
b10101101 %
#176
b1010011101100111 !
b1010011101100111 "
b1010011101100111 '
b1010011101100110 $
b1010011101100110 &
b10101110 %
#177
b1100010001110001 !
b1100010001110001 "
b1100010001110001 '
b1100010001110000 $
b1100010001110000 &
b10101111 %
#178
b10001110100 !
b10001110100 "
b10001110100 '
b10001110011 $
b10001110011 &
b10110000 %
#179
b1001100110111011 !
b1001100110111011 "
b1001100110111011 '
b1001100110111010 $
b1001100110111010 &
b10110001 %
#180
b1011001101011111 !
b1011001101011111 "
b1011001101011111 '
b1011001101011110 $
b1011001101011110 &
b10110010 %
#181
b111100111111011 !
b111100111111011 "
b111100111111011 '
b111100111111010 $
b111100111111010 &
b10110011 %
#182
b10111010110 !
b10111010110 "
b10111010110 '
b10111010101 $
b10111010101 &
b10110100 %
#183
b1111011000011011 !
b1111011000011011 "
b1111011000011011 '
b1111011000011010 $
b1111011000011010 &
b10110101 %
#184
b10111010 !
b10111010 "
b10111010 '
b10111001 $
b10111001 &
b10110110 %
#185
b110000100111000 !
b110000100111000 "
b110000100111000 '
b110000100110111 $
b110000100110111 &
b10110111 %
#186
b11011110010111 !
b11011110010111 "
b11011110010111 '
b11011110010110 $
b11011110010110 &
b10111000 %
#187
b10000111000001 !
b10000111000001 "
b10000111000001 '
b10000111000000 $
b10000111000000 &
b10111001 %
#188
b1001111100100111 !
b1001111100100111 "
b1001111100100111 '
b1001111100100110 $
b1001111100100110 &
b10111010 %
#189
b1101010110111 !
b1101010110111 "
b1101010110111 '
b1101010110110 $
b1101010110110 &
b10111011 %
#190
b1000001101111110 !
b1000001101111110 "
b1000001101111110 '
b1000001101111101 $
b1000001101111101 &
b10111100 %
#191
b111111011101 !
b111111011101 "
b111111011101 '
b111111011100 $
b111111011100 &
b10111101 %
#192
b101011110000111 !
b101011110000111 "
b101011110000111 '
b101011110000110 $
b101011110000110 &
b10111110 %
#193
b1111111101111001 !
b1111111101111001 "
b1111111101111001 '
b1111111101111000 $
b1111111101111000 &
b10111111 %
#194
b1001101101111111 !
b1001101101111111 "
b1001101101111111 '
b1001101101111110 $
b1001101101111110 &
b11000000 %
#195
b1000000011011100 !
b1000000011011100 "
b1000000011011100 '
b1000000011011011 $
b1000000011011011 &
b11000001 %
#196
b1011011011010000 !
b1011011011010000 "
b1011011011010000 '
b1011011011001111 $
b1011011011001111 &
b11000010 %
#197
b10101101111010 !
b10101101111010 "
b10101101111010 '
b10101101111001 $
b10101101111001 &
b11000011 %
#198
b1110010011111011 !
b1110010011111011 "
b1110010011111011 '
b1110010011111010 $
b1110010011111010 &
b11000100 %
#199
b1110111001100010 !
b1110111001100010 "
b1110111001100010 '
b1110111001100001 $
b1110111001100001 &
b11000101 %
#200
b100100011000 !
b100100011000 "
b100100011000 '
b100100010111 $
b100100010111 &
b11000110 %
#201
b111100010100010 !
b111100010100010 "
b111100010100010 '
b111100010100001 $
b111100010100001 &
b11000111 %
#202
b1001000110000111 !
b1001000110000111 "
b1001000110000111 '
b1001000110000110 $
b1001000110000110 &
b11001000 %
#203
b1001011001010001 !
b1001011001010001 "
b1001011001010001 '
b1001011001010000 $
b1001011001010000 &
b11001001 %
#204
b101100111110110 !
b101100111110110 "
b101100111110110 '
b101100111110101 $
b101100111110101 &
b11001010 %
#205
b1000100000110110 !
b1000100000110110 "
b1000100000110110 '
b1000100000110101 $
b1000100000110101 &
b11001011 %
#206
b1000101000101010 !
b1000101000101010 "
b1000101000101010 '
b1000101000101001 $
b1000101000101001 &
b11001100 %
#207
b111010111000010 !
b111010111000010 "
b111010111000010 '
b111010111000001 $
b111010111000001 &
b11001101 %
#208
b111010011000110 !
b111010011000110 "
b111010011000110 '
b111010011000101 $
b111010011000101 &
b11001110 %
#209
b1011010010011001 !
b1011010010011001 "
b1011010010011001 '
b1011010010011000 $
b1011010010011000 &
b11001111 %
#210
b111101101001100 !
b111101101001100 "
b111101101001100 '
b111101101001011 $
b111101101001011 &
b11010000 %
#211
b100001001110100 !
b100001001110100 "
b100001001110100 '
b100001001110011 $
b100001001110011 &
b11010001 %
#212
b1110011011101101 !
b1110011011101101 "
b1110011011101101 '
b1110011011101100 $
b1110011011101100 &
b11010010 %
#213
b1011010001011 !
b1011010001011 "
b1011010001011 '
b1011010001010 $
b1011010001010 &
b11010011 %
#214
b1101000101001111 !
b1101000101001111 "
b1101000101001111 '
b1101000101001110 $
b1101000101001110 &
b11010100 %
#215
b1000000010101001 !
b1000000010101001 "
b1000000010101001 '
b1000000010101000 $
b1000000010101000 &
b11010101 %
#216
b1111110110101010 !
b1111110110101010 "
b1111110110101010 '
b1111110110101001 $
b1111110110101001 &
b11010110 %
#217
b1000110010100010 !
b1000110010100010 "
b1000110010100010 '
b1000110010100001 $
b1000110010100001 &
b11010111 %
#218
b1011100100001111 !
b1011100100001111 "
b1011100100001111 '
b1011100100001110 $
b1011100100001110 &
b11011000 %
#219
b110011011100111 !
b110011011100111 "
b110011011100111 '
b110011011100110 $
b110011011100110 &
b11011001 %
#220
b1100000010100000 !
b1100000010100000 "
b1100000010100000 '
b1100000010011111 $
b1100000010011111 &
b11011010 %
#221
b1011010100101011 !
b1011010100101011 "
b1011010100101011 '
b1011010100101010 $
b1011010100101010 &
b11011011 %
#222
b1110100101011 !
b1110100101011 "
b1110100101011 '
b1110100101010 $
b1110100101010 &
b11011100 %
#223
b1111010010001110 !
b1111010010001110 "
b1111010010001110 '
b1111010010001101 $
b1111010010001101 &
b11011101 %
#224
b1111111110011111 !
b1111111110011111 "
b1111111110011111 '
b1111111110011110 $
b1111111110011110 &
b11011110 %
#225
b1110011000111001 !
b1110011000111001 "
b1110011000111001 '
b1110011000111000 $
b1110011000111000 &
b11011111 %
#226
b1010100001111010 !
b1010100001111010 "
b1010100001111010 '
b1010100001111001 $
b1010100001111001 &
b11100000 %
#227
b1110001111001001 !
b1110001111001001 "
b1110001111001001 '
b1110001111001000 $
b1110001111001000 &
b11100001 %
#228
b100010111001011 !
b100010111001011 "
b100010111001011 '
b100010111001010 $
b100010111001010 &
b11100010 %
#229
b100000100010100 !
b100000100010100 "
b100000100010100 '
b100000100010011 $
b100000100010011 &
b11100011 %
#230
b1100100101101100 !
b1100100101101100 "
b1100100101101100 '
b1100100101101011 $
b1100100101101011 &
b11100100 %
#231
b1010111011001000 !
b1010111011001000 "
b1010111011001000 '
b1010111011000111 $
b1010111011000111 &
b11100101 %
#232
b1101110110110111 !
b1101110110110111 "
b1101110110110111 '
b1101110110110110 $
b1101110110110110 &
b11100110 %
#233
b1001110110111011 !
b1001110110111011 "
b1001110110111011 '
b1001110110111010 $
b1001110110111010 &
b11100111 %
#234
b1010101111000101 !
b1010101111000101 "
b1010101111000101 '
b1010101111000100 $
b1010101111000100 &
b11101000 %
#235
b1001010110111010 !
b1001010110111010 "
b1001010110111010 '
b1001010110111001 $
b1001010110111001 &
b11101001 %
#236
b1101001110010011 !
b1101001110010011 "
b1101001110010011 '
b1101001110010010 $
b1101001110010010 &
b11101010 %
