01_Boolean_Logic/And.v
/**
 * And gate: 
 * out = 1 if (a == 1 and b == 1)
 *       0 otherwise
 */

`default_nettype none
module And(
  input a,
  input b,
  output out
);

  assign out = a & b;

endmodule

01_Boolean_Logic/And16.v
/**
 * 16-bit bitwise And:
 * for i = 0..15: assign out[i] = (a[i] and b[i])
 */

`default_nettype none
module And16(
  input [15:0] a,
  input [15:0] b,
  output [15:0] out
);

  // Old way od doing it
  // assign out[0] = a[0] & b[0];
  // assign out[1] = a[1] & b[1];
  // assign out[2] = a[2] & b[2];
  // assign out[3] = a[3] & b[3];
  // assign out[4] = a[4] & b[4];
  // assign out[5] = a[5] & b[5];
  // assign out[6] = a[6] & b[6];
  // assign out[7] = a[7] & b[7];
  // assign out[8] = a[8] & b[8];
  // assign out[9] = a[9] & b[9];
  // assign out[10] = a[10] & b[10];
  // assign out[11] = a[11] & b[11];
  // assign out[12] = a[12] & b[12];
  // assign out[13] = a[13] & b[13];
  // assign out[14] = a[14] & b[14];
  // assign out[15] = a[15] & b[15];


  // Modularized way of doing this shit
  genvar i;
  generate
    for(i =0; i < 16; i++) begin : gen_bit
      And and_inst(.a(a[i]),.b(b[i]),.out(out[i]));
    end
  endgenerate

endmodule

01_Boolean_Logic/10_And16/And16_tb.v
`default_nettype none
module And16_tb();
	
	// IN,OUT	
	reg [15:0] a,b;
	wire [15:0] out;

	// Part
	And16 AND16(
		.a(a),
		.b(b),
		.out(out)
	);
	
	// Compare
	wire [15:0] out_cmp;
	assign out_cmp = a&b;

	reg fail = 0;
	reg [15:0] n = 0;
	task check;
		#1
		if (out != out_cmp) 
			begin
				$display("FAIL: a=%16b, b=%16b, out=%16b",a,b,out);
				fail=1;
			end
	endtask
	  
	// Test
  	initial begin
  		$dumpvars(0, And16_tb);
		
		$display("------------------------");
		$display("Testbench: And16");
				
		for (n=0; n<10000;n=n+1) 
			begin
				a=$random;
				b=$random;
				check();
		
			end
		
		if (fail==0) $display("passed");
		$display("------------------------");
		$finish;
	end

endmodule

01_Boolean_Logic/10_And16/_build/default/And16_tb.vcd
$date
	Wed Aug  5 01:55:03 2026
$end
$version
	Icarus Verilog
$end
$timescale
	1ps
$end
$scope module And16_tb $end
$var wire 16 ! out_cmp [15:0] $end
$var wire 16 " out [15:0] $end
$var reg 16 # a [15:0] $end
$var reg 16 $ b [15:0] $end
$var reg 1 % fail $end
$var reg 16 & n [15:0] $end
$scope module AND16 $end
$var wire 16 ' a [15:0] $end
$var wire 16 ( b [15:0] $end
$var wire 16 ) out [15:0] $end
$scope begin gen_bit[0] $end
$var parameter 2 * i $end
$scope module and_inst $end
$var wire 1 + a $end
$var wire 1 , b $end
$var wire 1 - out $end
$upscope $end
$upscope $end
$scope begin gen_bit[1] $end
$var parameter 2 . i $end
$scope module and_inst $end
$var wire 1 / a $end
$var wire 1 0 b $end
$var wire 1 1 out $end
$upscope $end
$upscope $end
$scope begin gen_bit[2] $end
$var parameter 3 2 i $end
$scope module and_inst $end
$var wire 1 3 a $end
$var wire 1 4 b $end
$var wire 1 5 out $end
$upscope $end
$upscope $end
$scope begin gen_bit[3] $end
$var parameter 3 6 i $end
$scope module and_inst $end
$var wire 1 7 a $end
$var wire 1 8 b $end
$var wire 1 9 out $end
$upscope $end
$upscope $end
$scope begin gen_bit[4] $end
$var parameter 4 : i $end
$scope module and_inst $end
$var wire 1 ; a $end
$var wire 1 < b $end
$var wire 1 = out $end
$upscope $end
$upscope $end
$scope begin gen_bit[5] $end
$var parameter 4 > i $end
$scope module and_inst $end
$var wire 1 ? a $end
$var wire 1 @ b $end
$var wire 1 A out $end
$upscope $end
$upscope $end
$scope begin gen_bit[6] $end
$var parameter 4 B i $end
$scope module and_inst $end
$var wire 1 C a $end
$var wire 1 D b $end
$var wire 1 E out $end
$upscope $end
$upscope $end
$scope begin gen_bit[7] $end
$var parameter 4 F i $end
$scope module and_inst $end
$var wire 1 G a $end
$var wire 1 H b $end
$var wire 1 I out $end
$upscope $end
$upscope $end
$scope begin gen_bit[8] $end
$var parameter 5 J i $end
$scope module and_inst $end
$var wire 1 K a $end
$var wire 1 L b $end
$var wire 1 M out $end
$upscope $end
$upscope $end
$scope begin gen_bit[9] $end
$var parameter 5 N i $end
$scope module and_inst $end
$var wire 1 O a $end
$var wire 1 P b $end
$var wire 1 Q out $end
$upscope $end
$upscope $end
$scope begin gen_bit[10] $end
$var parameter 5 R i $end
$scope module and_inst $end
$var wire 1 S a $end
$var wire 1 T b $end
$var wire 1 U out $end
$upscope $end
$upscope $end
$scope begin gen_bit[11] $end
$var parameter 5 V i $end
$scope module and_inst $end
$var wire 1 W a $end
$var wire 1 X b $end
$var wire 1 Y out $end
$upscope $end
$upscope $end
$scope begin gen_bit[12] $end
$var parameter 5 Z i $end
$scope module and_inst $end
$var wire 1 [ a $end
$var wire 1 \ b $end
$var wire 1 ] out $end
$upscope $end
$upscope $end
$scope begin gen_bit[13] $end
$var parameter 5 ^ i $end
$scope module and_inst $end
$var wire 1 _ a $end
$var wire 1 ` b $end
$var wire 1 a out $end
$upscope $end
$upscope $end
$scope begin gen_bit[14] $end
$var parameter 5 b i $end
$scope module and_inst $end
$var wire 1 c a $end
$var wire 1 d b $end
$var wire 1 e out $end
$upscope $end
$upscope $end
$scope begin gen_bit[15] $end
$var parameter 5 f i $end
$scope module and_inst $end
$var wire 1 g a $end
$var wire 1 h b $end
$var wire 1 i out $end
$upscope $end
$upscope $end
$upscope $end
$scope task check $end
$upscope $end
$upscope $end
$enddefinitions $end
$comment Show the parameter values. $end
$dumpall
b1111 f
b1110 b
b1101 ^
b1100 Z
b1011 V
b1010 R
b1001 N
b1000 J
b111 F
b110 B
b101 >
b100 :
b11 6
b10 2
b1 .
b0 *
$end
#0
$dumpvars
0i
0h
0g
0e
1d
0c
0a
0`
1_
1]
1\
1[
0Y
1X
0W
1U
1T
1S
0Q
1P
0O
0M
0L
1K
0I
1H
0G
0E
0D
0C
0A
0@
1?
0=
0<
0;
09
08
07
05
04
13
01
00
0/
0-
1,
0+
b1010000000000 )
b101111010000001 (
b11010100100100 '
b0 &
0%
b101111010000001 $
b11010100100100 #
b1010000000000 "
b1010000000000 !
$end
#1
b101011000000001 "
b101011000000001 )
1-
1Q
1e
10
1@
1D
0H
0X
1+
03
17
0?
0K
1O
0_
1c
1g
b101011000000001 !
b101011001100011 $
b101011001100011 (
b1101011000001001 #
b1101011000001001 '
b1 &
#2
b1100100001101 "
b1100100001101 )
19
0Q
0e
15
1M
0U
1Y
00
14
18
0@
0D
1H
1L
0P
0T
1X
0d
1h
13
1K
0S
1W
1_
0g
b1100100001101 !
b1001100110001101 $
b1001100110001101 (
b111101100001101 #
b111101100001101 '
b10 &
#3
b0 "
b0 )
0-
05
09
0M
0Y
0]
0,
10
04
08
1<
0H
0L
1P
0X
1d
0h
07
1?
1C
0K
0O
1S
0W
0[
0_
0c
1g
b0 !
b101001000010010 $
b101001000010010 (
b1000010001100101 #
b1000010001100101 '
b11 &
#4
b1100000100000001 "
b1100000100000001 )
1-
1i
1M
1e
1,
00
14
18
0<
1L
0P
1T
1X
0\
1h
03
0?
0C
1K
1O
0S
1_
1c
b1100000100000001 !
b1100110100001101 $
b1100110100001101 (
b1110001100000001 #
b1110001100000001 '
b100 &
#5
b1100000100110100 "
b1100000100110100 )
0-
15
1=
1A
1<
1@
0+
1/
13
1;
1?
1C
0O
1[
b1100000100110100 !
b1100110100111101 $
b1100110100111101 (
b1111000101110110 #
b1111000101110110 '
b101 &
#6
b101011110001100 "
b101011110001100 )
0A
1]
19
0=
1I
1Q
1U
0i
0,
0<
0@
1H
1P
0X
1\
1`
1+
0/
17
0;
1G
1O
1S
0_
0g
b101011110001100 !
b1111011110001100 $
b1111011110001100 (
b101011111101101 #
b101011111101101 '
b110 &
#7
b10000011000000 "
b10000011000000 )
09
1E
0M
0e
05
0Q
0U
0]
1a
10
08
1D
0L
0P
0\
0d
0h
03
1;
0O
0S
1W
0[
1_
1g
b10000011000000 !
b10010011000110 $
b10010011000110 (
b1110100111111001 #
b1110100111111001 '
b111 &
#8
b1000000010000000 "
b1000000010000000 )
0E
1i
0a
04
18
1@
0D
1P
0T
1\
0`
1d
1h
13
07
0;
0?
0K
1S
0W
0_
0c
b1000000010000000 !
b1101001010101010 $
b1101001010101010 (
b1000010011000101 #
b1000010011000101 '
b1000 &
#9
b111001001100101 "
b111001001100101 )
1-
15
1E
0I
0i
1A
1Q
1]
1a
1e
1,
14
08
1<
1D
0H
1`
0h
1?
1K
1O
1[
1_
1c
b111001001100101 !
b111001001110111 $
b111001001110111 (
b1111011111100101 #
b1111011111100101 '
b1001 &
#10
b1101001000000010 "
b1101001000000010 )
1i
0-
11
05
0A
0E
0a
18
0<
0@
0D
1H
1L
1X
0`
1h
0+
1/
03
1;
0?
0C
0G
0K
0_
b1101001000000010 !
b1101101110001111 $
b1101101110001111 (
b1101011000010010 #
b1101011000010010 '
b1010 &
#11
b11000010 "
b11000010 )
0e
1E
1I
0Q
0]
0i
0,
1D
0L
1T
0X
0d
1?
1C
1G
1K
0O
0S
1W
0[
1_
0g
b11000010 !
b1001011011001110 $
b1001011011001110 (
b110100111110010 #
b110100111110010 '
b1011 &
#12
b100101011000000 "
b100101011000000 )
1Y
1e
01
1Q
1,
00
08
1X
0\
1d
0h
0/
17
0;
0K
1O
1[
b100101011000000 !
b100111011000101 $
b100111011000101 (
b111101011101000 #
b111101011101000 '
b1100 &
#13
b100000011100 "
b100000011100 )
19
0E
0e
15
1=
0I
0Q
18
1<
1@
0D
0P
0T
1`
0d
13
1;
0?
0G
1K
0O
0[
0_
b100000011100 !
b10100010111101 $
b10100010111101 (
b100100101011100 #
b100100101011100 '
b1101 &
#14
b100101 "
b100101 )
09
0Y
1-
0=
1A
08
0<
1D
0H
1P
1T
0X
1+
0;
1?
0C
0K
1[
b100101 !
b10011001100101 $
b10011001100101 (
b101100000101101 #
b101100000101101 '
b1110 &
#15
b1000000010 "
b1000000010 )
0-
0A
11
05
1Q
0,
10
04
18
0@
0D
1L
0`
1h
1/
03
07
1C
1O
0W
0[
1_
b1000000010 !
b1000011100001010 $
b1000011100001010 (
b110001001100011 #
b110001001100011 '
b1111 &
#16
b10000000000000 "
b10000000000000 )
0Q
1a
01
00
08
1@
0P
0T
1`
0h
0+
0/
0?
0C
1G
0c
b10000000000000 !
b10000100100000 $
b10000100100000 (
b10001010000000 #
b10001010000000 '
b10000 &
#17
b100010010001000 "
b100010010001000 )
1I
19
1U
0a
1e
1,
14
18
1<
0@
1H
0L
1T
1X
0`
1d
1h
1/
17
1?
1K
0O
1S
0_
1c
b100010010001000 !
b1100110010011101 $
b1100110010011101 (
b100010110101010 #
b100010110101010 '
b10001 &
#18
b11100000010010 "
b11100000010010 )
11
0I
0U
09
1=
1Y
1]
1a
0e
10
04
08
0H
0T
1\
1`
0d
13
07
1;
0?
0K
1O
1W
1[
1_
0c
b11100000010010 !
b1011100000010011 $
b1011100000010011 (
b11111010010110 #
b11111010010110 '
b10010 &
#19
b1000000000001 "
b1000000000001 )
0Y
0a
1-
01
0=
1D
1P
1T
0X
0`
1d
1+
0/
17
0;
0G
0O
0S
b1000000000001 !
b1101011001010011 $
b1101011001010011 (
b11100000001101 #
b11100000001101 '
b10011 &
#20
b100001000001 "
b100001000001 )
1Y
0]
1E
00
14
1H
0T
1X
0\
1`
0d
0h
1/
03
1?
1C
1K
1S
0_
1c
1g
b100001000001 !
b10101011010101 $
b10101011010101 (
b1101110101101011 #
b1101110101101011 '
b10100 &
#21
b101000000010 "
b101000000010 )
11
0-
0E
1Q
0,
10
18
0<
1@
0D
1T
1\
0+
07
0?
0C
0K
1O
0S
0[
0g
b101000000010 !
b11111010101110 $
b11111010101110 (
b100101000000010 #
b100101000000010 '
b10101 &
#22
b110000000001101 "
b110000000001101 )
0Y
1e
1-
01
15
19
0Q
1a
1,
0@
1D
0T
0X
1d
1+
0/
13
17
1;
1K
0O
1_
1g
b110000000001101 !
b111001011001111 $
b111001011001111 (
b1110100100011101 #
b1110100100011101 '
b10110 &
#23
b100000100000010 "
b100000100000010 )
0-
1M
11
05
09
0a
0,
04
0D
0H
1L
0P
1T
0\
1/
03
07
0;
1?
0_
0g
b100000100000010 !
b110010100001010 $
b110010100001010 (
b100100100100011 #
b100100100100011 '
b10111 &
#24
b100000001000 "
b100000001000 )
01
1Y
19
0M
0e
00
14
1<
1@
0L
1X
0`
0+
17
0?
1C
1G
0K
1O
0c
b100000001000 !
b100110000111100 $
b100110000111100 (
b101011001010 #
b101011001010 '
b11000 &
#25
b10000110000010 "
b10000110000010 )
11
1I
0Y
09
1M
1a
10
04
0<
0@
1H
1L
0T
0X
1`
07
1;
1?
1K
0O
1S
1[
1_
1g
b10000110000010 !
b110000110001010 $
b110000110001010 (
b1011110111110010 #
b1011110111110010 '
b11001 &
#26
b11000001000000 "
b11000001000000 )
1E
0M
1]
01
0I
00
1<
1D
0L
1T
1\
0d
1+
0/
0;
0?
0G
1O
0S
0W
b11000001000000 !
b11010011011000 $
b11010011011000 (
b1011001101000001 #
b1011001101000001 '
b11010 &
#27
b1001000001000 "
b1001000001000 )
0E
1Q
0a
19
1,
0<
0D
1P
0T
0`
0+
17
1;
1?
1c
b1001000001000 !
b1001010001001 $
b1001010001001 (
b1111001101111000 #
b1111001101111000 '
b11011 &
#28
b10110100010 "
b10110100010 )
09
1A
1M
11
1I
0Q
1U
0]
0,
10
14
08
1<
1@
1L
0P
1T
0\
1`
1d
1+
1/
0;
1G
0O
1S
1W
0[
0_
0c
0g
b10110100010 !
b110010110110110 $
b110010110110110 (
b110111101011 #
b110111101011 '
b11100 &
#29
b1000110000110 "
b1000110000110 )
15
0A
0U
1]
18
0<
1P
0T
1\
0`
0d
0+
13
07
0?
0S
1[
1_
1c
1g
b1000110000110 !
b1001110101110 $
b1001110101110 (
b1111100111000110 #
b1111100111000110 '
b11101 &
#30
b101000 "
b101000 )
05
0I
01
19
1A
0M
0]
04
0H
0P
1T
1X
1d
1h
0/
17
1;
1?
0C
0K
1O
0W
0[
0_
0c
0g
b101000 !
b1101110100101010 $
b1101110100101010 (
b1010111100 #
b1010111100 '
b11110 &
#31
b1001101000000001 "
b1001101000000001 )
09
1Q
1-
0A
1Y
1]
1i
1,
00
08
1<
1D
0L
1P
1`
0d
1+
1/
03
0;
0?
0G
1W
1[
1g
b1001101000000001 !
b1011111001110001 $
b1011111001110001 (
b1001101000001011 #
b1001101000001011 '
b11111 &
#32
b100000100000101 "
b100000100000101 )
15
1M
0Q
0Y
0]
1e
0i
10
14
18
0<
0@
1L
0P
0X
0`
1d
0h
0/
13
07
1G
1K
0O
0W
0[
1c
0g
b100000100000101 !
b101010101001111 $
b101010101001111 (
b100000110000101 #
b100000110000101 '
b100000 &
#33
b10000000111010 "
b10000000111010 )
0-
0e
11
05
19
1=
1A
0M
1a
0,
04
1<
1@
0D
1P
0T
1`
0d
1/
03
17
1;
1?
0G
0K
1_
b10000000111010 !
b11001100111010 $
b11001100111010 (
b110000000111011 #
b110000000111011 '
b100001 &
#34
b1000010100 "
b1000010100 )
01
09
0A
0a
15
1Q
1,
00
14
08
0@
1X
0\
0`
1d
0+
13
1C
1O
1[
0c
b1000010100 !
b100101100010101 $
b100101100010101 (
b11001001111110 #
b11001001111110 '
b100010 &
#35
b101111010001 "
b101111010001 )
1E
1-
05
1I
1M
1Y
04
18
1D
1H
1+
0/
03
07
1G
1K
1W
0_
1g
b101111010001 !
b100101111011001 $
b100101111011001 (
b1001101111110001 #
b1001101111110001 '
b100011 &
#36
b1101000000 "
b1101000000 )
0-
0=
0I
0Y
0,
14
0<
0H
1\
1`
1h
0+
1/
0;
0G
1S
0W
0[
0g
b1101000000 !
b1111101101001100 $
b1111101101001100 (
b11101100010 #
b11101100010 '
b100100 &
#37
b110001111 "
b110001111 )
11
1-
15
19
0E
1I
0Q
1,
10
0D
1H
0P
0X
0\
0d
1+
13
17
1;
0?
0C
1G
0O
1[
1c
b110001111 !
b1010000110001111 $
b1010000110001111 (
b101010110011111 #
b101010110011111 '
b100101 &
#38
b10000010110000 "
b10000010110000 )
09
1=
0M
0-
01
05
1A
1a
08
1<
1@
0L
1d
0h
0+
0/
03
1?
1C
0S
1W
0[
1_
0c
1g
b10000010110000 !
b110000010110111 $
b110000010110111 (
b1010100111111000 #
b1010100111111000 '
b100110 &
#39
b1010000011100 "
b1010000011100 )
19
0I
15
0A
1U
1]
0a
0,
00
18
0@
1D
0H
1T
1\
0`
0d
1h
1+
1/
13
0?
0C
0K
1O
1S
0W
1[
0_
1c
0g
b1010000011100 !
b1001010001011100 $
b1001010001011100 (
b101011010011111 #
b101011010011111 '
b100111 &
#40
b1001 "
b1001 )
1-
0=
05
0U
0]
1,
04
0<
0D
1H
1L
1P
1`
0h
03
1C
0G
0O
0S
0[
1g
b1001 !
b11011110001001 $
b11011110001001 (
b1100000001011011 #
b1100000001011011 '
b101000 &
#41
b11001001000000 "
b11001001000000 )
0-
09
1E
1Q
1]
1a
0,
08
1<
1D
0L
1X
0/
0;
1O
1[
1_
0c
0g
b11001001000000 !
b11111011010000 $
b11111011010000 (
b11001001001001 #
b11001001001001 '
b101001 &
#42
b1100000001010001 "
b1100000001010001 )
1-
1=
0Q
0]
0a
1e
1i
1,
0H
0P
1d
1h
1/
13
07
1;
1G
0O
0[
0_
1c
1g
b1100000001010001 !
b1111110001010001 $
b1111110001010001 (
b1100000011010111 #
b1100000011010111 '
b101010 &
#43
b10111100000100 "
b10111100000100 )
15
0=
0-
0E
1M
1Q
1U
1Y
1a
0e
0i
0,
14
18
0<
0D
1L
1P
0h
0+
0C
1K
1O
1S
1W
1_
0c
0g
b10111100000100 !
b111111100001100 $
b111111100001100 (
b10111110010110 #
b10111110010110 '
b101011 &
#44
b1100110011000000 "
b1100110011000000 )
1I
0Q
05
1E
0M
0a
1e
1i
04
1D
1H
0P
0\
1h
03
0;
1C
0K
0_
1c
1g
b1100110011000000 !
b1110110111001000 $
b1110110111001000 (
b1100111011000010 #
b1100111011000010 '
b101100 &
#45
b100100000110101 "
b100100000110101 )
0E
1-
15
1=
1A
0I
0U
0i
1,
14
1<
1@
0D
0H
1+
13
1;
1?
0G
0S
1[
0g
b100100000110101 !
b1110110100111101 $
b1110110100111101 (
b101101001110111 #
b101101001110111 '
b101101 &
#46
b10010 "
b10010 )
11
0Y
0e
0-
05
0A
0,
10
1D
0L
0T
0X
0`
0d
0h
0+
03
0?
0C
1K
1g
b10010 !
b1111110 $
b1111110 (
b1101101100010010 #
b1101101100010010 '
b101110 &
#47
b1000000100101001 "
b1000000100101001 )
1M
1i
1-
01
19
0=
1A
1,
00
04
0D
1L
1P
1T
1`
1d
1h
1+
0/
13
17
0;
1?
1C
0O
0W
0[
0c
b1000000100101001 !
b1110011100111001 $
b1110011100111001 (
b1000000101101101 #
b1000000101101101 '
b101111 &
#48
b1000011000010011 "
b1000011000010011 )
09
0M
11
1=
0A
1Q
1U
10
08
0@
1D
1H
0L
1\
1/
1;
0?
0C
1O
1S
1W
b1000011000010011 !
b1111011011010011 $
b1111011011010011 (
b1000111100011111 #
b1000111100011111 '
b110000 &
#49
b100000000000 "
b100000000000 )
0-
0Q
0U
1Y
01
0=
0i
0,
00
18
1@
0H
0P
0T
1X
0\
0`
0d
0/
07
0;
1G
1_
0g
b100000000000 !
b1000100001111000 $
b1000100001111000 (
b10111110000101 #
b10111110000101 '
b110001 &
#50
b100100101001001 "
b100100101001001 )
1-
1M
19
1E
1e
1,
0<
0@
1L
1P
1d
0h
1/
03
17
1;
1C
0G
0O
0S
1[
0_
1c
b100100101001001 !
b100101101001001 $
b100101101001001 (
b101100101011011 #
b101100101011011 '
b110010 &
#51
b1010111000101010 "
b1010111000101010 )
0-
11
1A
0E
0M
1Q
1U
1a
0e
1i
0,
10
1@
0D
1T
1`
0d
1h
13
1?
0C
0K
1O
1S
0[
1_
0c
1g
b1010111000101010 !
b1010111100101010 $
b1010111100101010 (
b1010111000111111 #
b1010111000111111 '
b110011 &
#52
b10000000000000 "
b10000000000000 )
09
0Q
01
0A
0U
0Y
0i
14
08
0@
1H
0L
0P
0T
1\
0h
0+
0/
03
0?
1C
1K
0S
0W
1c
0g
b10000000000000 !
b11100010000110 $
b11100010000110 (
b110001101011000 #
b110001101011000 '
b110100 &
#53
b10001100 "
b10001100 )
19
15
1I
0a
00
18
1<
1P
0X
1d
1h
1/
13
0;
0C
1G
0K
0O
1S
1W
0_
0c
b10001100 !
b1111001010011100 $
b1111001010011100 (
b110010001110 #
b110010001110 '
b110101 &
#54
b1001100000100010 "
b1001100000100010 )
11
09
0I
1Y
05
1A
1]
1i
10
08
0<
1@
0H
0P
1T
1X
0d
03
1;
1?
1C
1K
0S
1[
1g
b1001100000100010 !
b1011110000100110 $
b1011110000100110 (
b1001100111111010 #
b1001100111111010 '
b110110 &
#55
b1010000100011 "
b1010000100011 )
1-
1U
0Y
0i
1,
04
1H
0X
1+
07
0G
1O
1S
0W
0g
b1010000100011 !
b1011010010100011 $
b1011010010100011 (
b1011101110011 #
b1011101110011 '
b110111 &
#56
b1000000000100011 "
b1000000000100011 )
0U
0]
1i
1<
1P
0T
0`
13
17
0;
0C
0K
0O
0S
1W
0[
1_
1g
b1000000000100011 !
b1001001010110011 $
b1001001010110011 (
b1010100000101111 #
b1010100000101111 '
b111000 &
#57
b10001000100 "
b10001000100 )
0-
01
15
0A
1E
1U
0i
0,
00
14
0<
0@
1D
0H
1L
0P
1T
1X
0\
0h
1;
0?
1C
1O
1S
0W
1[
0_
1c
0g
b10001000100 !
b110101000100 $
b110101000100 (
b101011001011111 #
b101011001011111 '
b111001 &
#58
b11010011000011 "
b11010011000011 )
1-
11
05
1]
1I
1a
1,
10
04
18
1H
0L
1P
0X
1\
1`
07
1?
1G
1K
0O
1W
1_
1g
b11010011000011 !
b11011011001011 $
b11011011001011 (
b1111110111110111 #
b1111110111110111 '
b111010 &
#59
b1101001000010 "
b1101001000010 )
0I
1Y
0-
1Q
0U
0a
0,
1<
0H
1L
0T
1X
0`
1d
1h
0+
0;
0K
1O
0S
0_
0c
0g
b1101001000010 !
b1101101101011010 $
b1101101101011010 (
b1101011100110 #
b1101011100110 '
b111011 &
#60
b1100000000101001 "
b1100000000101001 )
1A
1-
01
19
0E
0Q
0Y
0]
1e
1i
1,
00
14
0<
1@
1H
0L
0X
0\
1`
1+
0/
03
17
0C
0G
1K
0O
0W
0[
1c
1g
b1100000000101001 !
b1110001011101101 $
b1110001011101101 (
b1100000100101001 #
b1100000100101001 '
b111100 &
#61
b10010001000000 "
b10010001000000 )
09
0e
0-
0A
1E
1U
1a
0i
08
0H
1T
1\
0d
0+
1/
1;
0?
1C
1G
0K
1S
1W
1_
0g
b10010001000000 !
b1011011001100101 $
b1011011001100101 (
b110110011011010 #
b110110011011010 '
b111101 &
#62
b1000000010010101 "
b1000000010010101 )
1=
1I
0a
1-
15
0E
0U
1i
10
18
1<
0@
1H
0P
0`
1+
0/
13
07
1?
0C
1O
0S
0W
1g
b1000000010010101 !
b1001010011011111 $
b1001010011011111 (
b1110001010110101 #
b1110001010110101 '
b111110 &
#63
b1100101000000 "
b1100101000000 )
0-
0=
05
1E
0I
1M
1Y
1]
0i
0,
00
08
0<
0H
1L
1P
1X
1`
1d
03
17
1C
0G
1K
0O
1W
1[
0_
0c
0g
b1100101000000 !
b1111111101000100 $
b1111111101000100 (
b1100101111001 #
b1100101111001 '
b111111 &
#64
b100000000000 "
b100000000000 )
0E
0M
0]
10
04
18
1@
0D
0T
0\
0`
0d
0h
0+
07
0?
1G
0K
1S
0[
b100000000000 !
b101100101010 $
b101100101010 (
b110011010000 #
b110011010000 '
b1000000 &
#65
b1000110100001010 "
b1000110100001010 )
1U
11
19
1M
1i
14
0@
1T
1d
1h
1+
1/
17
0;
1?
0C
1K
1_
1g
b1000110100001010 !
b1100111100001110 $
b1100111100001110 (
b1010110110101011 #
b1010110110101011 '
b1000001 &
#66
b1010110010011000 "
b1010110010011000 )
1I
0M
1a
01
1=
04
1<
1H
0L
0P
1\
1`
0d
0+
0/
13
1;
0?
1C
b1010110010011000 !
b1011110010011010 $
b1011110010011010 (
b1010110111011100 #
b1010110111011100 '
b1000010 &
#67
b1011000001 "
b1011000001 )
09
0=
1E
0a
1-
1Q
0U
0Y
0i
1,
08
0<
1D
1P
0T
0X
0\
0`
0h
1+
1?
0K
1O
0S
0W
1[
1c
0g
b1011000001 !
b1011000011 $
b1011000011 (
b111001011111101 #
b111001011111101 '
b1000011 &
#68
b1110100101000110 "
b1110100101000110 )
15
1a
1e
0-
11
0I
1M
0Q
1Y
1i
0,
14
18
0H
1L
0P
1X
1`
1d
1h
0+
1/
07
0?
0G
1K
0O
1S
1W
0[
1g
b1110100101000110 !
b1110100101001110 $
b1110100101001110 (
b1110110101010110 #
b1110110101010110 '
b1000100 &
#69
b11010000000010 "
b11010000000010 )
05
0E
1U
0e
0M
0Y
1]
0i
04
0D
0L
1T
0X
1\
0d
0h
1+
0;
1?
0K
1O
0W
1[
0g
b11010000000010 !
b11010000001010 $
b11010000001010 (
b111011001100111 #
b111011001100111 '
b1000101 &
#70
b1000100000110000 "
b1000100000110000 )
01
1A
0]
0a
1=
0U
1Y
1i
00
1<
1@
1P
0T
1X
0\
0`
1h
0+
1;
0C
1G
1K
0O
0S
1W
0c
1g
b1000100000110000 !
b1000101000111000 $
b1000101000111000 (
b1011100110110110 #
b1011100110110110 '
b1000110 &
#71
b1000010000111000 "
b1000010000111000 )
19
1U
0Y
1H
0P
1T
0X
1d
1+
0/
03
17
1C
0G
1O
1S
0W
0[
0_
b1000010000111000 !
b1100010010111000 $
b1100010010111000 (
b1000011101111001 #
b1000011101111001 '
b1000111 &
#72
b1110110010000 "
b1110110010000 )
1M
0i
09
0A
1I
1Y
1]
1,
10
08
0@
1L
1X
1\
0h
0+
13
07
0?
0C
1G
1W
1[
1_
b1110110010000 !
b101110110010011 $
b101110110010011 (
b1011111110010100 #
b1011111110010100 '
b1001000 &
#73
b100000000000 "
b100000000000 )
0U
0=
0I
0M
0]
00
18
1D
0H
0L
1P
0T
0\
1h
0;
0G
0K
0O
0[
0g
b100000000000 !
b1100101001011001 $
b1100101001011001 (
b10110000000100 #
b10110000000100 '
b1001001 &
#74
b100100001001001 "
b100100001001001 )
1-
19
1E
1e
14
0<
1T
1\
1+
1/
03
17
1;
1C
1G
1K
0S
1c
b100100001001001 !
b1101111001001101 $
b1101111001001101 (
b110100111011011 #
b110100111011011 '
b1001010 &
#75
b10011001001001 "
b10011001001001 )
1a
1Q
1U
0Y
0e
1@
0X
0\
1`
0d
0h
0/
1O
1S
0W
1[
0c
1g
b10011001001001 !
b10011001101101 $
b10011001101101 (
b1011011111011001 #
b1011011111011001 '
b1001011 &
#76
b100000001000010 "
b100000001000010 )
0Q
0a
0-
11
09
0U
1e
0,
10
04
0@
1H
1L
0P
0T
1X
0`
1d
0+
1/
13
07
1?
0G
0K
0S
0[
1c
b100000001000010 !
b100100111001010 $
b100100111001010 (
b1110001001110110 #
b1110001001110110 '
b1001100 &
#77
b10000110010100 "
b10000110010100 )
01
15
1=
1a
0E
1I
1M
0e
1,
00
14
08
1<
0D
0X
1\
1`
0C
1G
1K
0O
1S
1W
0c
0g
b10000110010100 !
b111000110010101 $
b111000110010101 (
b10110110110110 #
b10110110110110 '
b1001101 &
#78
b1101000000100 "
b1101000000100 )
1Y
0=
0I
0M
1Q
1]
0a
0,
0<
0H
1P
1X
0`
0d
1h
0;
0?
1C
0G
0K
1O
0S
1[
0_
b1101000000100 !
b1001101100000100 $
b1001101100000100 (
b1101001000110 #
b1101001000110 '
b1001110 &
#79
b101100001 "
b101100001 )
05
1E
1-
1A
1M
0Q
0Y
0]
1,
04
18
1@
1D
1T
0X
0\
0h
1+
1;
1?
1G
1K
0O
0W
0[
1_
1c
b101100001 !
b11101101001 $
b11101101001 (
b110000111110111 #
b110000111110111 '
b1001111 &
#80
b1000100010000000 "
b1000100010000000 )
0A
1I
0-
0E
0M
1Y
1i
0,
0@
0D
1H
0P
1X
1h
0+
0/
0C
0K
1O
1W
1[
0c
1g
b1000100010000000 !
b1000110110001000 $
b1000110110001000 (
b1011101010110100 #
b1011101010110100 '
b1010000 &
#81
b101000 "
b101000 )
1A
0Y
0i
19
0I
1,
14
1@
0H
0L
0X
0h
03
17
0;
0G
1K
0O
0_
1c
b101000 !
b10000101101 $
b10000101101 (
b1101100100101000 #
b1101100100101000 '
b1010001 &
#82
b1000000000110 "
b1000000000110 )
1]
11
15
09
0A
0,
10
1X
1\
1h
1+
1/
13
07
0?
1C
1G
0K
0W
1_
0c
0g
b1000000000110 !
b1001110000101110 $
b1001110000101110 (
b11000011000111 #
b11000011000111 '
b1010010 &
#83
b100010000001000 "
b100010000001000 )
01
05
19
1U
0]
1e
00
1<
0@
1L
0X
0\
1d
0h
0+
0/
03
17
0C
0G
1S
0[
1c
1g
b100010000001000 !
b100010100011100 $
b100010100011100 (
b1110010000001000 #
b1110010000001000 '
b1010011 &
#84
b11000101001 "
b11000101001 )
1-
1A
1Q
0e
1,
04
0<
1@
1P
0d
1+
13
1;
1?
1C
1G
1O
0c
b11000101001 !
b11100101001 $
b11100101001 (
b1010011011111101 #
b1010011011111101 '
b1010100 &
#85
b100 "
b100 )
15
09
0-
0A
0Q
0U
0,
10
14
08
0@
1H
1`
1d
0+
0?
0C
0G
0O
0S
1[
0_
b100 !
b110011110000110 $
b110011110000110 (
b1001000000011100 #
b1001000000011100 '
b1010101 &
