01_Boolean_Logic/Buffer.v
/**
 * Buffer:
 * out = in
 */

`default_nettype none
module Buffer(
  input in,
  output out
);

  assign out = in;

endmodule

01_Boolean_Logic/Buffer16.v
/**
 * 16-bit bitwise Buffer:
 * for i = 0..15: out[i] = in[i]
 */

`default_nettype none
module Buffer16(
  input [15:0] in,
  output [15:0] out
);

  // Old way od doing things
  // assign out[0] = in[0] ;
  // assign out[1] = in[1] ;
  // assign out[2] = in[2] ;
  // assign out[3] = in[3] ;
  // assign out[4] = in[4] ;
  // assign out[5] = in[5] ;
  // assign out[6] = in[6] ;
  // assign out[7] = in[7] ;
  // assign out[8] = in[8] ;
  // assign out[9] = in[9] ;
  // assign out[10] = in[10] ;
  // assign out[11] = in[11] ;
  // assign out[12] = in[12] ;
  // assign out[13] = in[13] ;
  // assign out[14] = in[14] ;
  // assign out[15] = in[15] ;

  genvar i;
  generate
    for(i = 0; i < 16; i++) begin : gen_buffer
      Buffer buffer_inst(.in(in[i]), .out(out[i]));
    end
  endgenerate

endmodule

01_Boolean_Logic/09_Buffer16/Buffer16_tb.v
`default_nettype none
module Buffer16_tb();
	
	// IN,OUT
	reg [15:0] in;
	wire [15:0] out;

	// Part
	Buffer16 BUFFER16(
		.in(in),
		.out(out)
	);

	// Compare
	wire [15:0] out_cmp;
	assign out_cmp = in;
	
	reg fail = 0;
	reg [15:0] n = 0;
	task check;
		#1
		if (out != out_cmp) 
			begin
				$display("FAIL: in=%16b, out=%16b",in,out);
				fail=1;
			end
	endtask
	  
  	// Test	
	initial begin
  		$dumpvars(0, Buffer16_tb);
		
		$display("------------------------");
		$display("Testbench: Buffer16");
		
		for (n=0; n<10000;n=n+1) 
			begin
				in=$random;
				check();
		
			end
			
		if (fail==0) $display("passed");
		$display("------------------------");
		$finish;
	end

endmodule

01_Boolean_Logic/09_Buffer16/_build/default/Buffer16_tb.vcd
$date
	Wed Aug  5 01:58:54 2026
$end
$version
	Icarus Verilog
$end
$timescale
	1ps
$end
$scope module Buffer16_tb $end
$var wire 16 ! out [15:0] $end
$var wire 16 " out_cmp [15:0] $end
$var reg 1 # fail $end
$var reg 16 $ in [15:0] $end
$var reg 16 % n [15:0] $end
$scope module BUFFER16 $end
$var wire 16 & in [15:0] $end
$var wire 16 ' out [15:0] $end
$scope begin gen_buffer[0] $end
$var parameter 2 ( i $end
$scope module buffer_inst $end
$var wire 1 ) in $end
$var wire 1 * out $end
$upscope $end
$upscope $end
$scope begin gen_buffer[1] $end
$var parameter 2 + i $end
$scope module buffer_inst $end
$var wire 1 , in $end
$var wire 1 - out $end
$upscope $end
$upscope $end
$scope begin gen_buffer[2] $end
$var parameter 3 . i $end
$scope module buffer_inst $end
$var wire 1 / in $end
$var wire 1 0 out $end
$upscope $end
$upscope $end
$scope begin gen_buffer[3] $end
$var parameter 3 1 i $end
$scope module buffer_inst $end
$var wire 1 2 in $end
$var wire 1 3 out $end
$upscope $end
$upscope $end
$scope begin gen_buffer[4] $end
$var parameter 4 4 i $end
$scope module buffer_inst $end
$var wire 1 5 in $end
$var wire 1 6 out $end
$upscope $end
$upscope $end
$scope begin gen_buffer[5] $end
$var parameter 4 7 i $end
$scope module buffer_inst $end
$var wire 1 8 in $end
$var wire 1 9 out $end
$upscope $end
$upscope $end
$scope begin gen_buffer[6] $end
$var parameter 4 : i $end
$scope module buffer_inst $end
$var wire 1 ; in $end
$var wire 1 < out $end
$upscope $end
$upscope $end
$scope begin gen_buffer[7] $end
$var parameter 4 = i $end
$scope module buffer_inst $end
$var wire 1 > in $end
$var wire 1 ? out $end
$upscope $end
$upscope $end
$scope begin gen_buffer[8] $end
$var parameter 5 @ i $end
$scope module buffer_inst $end
$var wire 1 A in $end
$var wire 1 B out $end
$upscope $end
$upscope $end
$scope begin gen_buffer[9] $end
$var parameter 5 C i $end
$scope module buffer_inst $end
$var wire 1 D in $end
$var wire 1 E out $end
$upscope $end
$upscope $end
$scope begin gen_buffer[10] $end
$var parameter 5 F i $end
$scope module buffer_inst $end
$var wire 1 G in $end
$var wire 1 H out $end
$upscope $end
$upscope $end
$scope begin gen_buffer[11] $end
$var parameter 5 I i $end
$scope module buffer_inst $end
$var wire 1 J in $end
$var wire 1 K out $end
$upscope $end
$upscope $end
$scope begin gen_buffer[12] $end
$var parameter 5 L i $end
$scope module buffer_inst $end
$var wire 1 M in $end
$var wire 1 N out $end
$upscope $end
$upscope $end
$scope begin gen_buffer[13] $end
$var parameter 5 O i $end
$scope module buffer_inst $end
$var wire 1 P in $end
$var wire 1 Q out $end
$upscope $end
$upscope $end
$scope begin gen_buffer[14] $end
$var parameter 5 R i $end
$scope module buffer_inst $end
$var wire 1 S in $end
$var wire 1 T out $end
$upscope $end
$upscope $end
$scope begin gen_buffer[15] $end
$var parameter 5 U i $end
$scope module buffer_inst $end
$var wire 1 V in $end
$var wire 1 W out $end
$upscope $end
$upscope $end
$upscope $end
$scope task check $end
$upscope $end
$upscope $end
$enddefinitions $end
$comment Show the parameter values. $end
$dumpall
b1111 U
b1110 R
b1101 O
b1100 L
b1011 I
b1010 F
b1001 C
b1000 @
b111 =
b110 :
b101 7
b100 4
b11 1
b10 .
b1 +
b0 (
$end
#0
$dumpvars
0W
0V
0T
0S
1Q
1P
1N
1M
0K
0J
1H
1G
0E
0D
1B
1A
0?
0>
0<
0;
19
18
06
05
03
02
10
1/
0-
0,
0*
0)
b11010100100100 '
b11010100100100 &
b0 %
b11010100100100 $
0#
b11010100100100 "
b11010100100100 !
$end
#1
b101111010000001 !
b101111010000001 '
1*
1)
00
0/
09
08
1?
1>
0B
0A
1E
1D
1K
1J
0Q
0P
1T
1S
b101111010000001 "
b101111010000001 $
b101111010000001 &
b1 %
#2
b1101011000001001 !
b1101011000001001 '
13
12
0?
0>
0K
0J
1W
1V
b1101011000001001 "
b1101011000001001 $
b1101011000001001 &
b10 %
#3
b101011001100011 !
b101011001100011 '
1-
1,
03
02
19
18
1<
1;
0W
0V
b101011001100011 "
b101011001100011 $
b101011001100011 &
b11 %
#4
b111101100001101 !
b111101100001101 '
0-
0,
10
1/
13
12
09
08
0<
0;
1B
1A
0H
0G
1K
1J
1Q
1P
b111101100001101 "
b111101100001101 $
b111101100001101 &
b100 %
#5
b1001100110001101 !
b1001100110001101 '
1?
1>
0E
0D
0Q
0P
0T
0S
1W
1V
b1001100110001101 "
b1001100110001101 $
b1001100110001101 &
b101 %
#6
b1000010001100101 !
b1000010001100101 '
03
02
19
18
1<
1;
0?
0>
0B
0A
1H
1G
0K
0J
0N
0M
b1000010001100101 "
b1000010001100101 $
b1000010001100101 &
b110 %
#7
b101001000010010 !
b101001000010010 '
0*
0)
1-
1,
00
0/
16
15
09
08
0<
0;
1E
1D
0H
0G
1N
1M
1T
1S
0W
0V
b101001000010010 "
b101001000010010 $
b101001000010010 &
b111 %
#8
b1110001100000001 !
b1110001100000001 '
1*
1)
0-
0,
06
05
1B
1A
0N
0M
1Q
1P
1W
1V
b1110001100000001 "
b1110001100000001 $
b1110001100000001 &
b1000 %
#9
b1100110100001101 !
b1100110100001101 '
10
1/
13
12
0E
0D
1H
1G
1K
1J
0Q
0P
b1100110100001101 "
b1100110100001101 $
b1100110100001101 &
b1001 %
#10
b1111000101110110 !
b1111000101110110 '
0*
0)
1-
1,
03
02
16
15
19
18
1<
1;
0H
0G
0K
0J
1N
1M
1Q
1P
b1111000101110110 "
b1111000101110110 $
b1111000101110110 &
b1010 %
#11
b1100110100111101 !
b1100110100111101 '
1*
1)
0-
0,
13
12
0<
0;
1H
1G
1K
1J
0N
0M
0Q
0P
b1100110100111101 "
b1100110100111101 $
b1100110100111101 &
b1011 %
#12
b101011111101101 !
b101011111101101 '
06
05
1<
1;
1?
1>
1E
1D
0K
0J
1N
1M
0W
0V
b101011111101101 "
b101011111101101 $
b101011111101101 &
b1100 %
#13
b1111011110001100 !
b1111011110001100 '
0*
0)
09
08
0<
0;
1Q
1P
1W
1V
b1111011110001100 "
b1111011110001100 $
b1111011110001100 &
b1101 %
#14
b1110100111111001 !
b1110100111111001 '
1*
1)
00
0/
16
15
19
18
1<
1;
0E
0D
0H
0G
1K
1J
0N
0M
b1110100111111001 "
b1110100111111001 $
b1110100111111001 &
b1110 %
#15
b10010011000110 !
b10010011000110 '
0*
0)
1-
1,
10
1/
03
02
06
05
09
08
0B
0A
1H
1G
0K
0J
0T
0S
0W
0V
b10010011000110 "
b10010011000110 $
b10010011000110 &
b1111 %
#16
b1000010011000101 !
b1000010011000101 '
1*
1)
0-
0,
0Q
0P
1W
1V
b1000010011000101 "
b1000010011000101 $
b1000010011000101 &
b10000 %
#17
b1101001010101010 !
b1101001010101010 '
0*
0)
1-
1,
00
0/
13
12
19
18
0<
0;
1E
1D
0H
0G
1N
1M
1T
1S
b1101001010101010 "
b1101001010101010 $
b1101001010101010 &
b10001 %
#18
b1111011111100101 !
b1111011111100101 '
1*
1)
0-
0,
10
1/
03
02
1<
1;
1B
1A
1H
1G
1Q
1P
b1111011111100101 "
b1111011111100101 $
b1111011111100101 &
b10010 %
#19
b111001001110111 !
b111001001110111 '
1-
1,
16
15
0?
0>
0B
0A
0H
0G
0W
0V
b111001001110111 "
b111001001110111 $
b111001001110111 &
b10011 %
#20
b1101011000010010 !
b1101011000010010 '
0*
0)
00
0/
09
08
0<
0;
1H
1G
0Q
0P
1W
1V
b1101011000010010 "
b1101011000010010 $
b1101011000010010 &
b10100 %
#21
b1101101110001111 !
b1101101110001111 '
1*
1)
10
1/
13
12
06
05
1?
1>
1B
1A
0H
0G
1K
1J
b1101101110001111 "
b1101101110001111 $
b1101101110001111 &
b10101 %
#22
b110100111110010 !
b110100111110010 '
0*
0)
00
0/
03
02
16
15
19
18
1<
1;
0E
0D
0N
0M
1Q
1P
0W
0V
b110100111110010 "
b110100111110010 $
b110100111110010 &
b10110 %
#23
b1001011011001110 !
b1001011011001110 '
10
1/
13
12
06
05
09
08
0B
0A
1E
1D
1H
1G
0K
0J
1N
1M
0Q
0P
0T
0S
1W
1V
b1001011011001110 "
b1001011011001110 $
b1001011011001110 &
b10111 %
#24
b111101011101000 !
b111101011101000 '
0-
0,
00
0/
19
18
0H
0G
1K
1J
1Q
1P
1T
1S
0W
0V
b111101011101000 "
b111101011101000 $
b111101011101000 &
b11000 %
#25
b100111011000101 !
b100111011000101 '
1*
1)
10
1/
03
02
09
08
1H
1G
0N
0M
0Q
0P
b100111011000101 "
b100111011000101 $
b100111011000101 &
b11001 %
#26
b100100101011100 !
b100100101011100 '
0*
0)
13
12
16
15
0?
0>
1B
1A
0E
0D
0H
0G
b100100101011100 "
b100100101011100 $
b100100101011100 &
b11010 %
#27
b10100010111101 !
b10100010111101 '
1*
1)
19
18
0<
0;
1?
1>
0B
0A
1Q
1P
0T
0S
b10100010111101 "
b10100010111101 $
b10100010111101 &
b11011 %
#28
b101100000101101 !
b101100000101101 '
06
05
0?
0>
1N
1M
0Q
0P
1T
1S
b101100000101101 "
b101100000101101 $
b101100000101101 &
b11100 %
#29
b10011001100101 !
b10011001100101 '
03
02
1<
1;
1E
1D
1H
1G
0K
0J
0N
0M
1Q
1P
0T
0S
b10011001100101 "
b10011001100101 $
b10011001100101 &
b11101 %
#30
b110001001100011 !
b110001001100011 '
1-
1,
00
0/
0H
0G
1T
1S
b110001001100011 "
b110001001100011 $
b110001001100011 &
b11110 %
#31
b1000011100001010 !
b1000011100001010 '
0*
0)
13
12
09
08
0<
0;
1B
1A
1H
1G
0Q
0P
0T
0S
1W
1V
b1000011100001010 "
b1000011100001010 $
b1000011100001010 &
b11111 %
#32
b10001010000000 !
b10001010000000 '
0-
0,
03
02
1?
1>
0B
0A
0H
0G
1Q
1P
0W
0V
b10001010000000 "
b10001010000000 $
b10001010000000 &
b100000 %
#33
b10000100100000 !
b10000100100000 '
19
18
0?
0>
1B
1A
0E
0D
b10000100100000 "
b10000100100000 $
b10000100100000 &
b100001 %
#34
b100010110101010 !
b100010110101010 '
1-
1,
13
12
1?
1>
1H
1G
0Q
0P
1T
1S
b100010110101010 "
b100010110101010 $
b100010110101010 &
b100010 %
#35
b1100110010011101 !
b1100110010011101 '
1*
1)
0-
0,
10
1/
16
15
09
08
0B
0A
1K
1J
1W
1V
b1100110010011101 "
b1100110010011101 $
b1100110010011101 &
b100011 %
#36
b11111010010110 !
b11111010010110 '
0*
0)
1-
1,
03
02
1E
1D
1N
1M
1Q
1P
0T
0S
0W
0V
b11111010010110 "
b11111010010110 $
b11111010010110 &
b100100 %
#37
b1011100000010011 !
b1011100000010011 '
1*
1)
00
0/
0?
0>
0E
0D
0H
0G
1W
1V
b1011100000010011 "
b1011100000010011 $
b1011100000010011 &
b100101 %
#38
b11100000001101 !
b11100000001101 '
0-
0,
10
1/
13
12
06
05
0W
0V
b11100000001101 "
b11100000001101 $
b11100000001101 &
b100110 %
#39
b1101011001010011 !
b1101011001010011 '
1-
1,
00
0/
03
02
16
15
1<
1;
1E
1D
1H
1G
0K
0J
0Q
0P
1T
1S
1W
1V
b1101011001010011 "
b1101011001010011 $
b1101011001010011 &
b100111 %
#40
b1101110101101011 !
b1101110101101011 '
13
12
06
05
19
18
1B
1A
0E
0D
1K
1J
b1101110101101011 "
b1101110101101011 $
b1101110101101011 &
b101000 %
#41
b10101011010101 !
b10101011010101 '
0-
0,
10
1/
03
02
16
15
09
08
1?
1>
0B
0A
1E
1D
0H
0G
0N
0M
1Q
1P
0T
0S
0W
0V
b10101011010101 "
b10101011010101 $
b10101011010101 &
b101001 %
#42
b100101000000010 !
b100101000000010 '
0*
0)
1-
1,
00
0/
06
05
0<
0;
0?
0>
0Q
0P
1T
1S
b100101000000010 "
b100101000000010 $
b100101000000010 &
b101010 %
#43
b11111010101110 !
b11111010101110 '
10
1/
13
12
19
18
1?
1>
1H
1G
1N
1M
1Q
1P
0T
0S
b11111010101110 "
b11111010101110 $
b11111010101110 &
b101011 %
#44
b1110100100011101 !
b1110100100011101 '
1*
1)
0-
0,
16
15
09
08
0?
0>
1B
1A
0E
0D
0H
0G
0N
0M
1T
1S
1W
1V
b1110100100011101 "
b1110100100011101 $
b1110100100011101 &
b101100 %
#45
b111001011001111 !
b111001011001111 '
1-
1,
06
05
1<
1;
1?
1>
0B
0A
1E
1D
0K
0J
1N
1M
0W
0V
b111001011001111 "
b111001011001111 $
b111001011001111 &
b101101 %
#46
b100100100100011 !
b100100100100011 '
00
0/
03
02
19
18
0<
0;
0?
0>
1B
1A
0E
0D
1K
1J
0N
0M
0Q
0P
b100100100100011 "
b100100100100011 $
b100100100100011 &
b101110 %
#47
b110010100001010 !
b110010100001010 '
0*
0)
13
12
09
08
1H
1G
0K
0J
1Q
1P
b110010100001010 "
b110010100001010 $
b110010100001010 &
b101111 %
#48
b101011001010 !
b101011001010 '
1<
1;
1?
1>
0B
0A
1E
1D
0H
0G
1K
1J
0Q
0P
0T
0S
b101011001010 "
b101011001010 $
b101011001010 &
b110000 %
#49
b100110000111100 !
b100110000111100 '
0-
0,
10
1/
16
15
19
18
0<
0;
0?
0>
0E
0D
1H
1G
1T
1S
b100110000111100 "
b100110000111100 $
b100110000111100 &
b110001 %
#50
b1011110111110010 !
b1011110111110010 '
1-
1,
00
0/
03
02
1<
1;
1?
1>
1B
1A
1N
1M
1Q
1P
0T
0S
1W
1V
b1011110111110010 "
b1011110111110010 $
b1011110111110010 &
b110010 %
#51
b110000110001010 !
b110000110001010 '
13
12
06
05
09
08
0<
0;
0H
0G
0K
0J
0N
0M
1T
1S
0W
0V
b110000110001010 "
b110000110001010 $
b110000110001010 &
b110011 %
#52
b1011001101000001 !
b1011001101000001 '
1*
1)
0-
0,
03
02
1<
1;
0?
0>
1E
1D
1N
1M
0T
0S
1W
1V
b1011001101000001 "
b1011001101000001 $
b1011001101000001 &
b110100 %
#53
b11010011011000 !
b11010011011000 '
0*
0)
13
12
16
15
1?
1>
0B
0A
0E
0D
1H
1G
0W
0V
b11010011011000 "
b11010011011000 $
b11010011011000 &
b110101 %
#54
b1111001101111000 !
b1111001101111000 '
19
18
0?
0>
1B
1A
1E
1D
0H
0G
1T
1S
1W
1V
b1111001101111000 "
b1111001101111000 $
b1111001101111000 &
b110110 %
#55
b1001010001001 !
b1001010001001 '
1*
1)
06
05
09
08
0<
0;
1?
1>
0B
0A
0Q
0P
0T
0S
0W
0V
b1001010001001 "
b1001010001001 $
b1001010001001 &
b110111 %
#56
b110111101011 !
b110111101011 '
1-
1,
19
18
1<
1;
1B
1A
0E
0D
1H
1G
1K
1J
0N
0M
b110111101011 "
b110111101011 $
b110111101011 &
b111000 %
#57
b110010110110110 !
b110010110110110 '
0*
0)
10
1/
03
02
16
15
0<
0;
0K
0J
1Q
1P
1T
1S
b110010110110110 "
b110010110110110 $
b110010110110110 &
b111001 %
#58
b1111100111000110 !
b1111100111000110 '
06
05
09
08
1<
1;
0H
0G
1K
1J
1N
1M
1W
1V
b1111100111000110 "
b1111100111000110 $
b1111100111000110 &
b111010 %
#59
b1001110101110 !
b1001110101110 '
13
12
19
18
0<
0;
1E
1D
0K
0J
0Q
0P
0T
0S
0W
0V
b1001110101110 "
b1001110101110 $
b1001110101110 &
b111011 %
#60
b1010111100 !
b1010111100 '
0-
0,
16
15
0B
0A
0N
0M
b1010111100 "
b1010111100 $
b1010111100 &
b111100 %
#61
b1101110100101010 !
b1101110100101010 '
1-
1,
00
0/
06
05
0?
0>
1B
1A
0E
0D
1H
1G
1K
1J
1N
1M
1T
1S
1W
1V
b1101110100101010 "
b1101110100101010 $
b1101110100101010 &
b111101 %
#62
b1001101000001011 !
b1001101000001011 '
1*
1)
09
08
0B
0A
1E
1D
0H
0G
0T
0S
b1001101000001011 "
b1001101000001011 $
b1001101000001011 &
b111110 %
#63
b1011111001110001 !
b1011111001110001 '
0-
0,
03
02
16
15
19
18
1<
1;
1H
1G
1Q
1P
b1011111001110001 "
b1011111001110001 $
b1011111001110001 &
b111111 %
#64
b100000110000101 !
b100000110000101 '
10
1/
06
05
09
08
0<
0;
1?
1>
1B
1A
0E
0D
0H
0G
0K
0J
0N
0M
0Q
0P
1T
1S
0W
0V
b100000110000101 "
b100000110000101 $
b100000110000101 &
b1000000 %
#65
b101010101001111 !
b101010101001111 '
1-
1,
13
12
1<
1;
0?
0>
1H
1G
1N
1M
b101010101001111 "
b101010101001111 $
b101010101001111 &
b1000001 %
#66
b110000000111011 !
b110000000111011 '
00
0/
16
15
19
18
0<
0;
0B
0A
0H
0G
0N
0M
1Q
1P
b110000000111011 "
b110000000111011 $
b110000000111011 &
b1000010 %
#67
b11001100111010 !
b11001100111010 '
0*
0)
1B
1A
1E
1D
1N
1M
0T
0S
b11001100111010 "
b11001100111010 $
b11001100111010 &
b1000011 %
#68
b11001001111110 !
b11001001111110 '
10
1/
1<
1;
0B
0A
b11001001111110 "
b11001001111110 $
b11001001111110 &
b1000100 %
#69
b100101100010101 !
b100101100010101 '
1*
1)
0-
0,
03
02
09
08
0<
0;
1B
1A
1K
1J
0N
0M
0Q
0P
1T
1S
b100101100010101 "
b100101100010101 $
b100101100010101 &
b1000101 %
#70
b1001101111110001 !
b1001101111110001 '
00
0/
19
18
1<
1;
1?
1>
1N
1M
0T
0S
1W
1V
b1001101111110001 "
b1001101111110001 $
b1001101111110001 &
b1000110 %
#71
b100101111011001 !
b100101111011001 '
13
12
09
08
0N
0M
1T
1S
0W
0V
b100101111011001 "
b100101111011001 $
b100101111011001 &
b1000111 %
#72
b11101100010 !
b11101100010 '
0*
0)
1-
1,
03
02
06
05
19
18
0?
0>
1H
1G
0K
0J
0T
0S
b11101100010 "
b11101100010 $
b11101100010 &
b1001000 %
#73
b1111101101001100 !
b1111101101001100 '
0-
0,
10
1/
13
12
09
08
0H
0G
1K
1J
1N
1M
1Q
1P
1T
1S
1W
1V
b1111101101001100 "
b1111101101001100 $
b1111101101001100 &
b1001001 %
#74
b101010110011111 !
b101010110011111 '
1*
1)
1-
1,
16
15
0<
0;
1?
1>
0E
0D
1H
1G
0K
0J
0Q
0P
0W
0V
b101010110011111 "
b101010110011111 $
b101010110011111 &
b1001010 %
#75
b1010000110001111 !
b1010000110001111 '
06
05
0H
0G
0N
0M
1Q
1P
0T
0S
1W
1V
b1010000110001111 "
b1010000110001111 $
b1010000110001111 &
b1001011 %
#76
b1010100111111000 !
b1010100111111000 '
0*
0)
0-
0,
00
0/
16
15
19
18
1<
1;
1K
1J
b1010100111111000 "
b1010100111111000 $
b1010100111111000 &
b1001100 %
#77
b110000010110111 !
b110000010110111 '
1*
1)
1-
1,
10
1/
03
02
0<
0;
0B
0A
0K
0J
1T
1S
0W
0V
b110000010110111 "
b110000010110111 $
b110000010110111 &
b1001101 %
#78
b101011010011111 !
b101011010011111 '
13
12
09
08
1E
1D
1H
1G
1N
1M
0Q
0P
b101011010011111 "
b101011010011111 $
b101011010011111 &
b1001110 %
#79
b1001010001011100 !
b1001010001011100 '
0*
0)
0-
0,
1<
1;
0?
0>
0E
0D
0T
0S
1W
1V
b1001010001011100 "
b1001010001011100 $
b1001010001011100 &
b1001111 %
#80
b1100000001011011 !
b1100000001011011 '
1*
1)
1-
1,
00
0/
0H
0G
0N
0M
1T
1S
b1100000001011011 "
b1100000001011011 $
b1100000001011011 &
b1010000 %
#81
b11011110001001 !
b11011110001001 '
0-
0,
06
05
0<
0;
1?
1>
1B
1A
1E
1D
1H
1G
1N
1M
1Q
1P
0T
0S
0W
0V
b11011110001001 "
b11011110001001 $
b11011110001001 &
b1010001 %
#82
b11001001001001 !
b11001001001001 '
1<
1;
0?
0>
0B
0A
0H
0G
b11001001001001 "
b11001001001001 $
b11001001001001 &
b1010010 %
#83
b11111011010000 !
b11111011010000 '
0*
0)
03
02
16
15
1?
1>
1H
1G
1K
1J
b11111011010000 "
b11111011010000 $
b11111011010000 &
b1010011 %
#84
b1100000011010111 !
b1100000011010111 '
1*
1)
1-
1,
10
1/
0E
0D
0H
0G
0K
0J
0N
0M
0Q
0P
1T
1S
1W
1V
b1100000011010111 "
b1100000011010111 $
b1100000011010111 &
b1010100 %
#85
b1111110001010001 !
b1111110001010001 '
0-
0,
00
0/
0?
0>
1H
1G
1K
1J
1N
1M
1Q
1P
b1111110001010001 "
b1111110001010001 $
b1111110001010001 &
b1010101 %
#86
b10111110010110 !
b10111110010110 '
0*
0)
1-
1,
10
1/
0<
0;
1?
1>
1B
1A
1E
1D
0N
0M
0T
0S
0W
0V
b10111110010110 "
b10111110010110 $
b10111110010110 &
b1010110 %
#87
b111111100001100 !
b111111100001100 '
0-
0,
13
12
06
05
0?
0>
1N
1M
1T
1S
b111111100001100 "
b111111100001100 $
b111111100001100 &
b1010111 %
#88
b1100111011000010 !
b1100111011000010 '
1-
1,
00
0/
03
02
1<
1;
1?
1>
0B
0A
0N
0M
0Q
0P
1W
1V
b1100111011000010 "
b1100111011000010 $
b1100111011000010 &
b1011000 %
#89
b1110110111001000 !
b1110110111001000 '
0-
0,
13
12
1B
1A
0E
0D
1Q
1P
b1110110111001000 "
b1110110111001000 $
b1110110111001000 &
b1011001 %
#90
b101101001110111 !
b101101001110111 '
1*
1)
1-
1,
10
1/
03
02
16
15
19
18
0?
0>
0B
0A
1E
1D
0H
0G
1N
1M
0Q
0P
0W
0V
b101101001110111 "
b101101001110111 $
b101101001110111 &
b1011010 %
#91
b1110110100111101 !
b1110110100111101 '
0-
0,
13
12
0<
0;
1B
1A
0E
0D
1H
1G
0N
0M
1Q
1P
1W
1V
b1110110100111101 "
b1110110100111101 $
b1110110100111101 &
b1011011 %
#92
b1101101100010010 !
b1101101100010010 '
0*
0)
1-
1,
00
0/
03
02
09
08
1E
1D
0H
0G
1N
1M
0Q
0P
b1101101100010010 "
b1101101100010010 $
b1101101100010010 &
b1011100 %
#93
b1111110 !
b1111110 '
10
1/
13
12
19
18
1<
1;
0B
0A
0E
0D
0K
0J
0N
0M
0T
0S
0W
0V
b1111110 "
b1111110 $
b1111110 &
b1011101 %
#94
b1000000101101101 !
b1000000101101101 '
1*
1)
0-
0,
06
05
1B
1A
1W
1V
b1000000101101101 "
b1000000101101101 $
b1000000101101101 &
b1011110 %
#95
b1110011100111001 !
b1110011100111001 '
00
0/
16
15
0<
0;
1E
1D
1H
1G
1Q
1P
1T
1S
b1110011100111001 "
b1110011100111001 $
b1110011100111001 &
b1011111 %
#96
b1000111100011111 !
b1000111100011111 '
1-
1,
10
1/
09
08
1K
1J
0Q
0P
0T
0S
b1000111100011111 "
b1000111100011111 $
b1000111100011111 &
b1100000 %
#97
b1111011011010011 !
b1111011011010011 '
00
0/
03
02
1<
1;
1?
1>
0B
0A
0K
0J
1N
1M
1Q
1P
1T
1S
b1111011011010011 "
b1111011011010011 $
b1111011011010011 &
b1100001 %
#98
b10111110000101 !
b10111110000101 '
0-
0,
10
1/
06
05
0<
0;
1B
1A
1K
1J
0N
0M
0T
0S
0W
0V
b10111110000101 "
b10111110000101 $
b10111110000101 &
b1100010 %
#99
b1000100001111000 !
b1000100001111000 '
0*
0)
00
0/
13
12
16
15
19
18
1<
1;
0?
0>
0B
0A
0E
0D
0H
0G
0Q
0P
1W
1V
b1000100001111000 "
b1000100001111000 $
b1000100001111000 &
b1100011 %
#100
b101100101011011 !
b101100101011011 '
1*
1)
1-
1,
09
08
1B
1A
1N
1M
1T
1S
0W
0V
b101100101011011 "
b101100101011011 $
b101100101011011 &
b1100100 %
#101
b100101101001001 !
b100101101001001 '
0-
0,
06
05
1E
1D
0N
0M
b100101101001001 "
b100101101001001 $
b100101101001001 &
b1100101 %
#102
b1010111000111111 !
b1010111000111111 '
1-
1,
10
1/
16
15
19
18
0<
0;
0B
0A
1H
1G
1Q
1P
0T
0S
1W
1V
b1010111000111111 "
b1010111000111111 $
b1010111000111111 &
b1100110 %
#103
b1010111100101010 !
b1010111100101010 '
0*
0)
00
0/
06
05
1B
1A
b1010111100101010 "
b1010111100101010 $
b1010111100101010 &
b1100111 %
#104
b110001101011000 !
b110001101011000 '
0-
0,
16
15
09
08
1<
1;
0H
0G
0K
0J
1T
1S
0W
0V
b110001101011000 "
b110001101011000 $
b110001101011000 &
b1101000 %
#105
b11100010000110 !
b11100010000110 '
1-
1,
10
1/
03
02
06
05
0<
0;
1?
1>
0B
0A
0E
0D
1K
1J
1N
1M
0T
0S
b11100010000110 "
b11100010000110 $
b11100010000110 &
b1101001 %
#106
b110010001110 !
b110010001110 '
13
12
1H
1G
0N
0M
0Q
0P
b110010001110 "
b110010001110 $
b110010001110 &
b1101010 %
#107
b1111001010011100 !
b1111001010011100 '
0-
0,
16
15
1E
1D
0H
0G
0K
0J
1N
1M
1Q
1P
1T
1S
1W
1V
b1111001010011100 "
b1111001010011100 $
b1111001010011100 &
b1101011 %
#108
b1001100111111010 !
b1001100111111010 '
1-
1,
00
0/
19
18
1<
1;
1B
1A
0E
0D
1K
1J
0Q
0P
0T
0S
b1001100111111010 "
b1001100111111010 $
b1001100111111010 &
b1101100 %
#109
b1011110000100110 !
b1011110000100110 '
10
1/
03
02
06
05
0<
0;
0?
0>
0B
0A
1H
1G
1Q
1P
b1011110000100110 "
b1011110000100110 $
b1011110000100110 &
b1101101 %
#110
b1011101110011 !
b1011101110011 '
1*
1)
00
0/
16
15
1<
1;
1B
1A
1E
1D
0K
0J
0Q
0P
0W
0V
b1011101110011 "
b1011101110011 $
b1011101110011 &
b1101110 %
#111
b1011010010100011 !
b1011010010100011 '
06
05
0<
0;
1?
1>
0B
0A
0E
0D
1Q
1P
1W
1V
b1011010010100011 "
b1011010010100011 $
b1011010010100011 &
b1101111 %
#112
b1010100000101111 !
b1010100000101111 '
10
1/
13
12
0?
0>
0H
0G
1K
1J
0N
0M
b1010100000101111 "
b1010100000101111 $
b1010100000101111 &
b1110000 %
#113
b1001001010110011 !
b1001001010110011 '
00
0/
03
02
16
15
1?
1>
1E
1D
0K
0J
1N
1M
0Q
0P
b1001001010110011 "
b1001001010110011 $
b1001001010110011 &
b1110001 %
#114
b101011001011111 !
b101011001011111 '
10
1/
13
12
09
08
1<
1;
0?
0>
1H
1G
1T
1S
0W
0V
b101011001011111 "
b101011001011111 $
b101011001011111 &
b1110010 %
#115
b110101000100 !
b110101000100 '
0*
0)
0-
0,
03
02
06
05
1B
1A
0E
0D
1K
1J
0N
0M
0T
0S
b110101000100 "
b110101000100 $
b110101000100 &
b1110011 %
#116
b1111110111110111 !
b1111110111110111 '
1*
1)
1-
1,
16
15
19
18
1?
1>
1N
1M
1Q
1P
1T
1S
1W
1V
b1111110111110111 "
b1111110111110111 $
b1111110111110111 &
b1110100 %
#117
b11011011001011 !
b11011011001011 '
00
0/
13
12
06
05
09
08
0B
0A
1E
1D
0K
0J
0T
0S
0W
0V
b11011011001011 "
b11011011001011 $
b11011011001011 &
b1110101 %
#118
b1101011100110 !
b1101011100110 '
0*
0)
10
1/
03
02
19
18
0H
0G
1K
1J
0Q
0P
b1101011100110 "
b1101011100110 $
b1101011100110 &
b1110110 %
#119
b1101101101011010 !
b1101101101011010 '
00
0/
13
12
16
15
09
08
0?
0>
1B
1A
1T
1S
1W
1V
b1101101101011010 "
b1101101101011010 $
b1101101101011010 &
b1110111 %
#120
b1100000100101001 !
b1100000100101001 '
1*
1)
0-
0,
06
05
19
18
0<
0;
0E
0D
0K
0J
0N
0M
b1100000100101001 "
b1100000100101001 $
b1100000100101001 &
b1111000 %
#121
b1110001011101101 !
b1110001011101101 '
10
1/
1<
1;
1?
1>
0B
0A
1E
1D
1Q
1P
b1110001011101101 "
b1110001011101101 $
b1110001011101101 &
b1111001 %
#122
b110110011011010 !
b110110011011010 '
0*
0)
1-
1,
00
0/
16
15
09
08
0E
0D
1H
1G
1K
1J
0W
0V
b110110011011010 "
b110110011011010 $
b110110011011010 &
b1111010 %
