01_Boolean_Logic/Mux.v
/** 
 * Multiplexor:
 * out = a if sel == 0
 *       b otherwise
 */

`default_nettype none
module Mux(
  input a,
  input b,
  input sel,
  output out
);

  assign out = sel ? b : a ;

endmodule

01_Boolean_Logic/06_Mux/Mux_tb.v
`default_nettype none
module Mux_tb();

	// IN,OUT
	reg a,b,sel;
	wire out;

	// Part
	Mux MUX(
		.a(a),
		.b(b),
		.sel(sel),
		.out(out)
	);
	
	// Compare
	wire out_cmp;
	assign out_cmp = (sel?b:a);
	
	reg fail = 0;
	task check;
		#1
		if (out != out_cmp) 
			begin
				$display("FAIL: a=%1b, b=%1b, sel=%1b, out=%1b",a,b,sel,out);
				fail=1;
			end
	endtask
	 
	// Test 
  	initial begin
		$dumpvars(0, Mux_tb);
		
		$display("------------------------");
		$display("Testbench: Mux");
		
		a=0;b=0;sel=0;check();
		a=0;b=0;sel=1;check();
		a=0;b=1;sel=0;check();
		a=0;b=1;sel=1;check();
		a=1;b=0;sel=0;check();
		a=1;b=0;sel=1;check();
		a=1;b=1;sel=0;check();
		a=1;b=1;sel=1;check();
		
		if (fail==0) $display("passed");
		$display("------------------------");
		$finish;
	end

endmodule

01_Boolean_Logic/06_Mux/_build/default/Mux_tb.vcd
$date
	Thu Mar 26 12:44:30 2026
$end
$version
	Icarus Verilog
$end
$timescale
	1ps
$end
$scope module Mux_tb $end
$var wire 1 ! out_cmp $end
$var wire 1 " out $end
$var reg 1 # a $end
$var reg 1 $ b $end
$var reg 1 % fail $end
$var reg 1 & sel $end
$scope module MUX $end
$var wire 1 # a $end
$var wire 1 $ b $end
$var wire 1 & sel $end
$var wire 1 " out $end
$upscope $end
$scope task check $end
$upscope $end
$upscope $end
$enddefinitions $end
$comment Show the parameter values. $end
$dumpall
$end
#0
$dumpvars
0&
0%
0$
0#
0"
0!
$end
#1
1&
#2
0&
1$
#3
1!
1"
1&
#4
0&
0$
1#
#5
0!
0"
1&
#6
1!
1"
0&
1$
#7
1&
