02_Boolean_Arithmetic/FullAdder.v
/**
 * Computes the sum of three bits.
 */

`default_nettype none
module FullAdder (
  input a,  //1-bit input
  input b,  //1-bit input
  input c,  //1-bit input
  output sum,  //Right bit of a + b + c
  output carry  //Left bit of a + b + c
);

  assign sum   = (a ^ b) ^ c;
  assign carry = (a & b) | (b & c) | (c & a);

endmodule

02_Boolean_Arithmetic/02_FullAdder/FullAdder_tb.v
`default_nettype none
module FullAdder_tb();

	// IN,OUT
	reg a,b,c;
	wire sum,carry;

	// Part
	FullAdder FULLADDER(
		.a(a),
		.b(b),
		.c(c),
		.sum(sum),
		.carry(carry)
	);

	// Compare
	wire [1:0] out_cmp;
	assign out_cmp = a+b+c;

	reg fail = 0;
	task check;
		#1
		if ({carry,sum} != out_cmp) 
			begin
				$display("FAIL: a=%1b, b=%1b, c=%1b, sum=%1b, carry=%1b",a,b,c,sum,carry);
				fail=1;
			end
	endtask
	  
  	initial begin
  		$dumpvars(0, FullAdder_tb);
		
		$display("------------------------");
		$display("Testbench: FullAdder");
		
		a=0;b=0;c=0;check();
		a=0;b=0;c=1;check();
		a=0;b=1;c=0;check();
		a=0;b=1;c=1;check();
		a=1;b=0;c=0;check();
		a=1;b=0;c=1;check();
		a=1;b=1;c=0;check();
		a=1;b=1;c=1;check();
		
		if (fail==0) $display("passed");
		$display("------------------------");
		$finish;
	end

endmodule

02_Boolean_Arithmetic/02_FullAdder/_build/default/FullAdder_tb.vcd
$date
	Tue Aug  4 23:22:14 2026
$end
$version
	Icarus Verilog
$end
$timescale
	1ps
$end
$scope module FullAdder_tb $end
$var wire 1 ! sum $end
$var wire 2 " out_cmp [1:0] $end
$var wire 1 # carry $end
$var reg 1 $ a $end
$var reg 1 % b $end
$var reg 1 & c $end
$var reg 1 ' fail $end
$scope module FULLADDER $end
$var wire 1 $ a $end
$var wire 1 % b $end
$var wire 1 & c $end
$var wire 1 # carry $end
$var wire 1 ! sum $end
$upscope $end
$scope task check $end
$upscope $end
$upscope $end
$enddefinitions $end
$comment Show the parameter values. $end
$dumpall
$end
#0
$dumpvars
0'
0&
0%
0$
0#
b0 "
0!
$end
#1
b1 "
1!
1&
#2
b1 "
0&
1%
#3
1#
b10 "
0!
1&
#4
0#
1!
b1 "
0&
0%
1$
#5
1#
b10 "
0!
1&
#6
b10 "
0&
1%
#7
b11 "
1!
1&
