03_Sequential_Logic/Register.v
/**
 * 16-bit register:
 * If load[t] == 1 then out[t+1] = in[t]
 * else out does not change
 */

`default_nettype none

module Register(
  input clk,
  input [15:0] in,
  input load,
  output reg [15:0] out
);

// put code here
  always @(posedge clk) begin
    if (load) begin
      out <= in;
    end
  end

endmodule

03_Sequential_Logic/02_Register/Register_tb.v
`default_nettype none
module Register_tb();

	// IN,OUT
	reg clk = 1;
	reg [15:0] in;
	reg load;
	wire [15:0] out;

	// Part
	Register REGISTER(
		.clk(clk),
		.in(in),
		.load(load),
		.out(out)
	);
	
	// Compare
	always #1 clk=~clk;
	always @(posedge clk) begin
		in <= $random;	
		load <= $random;
	end
	reg [15:0] out_cmp;
	always @(posedge clk)
		out_cmp <= (load?in:out);	
	reg fail = 0;
	reg [15:0] n = 0;
	task check;
		#1
		if (out != out_cmp) 
			begin
				$display("FAIL: clk=%1b, in=%16b, load=%1b, out=%16b",clk,in,load,out);
				fail=1;
			end
	endtask
	  
  	initial begin
  		$dumpvars(0, Register_tb);
		
		$display("------------------------");
		$display("Testbench: Register");

		for (n=0; n<1000;n=n+1) 
			check();
		
		if (fail==0) $display("passed");
		$display("------------------------");
		$finish;
	end

endmodule

03_Sequential_Logic/02_Register/_build/default/Register_tb.vcd
$date
	Wed Aug  5 00:14:38 2026
$end
$version
	Icarus Verilog
$end
$timescale
	1ps
$end
$scope module Register_tb $end
$var wire 16 ! out [15:0] $end
$var reg 1 " clk $end
$var reg 1 # fail $end
$var reg 16 $ in [15:0] $end
$var reg 1 % load $end
$var reg 16 & n [15:0] $end
$var reg 16 ' out_cmp [15:0] $end
$scope module REGISTER $end
$var wire 1 " clk $end
$var wire 16 ( in [15:0] $end
$var wire 1 % load $end
$var reg 16 ) out [15:0] $end
$upscope $end
$scope task check $end
$upscope $end
$upscope $end
$enddefinitions $end
$comment Show the parameter values. $end
$dumpall
$end
#0
$dumpvars
bx )
bx (
bx '
b0 &
x%
bx $
0#
1"
bx !
$end
#1
b1 &
0"
#2
1%
b11010100100100 $
b11010100100100 (
b10 &
1"
#3
b11 &
0"
#4
b11010100100100 '
b1101011000001001 $
b1101011000001001 (
b11010100100100 !
b11010100100100 )
b100 &
1"
#5
b101 &
0"
#6
b1101011000001001 !
b1101011000001001 )
b111101100001101 $
b111101100001101 (
b1101011000001001 '
b110 &
1"
#7
b111 &
0"
#8
b111101100001101 '
0%
b1000010001100101 $
b1000010001100101 (
b111101100001101 !
b111101100001101 )
b1000 &
1"
#9
b1001 &
0"
#10
1%
b1110001100000001 $
b1110001100000001 (
b1010 &
1"
#11
b1011 &
0"
#12
b1110001100000001 '
b1111000101110110 $
b1111000101110110 (
b1110001100000001 !
b1110001100000001 )
b1100 &
1"
#13
b1101 &
0"
#14
b1111000101110110 !
b1111000101110110 )
0%
b101011111101101 $
b101011111101101 (
b1111000101110110 '
b1110 &
1"
#15
b1111 &
0"
#16
b1110100111111001 $
b1110100111111001 (
b10000 &
1"
#17
b10001 &
0"
#18
b1000010011000101 $
b1000010011000101 (
b10010 &
1"
#19
b10011 &
0"
#20
1%
b1111011111100101 $
b1111011111100101 (
b10100 &
1"
#21
b10101 &
0"
#22
b1111011111100101 !
b1111011111100101 )
b1101011000010010 $
b1101011000010010 (
b1111011111100101 '
b10110 &
1"
#23
b10111 &
0"
#24
b1101011000010010 '
0%
b110100111110010 $
b110100111110010 (
b1101011000010010 !
b1101011000010010 )
b11000 &
1"
#25
b11001 &
0"
#26
1%
b111101011101000 $
b111101011101000 (
b11010 &
1"
#27
b11011 &
0"
#28
b111101011101000 '
b100100101011100 $
b100100101011100 (
b111101011101000 !
b111101011101000 )
b11100 &
1"
#29
b11101 &
0"
#30
b100100101011100 !
b100100101011100 )
b101100000101101 $
b101100000101101 (
b100100101011100 '
b11110 &
1"
#31
b11111 &
0"
#32
b101100000101101 '
0%
b110001001100011 $
b110001001100011 (
b101100000101101 !
b101100000101101 )
b100000 &
1"
#33
b100001 &
0"
#34
b10001010000000 $
b10001010000000 (
b100010 &
1"
#35
b100011 &
0"
#36
1%
b100010110101010 $
b100010110101010 (
b100100 &
1"
#37
b100101 &
0"
#38
b100010110101010 !
b100010110101010 )
b11111010010110 $
b11111010010110 (
b100010110101010 '
b100110 &
1"
#39
b100111 &
0"
#40
b11111010010110 '
b11100000001101 $
b11100000001101 (
b11111010010110 !
b11111010010110 )
b101000 &
1"
#41
b101001 &
0"
#42
b11100000001101 !
b11100000001101 )
b1101110101101011 $
b1101110101101011 (
b11100000001101 '
b101010 &
1"
#43
b101011 &
0"
#44
b1101110101101011 '
0%
b100101000000010 $
b100101000000010 (
b1101110101101011 !
b1101110101101011 )
b101100 &
1"
#45
b101101 &
0"
#46
1%
b1110100100011101 $
b1110100100011101 (
b101110 &
1"
#47
b101111 &
0"
#48
b1110100100011101 '
0%
b100100100100011 $
b100100100100011 (
b1110100100011101 !
b1110100100011101 )
b110000 &
1"
#49
b110001 &
0"
#50
b101011001010 $
b101011001010 (
b110010 &
1"
#51
b110011 &
0"
#52
b1011110111110010 $
b1011110111110010 (
b110100 &
1"
#53
b110101 &
0"
#54
b1011001101000001 $
b1011001101000001 (
b110110 &
1"
#55
b110111 &
0"
#56
1%
b1111001101111000 $
b1111001101111000 (
b111000 &
1"
#57
b111001 &
0"
#58
b1111001101111000 !
b1111001101111000 )
0%
b110111101011 $
b110111101011 (
b1111001101111000 '
b111010 &
1"
#59
b111011 &
0"
#60
b1111100111000110 $
b1111100111000110 (
b111100 &
1"
#61
b111101 &
0"
#62
b1010111100 $
b1010111100 (
b111110 &
1"
#63
b111111 &
0"
#64
1%
b1001101000001011 $
b1001101000001011 (
b1000000 &
1"
#65
b1000001 &
0"
#66
b1001101000001011 !
b1001101000001011 )
b100000110000101 $
b100000110000101 (
b1001101000001011 '
b1000010 &
1"
#67
b1000011 &
0"
#68
b100000110000101 '
0%
b110000000111011 $
b110000000111011 (
b100000110000101 !
b100000110000101 )
b1000100 &
1"
#69
b1000101 &
0"
#70
1%
b11001001111110 $
b11001001111110 (
b1000110 &
1"
#71
b1000111 &
0"
#72
b11001001111110 '
b1001101111110001 $
b1001101111110001 (
b11001001111110 !
b11001001111110 )
b1001000 &
1"
#73
b1001001 &
0"
#74
b1001101111110001 !
b1001101111110001 )
0%
b11101100010 $
b11101100010 (
b1001101111110001 '
b1001010 &
1"
#75
b1001011 &
0"
#76
1%
b101010110011111 $
b101010110011111 (
b1001100 &
1"
#77
b1001101 &
0"
#78
b101010110011111 !
b101010110011111 )
b1010100111111000 $
b1010100111111000 (
b101010110011111 '
b1001110 &
1"
#79
b1001111 &
0"
#80
b1010100111111000 '
0%
b101011010011111 $
b101011010011111 (
b1010100111111000 !
b1010100111111000 )
b1010000 &
1"
#81
b1010001 &
0"
#82
1%
b1100000001011011 $
b1100000001011011 (
b1010010 &
1"
#83
b1010011 &
0"
#84
b1100000001011011 '
0%
b11001001001001 $
b11001001001001 (
b1100000001011011 !
b1100000001011011 )
b1010100 &
1"
#85
b1010101 &
0"
#86
1%
b1100000011010111 $
b1100000011010111 (
b1010110 &
1"
#87
b1010111 &
0"
#88
b1100000011010111 '
0%
b10111110010110 $
b10111110010110 (
b1100000011010111 !
b1100000011010111 )
b1011000 &
1"
#89
b1011001 &
0"
#90
b1100111011000010 $
b1100111011000010 (
b1011010 &
1"
#91
b1011011 &
0"
#92
1%
b101101001110111 $
b101101001110111 (
b1011100 &
1"
#93
b1011101 &
0"
#94
b101101001110111 !
b101101001110111 )
0%
b1101101100010010 $
b1101101100010010 (
b101101001110111 '
b1011110 &
1"
#95
b1011111 &
0"
#96
1%
b1000000101101101 $
b1000000101101101 (
b1100000 &
1"
#97
b1100001 &
0"
#98
b1000000101101101 !
b1000000101101101 )
b1000111100011111 $
b1000111100011111 (
b1000000101101101 '
b1100010 &
1"
#99
b1100011 &
0"
#100
b1000111100011111 '
0%
b10111110000101 $
b10111110000101 (
b1000111100011111 !
b1000111100011111 )
b1100100 &
1"
#101
b1100101 &
0"
#102
1%
b101100101011011 $
b101100101011011 (
b1100110 &
1"
#103
b1100111 &
0"
#104
b101100101011011 '
0%
b1010111000111111 $
b1010111000111111 (
b101100101011011 !
b101100101011011 )
b1101000 &
1"
#105
b1101001 &
0"
#106
b110001101011000 $
b110001101011000 (
b1101010 &
1"
#107
b1101011 &
0"
#108
b110010001110 $
b110010001110 (
b1101100 &
1"
#109
b1101101 &
0"
#110
b1001100111111010 $
b1001100111111010 (
b1101110 &
1"
#111
b1101111 &
0"
#112
1%
b1011101110011 $
b1011101110011 (
b1110000 &
1"
#113
b1110001 &
0"
#114
b1011101110011 !
b1011101110011 )
b1010100000101111 $
b1010100000101111 (
b1011101110011 '
b1110010 &
1"
#115
b1110011 &
0"
#116
b1010100000101111 '
0%
b101011001011111 $
b101011001011111 (
b1010100000101111 !
b1010100000101111 )
b1110100 &
1"
#117
b1110101 &
0"
#118
1%
b1111110111110111 $
b1111110111110111 (
b1110110 &
1"
#119
b1110111 &
0"
#120
b1111110111110111 '
0%
b1101011100110 $
b1101011100110 (
b1111110111110111 !
b1111110111110111 )
b1111000 &
1"
#121
b1111001 &
0"
#122
1%
b1100000100101001 $
b1100000100101001 (
b1111010 &
1"
#123
b1111011 &
0"
#124
b1100000100101001 '
b110110011011010 $
b110110011011010 (
b1100000100101001 !
b1100000100101001 )
b1111100 &
1"
#125
b1111101 &
0"
#126
b110110011011010 !
b110110011011010 )
b1110001010110101 $
b1110001010110101 (
b110110011011010 '
b1111110 &
1"
#127
b1111111 &
0"
#128
b1110001010110101 '
0%
b1100101111001 $
b1100101111001 (
b1110001010110101 !
b1110001010110101 )
b10000000 &
1"
#129
b10000001 &
0"
#130
b110011010000 $
b110011010000 (
b10000010 &
1"
#131
b10000011 &
0"
#132
b1010110110101011 $
b1010110110101011 (
b10000100 &
1"
#133
b10000101 &
0"
#134
b1010110111011100 $
b1010110111011100 (
b10000110 &
1"
#135
b10000111 &
0"
#136
1%
b111001011111101 $
b111001011111101 (
b10001000 &
1"
#137
b10001001 &
0"
#138
b111001011111101 !
b111001011111101 )
0%
b1110110101010110 $
b1110110101010110 (
b111001011111101 '
b10001010 &
1"
#139
b10001011 &
0"
#140
b111011001100111 $
b111011001100111 (
b10001100 &
1"
#141
b10001101 &
0"
#142
b1011100110110110 $
b1011100110110110 (
b10001110 &
1"
#143
b10001111 &
0"
#144
b1000011101111001 $
b1000011101111001 (
b10010000 &
1"
#145
b10010001 &
0"
#146
1%
b1011111110010100 $
b1011111110010100 (
b10010010 &
1"
#147
b10010011 &
0"
#148
b1011111110010100 '
b10110000000100 $
b10110000000100 (
b1011111110010100 !
b1011111110010100 )
b10010100 &
1"
#149
b10010101 &
0"
#150
b10110000000100 !
b10110000000100 )
b110100111011011 $
b110100111011011 (
b10110000000100 '
b10010110 &
1"
#151
b10010111 &
0"
#152
b110100111011011 '
b1011011111011001 $
b1011011111011001 (
b110100111011011 !
b110100111011011 )
b10011000 &
1"
#153
b10011001 &
0"
#154
b1011011111011001 !
b1011011111011001 )
0%
b1110001001110110 $
b1110001001110110 (
b1011011111011001 '
b10011010 &
1"
#155
b10011011 &
0"
#156
1%
b10110110110110 $
b10110110110110 (
b10011100 &
1"
#157
b10011101 &
0"
#158
b10110110110110 !
b10110110110110 )
0%
b1101001000110 $
b1101001000110 (
b10110110110110 '
b10011110 &
1"
#159
b10011111 &
0"
#160
1%
b110000111110111 $
b110000111110111 (
b10100000 &
1"
#161
b10100001 &
0"
#162
b110000111110111 !
b110000111110111 )
0%
b1011101010110100 $
b1011101010110100 (
b110000111110111 '
b10100010 &
1"
#163
b10100011 &
0"
#164
1%
b1101100100101000 $
b1101100100101000 (
b10100100 &
1"
#165
b10100101 &
0"
#166
b1101100100101000 !
b1101100100101000 )
0%
b11000011000111 $
b11000011000111 (
b1101100100101000 '
b10100110 &
1"
#167
b10100111 &
0"
#168
b1110010000001000 $
b1110010000001000 (
b10101000 &
1"
#169
b10101001 &
0"
#170
1%
b1010011011111101 $
b1010011011111101 (
b10101010 &
1"
#171
b10101011 &
0"
#172
b1010011011111101 '
0%
b1001000000011100 $
b1001000000011100 (
b1010011011111101 !
b1010011011111101 )
b10101100 &
1"
#173
b10101101 &
0"
#174
1%
b100011011010 $
b100011011010 (
b10101110 &
1"
#175
b10101111 &
0"
#176
b100011011010 '
0%
b1010011101100110 $
b1010011101100110 (
b100011011010 !
b100011011010 )
b10110000 &
1"
#177
b10110001 &
0"
#178
b10001110011 $
b10001110011 (
b10110010 &
1"
#179
b10110011 &
0"
#180
b1011001101011110 $
b1011001101011110 (
b10110100 &
1"
#181
b10110101 &
0"
#182
b10111010101 $
b10111010101 (
b10110110 &
1"
#183
b10110111 &
0"
#184
1%
b10111001 $
b10111001 (
b10111000 &
1"
#185
b10111001 &
0"
#186
b10111001 !
b10111001 )
0%
b11011110010110 $
b11011110010110 (
b10111001 '
b10111010 &
1"
#187
b10111011 &
0"
#188
b1001111100100110 $
b1001111100100110 (
b10111100 &
1"
#189
b10111101 &
0"
#190
b1000001101111101 $
b1000001101111101 (
b10111110 &
1"
#191
b10111111 &
0"
#192
b101011110000110 $
b101011110000110 (
b11000000 &
1"
#193
b11000001 &
0"
#194
1%
b1001101101111110 $
b1001101101111110 (
b11000010 &
1"
#195
b11000011 &
0"
#196
b1001101101111110 '
b1011011011001111 $
b1011011011001111 (
b1001101101111110 !
b1001101101111110 )
b11000100 &
1"
#197
b11000101 &
0"
#198
b1011011011001111 !
b1011011011001111 )
b1110010011111010 $
b1110010011111010 (
b1011011011001111 '
b11000110 &
1"
#199
b11000111 &
0"
#200
b1110010011111010 '
b100100010111 $
b100100010111 (
b1110010011111010 !
b1110010011111010 )
b11001000 &
1"
#201
b11001001 &
0"
#202
b100100010111 !
b100100010111 )
0%
b1001000110000110 $
b1001000110000110 (
b100100010111 '
b11001010 &
1"
#203
b11001011 &
0"
#204
1%
b101100111110101 $
b101100111110101 (
b11001100 &
1"
#205
b11001101 &
0"
#206
b101100111110101 !
b101100111110101 )
b1000101000101001 $
b1000101000101001 (
b101100111110101 '
b11001110 &
1"
#207
b11001111 &
0"
#208
b1000101000101001 '
0%
b111010011000101 $
b111010011000101 (
b1000101000101001 !
b1000101000101001 )
b11010000 &
1"
#209
b11010001 &
0"
#210
1%
b111101101001011 $
b111101101001011 (
b11010010 &
1"
#211
b11010011 &
0"
#212
b111101101001011 '
0%
b1110011011101100 $
b1110011011101100 (
b111101101001011 !
b111101101001011 )
b11010100 &
1"
#213
b11010101 &
0"
#214
b1101000101001110 $
b1101000101001110 (
b11010110 &
1"
#215
b11010111 &
0"
#216
1%
b1111110110101001 $
b1111110110101001 (
b11011000 &
1"
#217
b11011001 &
0"
#218
b1111110110101001 !
b1111110110101001 )
0%
b1011100100001110 $
b1011100100001110 (
b1111110110101001 '
b11011010 &
1"
#219
b11011011 &
0"
#220
b1100000010011111 $
b1100000010011111 (
b11011100 &
1"
#221
b11011101 &
0"
#222
1%
b1110100101010 $
b1110100101010 (
b11011110 &
1"
#223
b11011111 &
0"
#224
b1110100101010 '
0%
b1111111110011110 $
b1111111110011110 (
b1110100101010 !
b1110100101010 )
b11100000 &
1"
#225
b11100001 &
0"
#226
b1010100001111001 $
b1010100001111001 (
b11100010 &
1"
#227
b11100011 &
0"
#228
1%
b100010111001010 $
b100010111001010 (
b11100100 &
1"
#229
b11100101 &
0"
#230
b100010111001010 !
b100010111001010 )
b1100100101101011 $
b1100100101101011 (
b100010111001010 '
b11100110 &
1"
#231
b11100111 &
0"
#232
b1100100101101011 '
0%
b1101110110110110 $
b1101110110110110 (
b1100100101101011 !
b1100100101101011 )
b11101000 &
1"
#233
b11101001 &
0"
#234
1%
b1010101111000100 $
b1010101111000100 (
b11101010 &
1"
#235
b11101011 &
0"
#236
b1010101111000100 '
0%
b1101001110010010 $
b1101001110010010 (
b1010101111000100 !
b1010101111000100 )
b11101100 &
1"
#237
b11101101 &
0"
#238
b11101101111111 $
b11101101111111 (
b11101110 &
1"
#239
b11101111 &
0"
#240
b1111010111111010 $
b1111010111111010 (
b11110000 &
1"
#241
b11110001 &
0"
#242
1%
b10000100110010 $
b10000100110010 (
b11110010 &
1"
#243
b11110011 &
0"
#244
b10000100110010 '
0%
b1100110110000100 $
b1100110110000100 (
b10000100110010 !
b10000100110010 )
b11110100 &
1"
#245
b11110101 &
0"
#246
1%
b1100111111001010 $
b1100111111001010 (
b11110110 &
1"
#247
b11110111 &
0"
#248
b1100111111001010 '
0%
b1010100010100001 $
b1010100010100001 (
b1100111111001010 !
b1100111111001010 )
b11111000 &
1"
#249
b11111001 &
0"
#250
1%
b110101011111011 $
b110101011111011 (
b11111010 &
1"
#251
b11111011 &
0"
#252
b110101011111011 '
b1001000011101111 $
b1001000011101111 (
b110101011111011 !
b110101011111011 )
b11111100 &
1"
#253
b11111101 &
0"
#254
b1001000011101111 !
b1001000011101111 )
b1110010100110110 $
b1110010100110110 (
b1001000011101111 '
b11111110 &
1"
#255
b11111111 &
0"
#256
b1110010100110110 '
b101011010001111 $
b101011010001111 (
b1110010100110110 !
b1110010100110110 )
b100000000 &
1"
#257
b100000001 &
0"
#258
b101011010001111 !
b101011010001111 )
0%
b1110011110001000 $
b1110011110001000 (
b101011010001111 '
b100000010 &
1"
#259
b100000011 &
0"
#260
b1000000110011011 $
b1000000110011011 (
b100000100 &
1"
#261
b100000101 &
0"
#262
1%
b1101111100101000 $
b1101111100101000 (
b100000110 &
1"
#263
b100000111 &
0"
#264
b1101111100101000 '
0%
b101111101001011 $
b101111101001011 (
b1101111100101000 !
b1101111100101000 )
b100001000 &
1"
#265
b100001001 &
0"
#266
1%
b1111011000011110 $
b1111011000011110 (
b100001010 &
1"
#267
b100001011 &
0"
#268
b1111011000011110 '
0%
b1111110111101100 $
b1111110111101100 (
b1111011000011110 !
b1111011000011110 )
b100001100 &
1"
#269
b100001101 &
0"
#270
b1101111010001 $
b1101111010001 (
b100001110 &
1"
#271
b100001111 &
0"
#272
1%
b10010001000001 $
b10010001000001 (
b100010000 &
1"
#273
b100010001 &
0"
#274
b10010001000001 !
b10010001000001 )
b1111100111011000 $
b1111100111011000 (
b10010001000001 '
b100010010 &
1"
#275
b100010011 &
0"
#276
b1111100111011000 '
b110001001010110 $
b110001001010110 (
b1111100111011000 !
b1111100111011000 )
b100010100 &
1"
#277
b100010101 &
0"
#278
b110001001010110 !
b110001001010110 )
0%
b1111101011100010 $
b1111101011100010 (
b110001001010110 '
b100010110 &
1"
#279
b100010111 &
0"
#280
b1101110011 $
b1101110011 (
b100011000 &
1"
#281
b100011001 &
0"
#282
b100110100010010 $
b100110100010010 (
b100011010 &
1"
#283
b100011011 &
0"
#284
1%
b1001000111001 $
b1001000111001 (
b100011100 &
1"
#285
b100011101 &
0"
#286
b1001000111001 !
b1001000111001 )
b1101110010100001 $
b1101110010100001 (
b1001000111001 '
b100011110 &
1"
#287
b100011111 &
0"
#288
b1101110010100001 '
0%
b101110110000001 $
b101110110000001 (
b1101110010100001 !
b1101110010100001 )
b100100000 &
1"
#289
b100100001 &
0"
#290
1%
b101010100100111 $
b101010100100111 (
b100100010 &
1"
#291
b100100011 &
0"
#292
b101010100100111 '
0%
b110111000011111 $
b110111000011111 (
b101010100100111 !
b101010100100111 )
b100100100 &
1"
#293
b100100101 &
0"
#294
b10001101011000 $
b10001101011000 (
b100100110 &
1"
#295
b100100111 &
0"
#296
b1001001100010100 $
b1001001100010100 (
b100101000 &
1"
#297
b100101001 &
0"
#298
1%
b111000010010110 $
b111000010010110 (
b100101010 &
1"
#299
b100101011 &
0"
#300
b111000010010110 '
b1101010101010101 $
b1101010101010101 (
b111000010010110 !
b111000010010110 )
b100101100 &
1"
#301
b100101101 &
0"
#302
b1101010101010101 !
b1101010101010101 )
b10101100101011 $
b10101100101011 (
b1101010101010101 '
b100101110 &
1"
#303
b100101111 &
0"
#304
b10101100101011 '
b1110101101 $
b1110101101 (
b10101100101011 !
b10101100101011 )
b100110000 &
1"
#305
b100110001 &
0"
#306
b1110101101 !
b1110101101 )
b1111111110000100 $
b1111111110000100 (
b1110101101 '
b100110010 &
1"
#307
b100110011 &
0"
#308
b1111111110000100 '
b1010011011100111 $
b1010011011100111 (
b1111111110000100 !
b1111111110000100 )
b100110100 &
1"
#309
b100110101 &
0"
#310
b1010011011100111 !
b1010011011100111 )
b101011001001001 $
b101011001001001 (
b1010011011100111 '
b100110110 &
1"
#311
b100110111 &
0"
#312
b101011001001001 '
b111111001001 $
b111111001001 (
b101011001001001 !
b101011001001001 )
b100111000 &
1"
#313
b100111001 &
0"
#314
b111111001001 !
b111111001001 )
0%
b101111010100001 $
b101111010100001 (
b111111001001 '
b100111010 &
1"
#315
b100111011 &
0"
#316
1%
b100010111111010 $
b100010111111010 (
b100111100 &
1"
#317
b100111101 &
0"
#318
b100010111111010 !
b100010111111010 )
0%
b10110000011 $
b10110000011 (
b100010111111010 '
b100111110 &
1"
#319
b100111111 &
0"
#320
b1010001110010 $
b1010001110010 (
b101000000 &
1"
#321
b101000001 &
0"
#322
1%
b1111001001101000 $
b1111001001101000 (
b101000010 &
1"
#323
b101000011 &
0"
#324
b1111001001101000 '
0%
b110110000110 $
b110110000110 (
b1111001001101000 !
b1111001001101000 )
b101000100 &
1"
#325
b101000101 &
0"
#326
b1001011100111000 $
b1001011100111000 (
b101000110 &
1"
#327
b101000111 &
0"
#328
b111011000101000 $
b111011000101000 (
b101001000 &
1"
#329
b101001001 &
0"
#330
b1101011000101 $
b1101011000101 (
b101001010 &
1"
#331
b101001011 &
0"
#332
1%
b101111101110100 $
b101111101110100 (
b101001100 &
1"
#333
b101001101 &
0"
#334
b101111101110100 !
b101111101110100 )
0%
b110101010110000 $
b110101010110000 (
b101111101110100 '
b101001110 &
1"
#335
b101001111 &
0"
#336
b1001001100101010 $
b1001001100101010 (
b101010000 &
1"
#337
b101010001 &
0"
#338
1%
b11010100010101 $
b11010100010101 (
b101010010 &
1"
#339
b101010011 &
0"
#340
b11010100010101 '
b1001110100010111 $
b1001110100010111 (
b11010100010101 !
b11010100010101 )
b101010100 &
1"
#341
b101010101 &
0"
#342
b1001110100010111 !
b1001110100010111 )
0%
b1110001111001001 $
b1110001111001001 (
b1001110100010111 '
b101010110 &
1"
#343
b101010111 &
0"
#344
1%
b1100101100100101 $
b1100101100100101 (
b101011000 &
1"
#345
b101011001 &
0"
#346
b1100101100100101 !
b1100101100100101 )
0%
b1010001010001101 $
b1010001010001101 (
b1100101100100101 '
b101011010 &
1"
#347
b101011011 &
0"
#348
b10011100000111 $
b10011100000111 (
b101011100 &
1"
#349
b101011101 &
0"
#350
1%
b101110100001100 $
b101110100001100 (
b101011110 &
1"
#351
b101011111 &
0"
#352
b101110100001100 '
0%
b111110000111011 $
b111110000111011 (
b101110100001100 !
b101110100001100 )
b101100000 &
1"
#353
b101100001 &
0"
#354
b1100001011110111 $
b1100001011110111 (
b101100010 &
1"
#355
b101100011 &
0"
#356
1%
b101100001011100 $
b101100001011100 (
b101100100 &
1"
#357
b101100101 &
0"
#358
b101100001011100 !
b101100001011100 )
0%
b11101000100000 $
b11101000100000 (
b101100001011100 '
b101100110 &
1"
#359
b101100111 &
0"
#360
b100101110010 $
b100101110010 (
b101101000 &
1"
#361
b101101001 &
0"
#362
1%
b1111010111011101 $
b1111010111011101 (
b101101010 &
1"
#363
b101101011 &
0"
#364
b1111010111011101 '
b1001100101001011 $
b1001100101001011 (
b1111010111011101 !
b1111010111011101 )
b101101100 &
1"
#365
b101101101 &
0"
#366
b1001100101001011 !
b1001100101001011 )
b1101101010011110 $
b1101101010011110 (
b1001100101001011 '
b101101110 &
1"
#367
b101101111 &
0"
#368
b1101101010011110 '
b1101001001111011 $
b1101001001111011 (
b1101101010011110 !
b1101101010011110 )
b101110000 &
1"
#369
b101110001 &
0"
#370
b1101001001111011 !
b1101001001111011 )
b1001101000000011 $
b1001101000000011 (
b1101001001111011 '
b101110010 &
1"
#371
b101110011 &
0"
#372
b1001101000000011 '
b100001100011101 $
b100001100011101 (
b1001101000000011 !
b1001101000000011 )
b101110100 &
1"
#373
b101110101 &
0"
#374
b100001100011101 !
b100001100011101 )
b1001111101000100 $
b1001111101000100 (
b100001100011101 '
b101110110 &
1"
#375
b101110111 &
0"
#376
b1001111101000100 '
b11010011100000 $
b11010011100000 (
b1001111101000100 !
b1001111101000100 )
b101111000 &
1"
#377
b101111001 &
0"
#378
b11010011100000 !
b11010011100000 )
0%
b1010101010010 $
b1010101010010 (
b11010011100000 '
b101111010 &
1"
#379
b101111011 &
0"
#380
b1011011110001101 $
b1011011110001101 (
b101111100 &
1"
#381
b101111101 &
0"
#382
b1110011110000100 $
b1110011110000100 (
b101111110 &
1"
#383
b101111111 &
0"
#384
b1001001010001100 $
b1001001010001100 (
b110000000 &
1"
#385
b110000001 &
0"
#386
b1100000100010111 $
b1100000100010111 (
b110000010 &
1"
#387
b110000011 &
0"
#388
b101011110000100 $
b101011110000100 (
b110000100 &
1"
#389
b110000101 &
0"
#390
b111101111100 $
b111101111100 (
b110000110 &
1"
#391
b110000111 &
0"
#392
1%
b100110110111010 $
b100110110111010 (
b110001000 &
1"
#393
b110001001 &
0"
#394
b100110110111010 !
b100110110111010 )
b1111111010100110 $
b1111111010100110 (
b100110110111010 '
b110001010 &
1"
#395
b110001011 &
0"
#396
b1111111010100110 '
0%
b1000001100110010 $
b1000001100110010 (
b1111111010100110 !
b1111111010100110 )
b110001100 &
1"
#397
b110001101 &
0"
#398
b111110001001001 $
b111110001001001 (
b110001110 &
1"
#399
b110001111 &
0"
#400
1%
b1100000000111101 $
b1100000000111101 (
b110010000 &
1"
#401
b110010001 &
0"
#402
b1100000000111101 !
b1100000000111101 )
b11000001011100 $
b11000001011100 (
b1100000000111101 '
b110010010 &
1"
#403
b110010011 &
0"
#404
b11000001011100 '
b1001011110000110 $
b1001011110000110 (
b11000001011100 !
b11000001011100 )
b110010100 &
1"
#405
b110010101 &
0"
#406
b1001011110000110 !
b1001011110000110 )
0%
b1000101010110100 $
b1000101010110100 (
b1001011110000110 '
b110010110 &
1"
#407
b110010111 &
0"
#408
b101000000101100 $
b101000000101100 (
b110011000 &
1"
#409
b110011001 &
0"
#410
b1011011100000111 $
b1011011100000111 (
b110011010 &
1"
#411
b110011011 &
0"
#412
b1111100100010001 $
b1111100100010001 (
b110011100 &
1"
#413
b110011101 &
0"
#414
1%
b1001111001001011 $
b1001111001001011 (
b110011110 &
1"
#415
b110011111 &
0"
#416
b1001111001001011 '
b101101111101100 $
b101101111101100 (
b1001111001001011 !
b1001111001001011 )
b110100000 &
1"
#417
b110100001 &
0"
#418
b101101111101100 !
b101101111101100 )
b1110111110100100 $
b1110111110100100 (
b101101111101100 '
b110100010 &
1"
#419
b110100011 &
0"
#420
b1110111110100100 '
b10000111001 $
b10000111001 (
b1110111110100100 !
b1110111110100100 )
b110100100 &
1"
#421
b110100101 &
0"
#422
b10000111001 !
b10000111001 )
b1010011010100 $
b1010011010100 (
b10000111001 '
b110100110 &
1"
#423
b110100111 &
0"
#424
b1010011010100 '
0%
b100000110011101 $
b100000110011101 (
b1010011010100 !
b1010011010100 )
b110101000 &
1"
#425
b110101001 &
0"
#426
1%
b11100110000010 $
b11100110000010 (
b110101010 &
1"
#427
b110101011 &
0"
#428
b11100110000010 '
0%
b1101011011001 $
b1101011011001 (
b11100110000010 !
b11100110000010 )
b110101100 &
1"
#429
b110101101 &
0"
#430
1%
b100110000011100 $
b100110000011100 (
b110101110 &
1"
#431
b110101111 &
0"
#432
b100110000011100 '
0%
b110000111100011 $
b110000111100011 (
b100110000011100 !
b100110000011100 )
b110110000 &
1"
#433
b110110001 &
0"
#434
1%
b1111100011001000 $
b1111100011001000 (
b110110010 &
1"
#435
b110110011 &
0"
#436
b1111100011001000 '
0%
b1001110100111010 $
b1001110100111010 (
b1111100011001000 !
b1111100011001000 )
b110110100 &
1"
#437
b110110101 &
0"
#438
1%
b1010100000101011 $
b1010100000101011 (
b110110110 &
1"
#439
b110110111 &
0"
#440
b1010100000101011 '
0%
b1110000010010 $
b1110000010010 (
b1010100000101011 !
b1010100000101011 )
b110111000 &
1"
#441
b110111001 &
0"
#442
b1000100101011001 $
b1000100101011001 (
b110111010 &
1"
#443
b110111011 &
0"
#444
1%
b1110101001101110 $
b1110101001101110 (
b110111100 &
1"
#445
b110111101 &
0"
#446
b1110101001101110 !
b1110101001101110 )
0%
b1000011111011011 $
b1000011111011011 (
b1110101001101110 '
b110111110 &
1"
#447
b110111111 &
0"
#448
b1101001110111011 $
b1101001110111011 (
b111000000 &
1"
#449
b111000001 &
0"
#450
1%
b100110000001111 $
b100110000001111 (
b111000010 &
1"
#451
b111000011 &
0"
#452
b100110000001111 '
b110001000001100 $
b110001000001100 (
b100110000001111 !
b100110000001111 )
b111000100 &
1"
#453
b111000101 &
0"
#454
b110001000001100 !
b110001000001100 )
b100100111000101 $
b100100111000101 (
b110001000001100 '
b111000110 &
1"
#455
b111000111 &
0"
#456
b100100111000101 '
b1110010110010000 $
b1110010110010000 (
b100100111000101 !
b100100111000101 )
b111001000 &
1"
#457
b111001001 &
0"
#458
b1110010110010000 !
b1110010110010000 )
b1010010001101001 $
b1010010001101001 (
b1110010110010000 '
b111001010 &
1"
#459
b111001011 &
0"
#460
b1010010001101001 '
0%
b110010101001010 $
b110010101001010 (
b1010010001101001 !
b1010010001101001 )
b111001100 &
1"
#461
b111001101 &
0"
#462
b100110110011011 $
b100110110011011 (
b111001110 &
1"
#463
b111001111 &
0"
#464
1%
b1011000110111000 $
b1011000110111000 (
b111010000 &
1"
#465
b111010001 &
0"
