03_Sequential_Logic/DFF.v
/**
* Data-Flip-Flop
* out[t+1] = in[t]
*/

`default_nettype none
module DFF(
  input clk,
  input in,
  output reg out
);

  // No need to implement this chip
  // This chip is implemented in verilog using reg-variables

  always @(posedge clk) begin
    if (in)
      out <= 1'b1;
    else
      out <= 1'b0;
  end

endmodule

03_Sequential_Logic/00_DFF/DFF_tb.v
`default_nettype none
module DFF_tb();

	// IN,OUT
	reg clk = 1;
	reg in;
	wire out;

	// Part
	DFF DFF(
		.clk(clk),
		.in(in),
		.out(out)
	);

	// Compare
	always #1 clk=~clk;
	always @(posedge clk)
		in <= $random;	
	
	reg out_cmp;
	always @(posedge clk)
		out_cmp <= in;	
	
	reg fail = 0;
	reg [15:0] n = 0;
	task check;
		#1
		if (out != out_cmp) 
			begin
				$display("FAIL: clk=%1b, in=%1b, out=%1b",clk,in,out);
				fail=1;
			end
	endtask
	
	// Test  
  	initial begin
  		$dumpvars(0, DFF_tb);
		
		$display("------------------------");
		$display("Testbench: DFF");

		for (n=0; n<1000;n=n+1) 
			check();
		
		if (fail==0) $display("passed");
		$display("------------------------");
		$finish;
	end

endmodule

03_Sequential_Logic/00_DFF/_build/default/DFF_tb.vcd
$date
	Tue Aug  4 23:48:28 2026
$end
$version
	Icarus Verilog
$end
$timescale
	1ps
$end
$scope module DFF_tb $end
$var wire 1 ! out $end
$var reg 1 " clk $end
$var reg 1 # fail $end
$var reg 1 $ in $end
$var reg 16 % n [15:0] $end
$var reg 1 & out_cmp $end
$scope module DFF $end
$var wire 1 " clk $end
$var wire 1 $ in $end
$var reg 1 ! out $end
$upscope $end
$scope task check $end
$upscope $end
$upscope $end
$enddefinitions $end
$comment Show the parameter values. $end
$dumpall
$end
#0
$dumpvars
x&
b0 %
x$
0#
1"
x!
$end
#1
b1 %
0"
#2
0!
0$
b10 %
1"
#3
b11 %
0"
#4
0&
1$
b100 %
1"
#5
b101 %
0"
#6
1!
1&
b110 %
1"
#7
b111 %
0"
#8
b1000 %
1"
#9
b1001 %
0"
#10
b1010 %
1"
#11
b1011 %
0"
#12
b1100 %
1"
#13
b1101 %
0"
#14
b1110 %
1"
#15
b1111 %
0"
#16
0$
b10000 %
1"
#17
b10001 %
0"
#18
0!
1$
0&
b10010 %
1"
#19
b10011 %
0"
#20
1&
1!
b10100 %
1"
#21
b10101 %
0"
#22
0$
b10110 %
1"
#23
b10111 %
0"
#24
0&
1$
0!
b11000 %
1"
#25
b11001 %
0"
#26
1!
1&
b11010 %
1"
#27
b11011 %
0"
#28
0$
b11100 %
1"
#29
b11101 %
0"
#30
0!
1$
0&
b11110 %
1"
#31
b11111 %
0"
#32
1&
0$
1!
b100000 %
1"
#33
b100001 %
0"
#34
0!
1$
0&
b100010 %
1"
#35
b100011 %
0"
#36
1&
0$
1!
b100100 %
1"
#37
b100101 %
0"
#38
0!
1$
0&
b100110 %
1"
#39
b100111 %
0"
#40
1&
1!
b101000 %
1"
#41
b101001 %
0"
#42
0$
b101010 %
1"
#43
b101011 %
0"
#44
0&
1$
0!
b101100 %
1"
#45
b101101 %
0"
#46
1!
0$
1&
b101110 %
1"
#47
b101111 %
0"
#48
0&
0!
b110000 %
1"
#49
b110001 %
0"
#50
b110010 %
1"
#51
b110011 %
0"
#52
1$
b110100 %
1"
#53
b110101 %
0"
#54
1!
0$
1&
b110110 %
1"
#55
b110111 %
0"
#56
0&
1$
0!
b111000 %
1"
#57
b111001 %
0"
#58
1!
1&
b111010 %
1"
#59
b111011 %
0"
#60
b111100 %
1"
#61
b111101 %
0"
#62
b111110 %
1"
#63
b111111 %
0"
#64
0$
b1000000 %
1"
#65
b1000001 %
0"
#66
0!
0&
b1000010 %
1"
#67
b1000011 %
0"
#68
b1000100 %
1"
#69
b1000101 %
0"
#70
b1000110 %
1"
#71
b1000111 %
0"
#72
1$
b1001000 %
1"
#73
b1001001 %
0"
#74
1!
0$
1&
b1001010 %
1"
#75
b1001011 %
0"
#76
0&
1$
0!
b1001100 %
1"
#77
b1001101 %
0"
#78
1!
1&
b1001110 %
1"
#79
b1001111 %
0"
#80
b1010000 %
1"
#81
b1010001 %
0"
#82
b1010010 %
1"
#83
b1010011 %
0"
#84
b1010100 %
1"
#85
b1010101 %
0"
#86
0$
b1010110 %
1"
#87
b1010111 %
0"
#88
0&
0!
b1011000 %
1"
#89
b1011001 %
0"
#90
1$
b1011010 %
1"
#91
b1011011 %
0"
#92
1&
1!
b1011100 %
1"
#93
b1011101 %
0"
#94
b1011110 %
1"
#95
b1011111 %
0"
#96
0$
b1100000 %
1"
#97
b1100001 %
0"
#98
0!
0&
b1100010 %
1"
#99
b1100011 %
0"
#100
b1100100 %
1"
#101
b1100101 %
0"
#102
b1100110 %
1"
#103
b1100111 %
0"
#104
b1101000 %
1"
#105
b1101001 %
0"
#106
1$
b1101010 %
1"
#107
b1101011 %
0"
#108
1&
0$
1!
b1101100 %
1"
#109
b1101101 %
0"
#110
0!
0&
b1101110 %
1"
#111
b1101111 %
0"
#112
1$
b1110000 %
1"
#113
b1110001 %
0"
#114
1!
1&
b1110010 %
1"
#115
b1110011 %
0"
#116
0$
b1110100 %
1"
#117
b1110101 %
0"
#118
0!
0&
b1110110 %
1"
#119
b1110111 %
0"
#120
b1111000 %
1"
#121
b1111001 %
0"
#122
b1111010 %
1"
#123
b1111011 %
0"
#124
b1111100 %
1"
#125
b1111101 %
0"
#126
1$
b1111110 %
1"
#127
b1111111 %
0"
#128
1&
1!
b10000000 %
1"
#129
b10000001 %
0"
#130
b10000010 %
1"
#131
b10000011 %
0"
#132
b10000100 %
1"
#133
b10000101 %
0"
#134
b10000110 %
1"
#135
b10000111 %
0"
#136
0$
b10001000 %
1"
#137
b10001001 %
0"
#138
0!
0&
b10001010 %
1"
#139
b10001011 %
0"
#140
1$
b10001100 %
1"
#141
b10001101 %
0"
#142
1!
1&
b10001110 %
1"
#143
b10001111 %
0"
#144
b10010000 %
1"
#145
b10010001 %
0"
#146
0$
b10010010 %
1"
#147
b10010011 %
0"
#148
0&
0!
b10010100 %
1"
#149
b10010101 %
0"
#150
1$
b10010110 %
1"
#151
b10010111 %
0"
#152
1&
1!
b10011000 %
1"
#153
b10011001 %
0"
#154
0$
b10011010 %
1"
#155
b10011011 %
0"
#156
0&
1$
0!
b10011100 %
1"
#157
b10011101 %
0"
#158
1!
1&
b10011110 %
1"
#159
b10011111 %
0"
#160
0$
b10100000 %
1"
#161
b10100001 %
0"
#162
0!
1$
0&
b10100010 %
1"
#163
b10100011 %
0"
#164
1&
1!
b10100100 %
1"
#165
b10100101 %
0"
#166
b10100110 %
1"
#167
b10100111 %
0"
#168
0$
b10101000 %
1"
#169
b10101001 %
0"
#170
0!
1$
0&
b10101010 %
1"
#171
b10101011 %
0"
#172
1&
1!
b10101100 %
1"
#173
b10101101 %
0"
#174
0$
b10101110 %
1"
#175
b10101111 %
0"
#176
0&
0!
b10110000 %
1"
#177
b10110001 %
0"
#178
b10110010 %
1"
#179
b10110011 %
0"
#180
b10110100 %
1"
#181
b10110101 %
0"
#182
1$
b10110110 %
1"
#183
b10110111 %
0"
#184
1&
1!
b10111000 %
1"
#185
b10111001 %
0"
#186
0$
b10111010 %
1"
#187
b10111011 %
0"
#188
0&
0!
b10111100 %
1"
#189
b10111101 %
0"
#190
1$
b10111110 %
1"
#191
b10111111 %
0"
#192
1&
1!
b11000000 %
1"
#193
b11000001 %
0"
#194
b11000010 %
1"
#195
b11000011 %
0"
#196
b11000100 %
1"
#197
b11000101 %
0"
#198
b11000110 %
1"
#199
b11000111 %
0"
#200
0$
b11001000 %
1"
#201
b11001001 %
0"
#202
0!
1$
0&
b11001010 %
1"
#203
b11001011 %
0"
#204
1&
1!
b11001100 %
1"
#205
b11001101 %
0"
#206
b11001110 %
1"
#207
b11001111 %
0"
#208
0$
b11010000 %
1"
#209
b11010001 %
0"
#210
0!
0&
b11010010 %
1"
#211
b11010011 %
0"
#212
b11010100 %
1"
#213
b11010101 %
0"
#214
b11010110 %
1"
#215
b11010111 %
0"
#216
b11011000 %
1"
#217
b11011001 %
0"
#218
b11011010 %
1"
#219
b11011011 %
0"
#220
b11011100 %
1"
#221
b11011101 %
0"
#222
1$
b11011110 %
1"
#223
b11011111 %
0"
#224
1&
1!
b11100000 %
1"
#225
b11100001 %
0"
#226
b11100010 %
1"
#227
b11100011 %
0"
#228
b11100100 %
1"
#229
b11100101 %
0"
#230
b11100110 %
1"
#231
b11100111 %
0"
#232
0$
b11101000 %
1"
#233
b11101001 %
0"
#234
0!
1$
0&
b11101010 %
1"
#235
b11101011 %
0"
#236
1&
1!
b11101100 %
1"
#237
b11101101 %
0"
#238
0$
b11101110 %
1"
#239
b11101111 %
0"
#240
0&
0!
b11110000 %
1"
#241
b11110001 %
0"
#242
1$
b11110010 %
1"
#243
b11110011 %
0"
#244
1&
1!
b11110100 %
1"
#245
b11110101 %
0"
#246
0$
b11110110 %
1"
#247
b11110111 %
0"
#248
0&
1$
0!
b11111000 %
1"
#249
b11111001 %
0"
#250
1!
1&
b11111010 %
1"
#251
b11111011 %
0"
#252
b11111100 %
1"
#253
b11111101 %
0"
#254
b11111110 %
1"
#255
b11111111 %
0"
#256
0$
b100000000 %
1"
#257
b100000001 %
0"
#258
0!
0&
b100000010 %
1"
#259
b100000011 %
0"
#260
b100000100 %
1"
#261
b100000101 %
0"
#262
1$
b100000110 %
1"
#263
b100000111 %
0"
#264
1&
0$
1!
b100001000 %
1"
#265
b100001001 %
0"
#266
0!
0&
b100001010 %
1"
#267
b100001011 %
0"
#268
b100001100 %
1"
#269
b100001101 %
0"
#270
1$
b100001110 %
1"
#271
b100001111 %
0"
#272
1&
1!
b100010000 %
1"
#273
b100010001 %
0"
#274
0$
b100010010 %
1"
#275
b100010011 %
0"
#276
0&
0!
b100010100 %
1"
#277
b100010101 %
0"
#278
1$
b100010110 %
1"
#279
b100010111 %
0"
#280
1&
0$
1!
b100011000 %
1"
#281
b100011001 %
0"
#282
0!
0&
b100011010 %
1"
#283
b100011011 %
0"
#284
b100011100 %
1"
#285
b100011101 %
0"
#286
1$
b100011110 %
1"
#287
b100011111 %
0"
#288
1&
0$
1!
b100100000 %
1"
#289
b100100001 %
0"
#290
0!
0&
b100100010 %
1"
#291
b100100011 %
0"
#292
1$
b100100100 %
1"
#293
b100100101 %
0"
#294
1!
0$
1&
b100100110 %
1"
#295
b100100111 %
0"
#296
0&
1$
0!
b100101000 %
1"
#297
b100101001 %
0"
#298
1!
1&
b100101010 %
1"
#299
b100101011 %
0"
#300
b100101100 %
1"
#301
b100101101 %
0"
#302
b100101110 %
1"
#303
b100101111 %
0"
#304
b100110000 %
1"
#305
b100110001 %
0"
#306
0$
b100110010 %
1"
#307
b100110011 %
0"
#308
0&
0!
b100110100 %
1"
#309
b100110101 %
0"
#310
b100110110 %
1"
#311
b100110111 %
0"
#312
1$
b100111000 %
1"
#313
b100111001 %
0"
#314
1!
0$
1&
b100111010 %
1"
#315
b100111011 %
0"
#316
0&
0!
b100111100 %
1"
#317
b100111101 %
0"
#318
1$
b100111110 %
1"
#319
b100111111 %
0"
#320
1&
1!
b101000000 %
1"
#321
b101000001 %
0"
#322
0$
b101000010 %
1"
#323
b101000011 %
0"
#324
0&
0!
b101000100 %
1"
#325
b101000101 %
0"
#326
b101000110 %
1"
#327
b101000111 %
0"
#328
1$
b101001000 %
1"
#329
b101001001 %
0"
#330
1!
1&
b101001010 %
1"
#331
b101001011 %
0"
#332
0$
b101001100 %
1"
#333
b101001101 %
0"
#334
0!
0&
b101001110 %
1"
#335
b101001111 %
0"
#336
b101010000 %
1"
#337
b101010001 %
0"
#338
1$
b101010010 %
1"
#339
b101010011 %
0"
#340
1&
1!
b101010100 %
1"
#341
b101010101 %
0"
#342
0$
b101010110 %
1"
#343
b101010111 %
0"
#344
0&
0!
b101011000 %
1"
#345
b101011001 %
0"
#346
b101011010 %
1"
#347
b101011011 %
0"
#348
1$
b101011100 %
1"
#349
b101011101 %
0"
#350
1!
0$
1&
b101011110 %
1"
#351
b101011111 %
0"
#352
0&
0!
b101100000 %
1"
#353
b101100001 %
0"
#354
1$
b101100010 %
1"
#355
b101100011 %
0"
#356
1&
0$
1!
b101100100 %
1"
#357
b101100101 %
0"
#358
0!
0&
b101100110 %
1"
#359
b101100111 %
0"
#360
b101101000 %
1"
#361
b101101001 %
0"
#362
1$
b101101010 %
1"
#363
b101101011 %
0"
#364
1&
0$
1!
b101101100 %
1"
#365
b101101101 %
0"
#366
0!
1$
0&
b101101110 %
1"
#367
b101101111 %
0"
#368
1&
1!
b101110000 %
1"
#369
b101110001 %
0"
#370
0$
b101110010 %
1"
#371
b101110011 %
0"
#372
0&
0!
b101110100 %
1"
#373
b101110101 %
0"
#374
b101110110 %
1"
#375
b101110111 %
0"
#376
b101111000 %
1"
#377
b101111001 %
0"
#378
1$
b101111010 %
1"
#379
b101111011 %
0"
#380
1&
0$
1!
b101111100 %
1"
#381
b101111101 %
0"
#382
0!
0&
b101111110 %
1"
#383
b101111111 %
0"
#384
b110000000 %
1"
#385
b110000001 %
0"
#386
b110000010 %
1"
#387
b110000011 %
0"
#388
1$
b110000100 %
1"
#389
b110000101 %
0"
#390
1!
1&
b110000110 %
1"
#391
b110000111 %
0"
#392
b110001000 %
1"
#393
b110001001 %
0"
#394
0$
b110001010 %
1"
#395
b110001011 %
0"
#396
0&
1$
0!
b110001100 %
1"
#397
b110001101 %
0"
#398
1!
1&
b110001110 %
1"
#399
b110001111 %
0"
#400
b110010000 %
1"
#401
b110010001 %
0"
#402
0$
b110010010 %
1"
#403
b110010011 %
0"
#404
0&
0!
b110010100 %
1"
#405
b110010101 %
0"
#406
1$
b110010110 %
1"
#407
b110010111 %
0"
#408
1&
1!
b110011000 %
1"
#409
b110011001 %
0"
#410
b110011010 %
1"
#411
b110011011 %
0"
#412
b110011100 %
1"
#413
b110011101 %
0"
#414
b110011110 %
1"
#415
b110011111 %
0"
#416
0$
b110100000 %
1"
#417
b110100001 %
0"
#418
0!
1$
0&
b110100010 %
1"
#419
b110100011 %
0"
#420
1&
1!
b110100100 %
1"
#421
b110100101 %
0"
#422
0$
b110100110 %
1"
#423
b110100111 %
0"
#424
0&
0!
b110101000 %
1"
#425
b110101001 %
0"
#426
b110101010 %
1"
#427
b110101011 %
0"
#428
b110101100 %
1"
#429
b110101101 %
0"
#430
1$
b110101110 %
1"
#431
b110101111 %
0"
#432
1&
1!
b110110000 %
1"
#433
b110110001 %
0"
#434
0$
b110110010 %
1"
#435
b110110011 %
0"
#436
0&
0!
b110110100 %
1"
#437
b110110101 %
0"
#438
1$
b110110110 %
1"
#439
b110110111 %
0"
#440
1&
0$
1!
b110111000 %
1"
#441
b110111001 %
0"
#442
0!
0&
b110111010 %
1"
#443
b110111011 %
0"
#444
1$
b110111100 %
1"
#445
b110111101 %
0"
#446
1!
0$
1&
b110111110 %
1"
#447
b110111111 %
0"
#448
0&
0!
b111000000 %
1"
#449
b111000001 %
0"
#450
1$
b111000010 %
1"
#451
b111000011 %
0"
#452
1&
0$
1!
b111000100 %
1"
#453
b111000101 %
0"
#454
0!
0&
b111000110 %
1"
#455
b111000111 %
0"
#456
1$
b111001000 %
1"
#457
b111001001 %
0"
#458
1!
1&
b111001010 %
1"
#459
b111001011 %
0"
#460
b111001100 %
1"
#461
b111001101 %
0"
#462
0$
b111001110 %
1"
#463
b111001111 %
0"
#464
0&
0!
b111010000 %
1"
#465
b111010001 %
0"
#466
b111010010 %
1"
#467
b111010011 %
0"
#468
1$
b111010100 %
1"
#469
b111010101 %
0"
#470
1!
0$
1&
b111010110 %
1"
#471
b111010111 %
0"
#472
0&
0!
b111011000 %
1"
#473
b111011001 %
0"
#474
1$
b111011010 %
1"
#475
b111011011 %
0"
#476
1&
0$
1!
b111011100 %
1"
#477
b111011101 %
0"
#478
0!
0&
b111011110 %
1"
#479
b111011111 %
0"
#480
b111100000 %
1"
#481
b111100001 %
0"
#482
b111100010 %
1"
#483
b111100011 %
0"
#484
1$
b111100100 %
1"
#485
b111100101 %
0"
#486
1!
0$
1&
b111100110 %
1"
#487
b111100111 %
0"
#488
0&
0!
b111101000 %
1"
#489
b111101001 %
0"
#490
b111101010 %
1"
#491
b111101011 %
0"
#492
1$
b111101100 %
1"
#493
b111101101 %
0"
#494
1!
1&
b111101110 %
1"
#495
b111101111 %
0"
#496
0$
b111110000 %
1"
#497
b111110001 %
0"
#498
0!
1$
0&
b111110010 %
1"
#499
b111110011 %
0"
#500
1&
1!
b111110100 %
1"
#501
b111110101 %
0"
#502
b111110110 %
1"
#503
b111110111 %
0"
#504
b111111000 %
1"
#505
b111111001 %
0"
#506
0$
b111111010 %
1"
#507
b111111011 %
0"
#508
0&
1$
0!
b111111100 %
1"
#509
b111111101 %
0"
#510
1!
1&
b111111110 %
1"
#511
b111111111 %
0"
#512
b1000000000 %
1"
#513
b1000000001 %
0"
#514
0$
b1000000010 %
1"
#515
b1000000011 %
0"
#516
0&
0!
b1000000100 %
1"
#517
b1000000101 %
0"
#518
1$
b1000000110 %
1"
#519
b1000000111 %
0"
#520
1&
0$
1!
b1000001000 %
1"
#521
b1000001001 %
0"
#522
0!
0&
b1000001010 %
1"
#523
b1000001011 %
0"
#524
1$
b1000001100 %
1"
#525
b1000001101 %
0"
#526
1!
1&
b1000001110 %
1"
#527
b1000001111 %
0"
#528
0$
b1000010000 %
1"
#529
b1000010001 %
0"
#530
0!
0&
b1000010010 %
1"
#531
b1000010011 %
0"
#532
1$
b1000010100 %
1"
#533
b1000010101 %
0"
#534
1!
0$
1&
b1000010110 %
1"
#535
b1000010111 %
0"
#536
0&
0!
b1000011000 %
1"
#537
b1000011001 %
0"
#538
1$
b1000011010 %
1"
#539
b1000011011 %
0"
#540
1&
0$
1!
b1000011100 %
1"
#541
b1000011101 %
0"
#542
0!
1$
0&
b1000011110 %
1"
#543
b1000011111 %
0"
#544
1&
1!
b1000100000 %
1"
#545
b1000100001 %
0"
#546
0$
b1000100010 %
1"
#547
b1000100011 %
0"
#548
0&
1$
0!
b1000100100 %
1"
#549
b1000100101 %
0"
#550
1!
0$
1&
b1000100110 %
1"
#551
b1000100111 %
0"
#552
0&
1$
0!
b1000101000 %
1"
#553
b1000101001 %
0"
#554
1!
0$
1&
b1000101010 %
1"
#555
b1000101011 %
0"
#556
0&
0!
b1000101100 %
1"
#557
b1000101101 %
0"
#558
1$
b1000101110 %
1"
#559
b1000101111 %
0"
#560
1&
0$
1!
b1000110000 %
1"
#561
b1000110001 %
0"
#562
0!
0&
b1000110010 %
1"
#563
b1000110011 %
0"
#564
b1000110100 %
1"
#565
b1000110101 %
0"
#566
1$
b1000110110 %
1"
#567
b1000110111 %
0"
#568
1&
1!
b1000111000 %
1"
#569
b1000111001 %
0"
#570
b1000111010 %
1"
#571
b1000111011 %
0"
#572
b1000111100 %
1"
#573
b1000111101 %
0"
#574
b1000111110 %
1"
#575
b1000111111 %
0"
#576
0$
b1001000000 %
1"
#577
b1001000001 %
0"
#578
0!
1$
0&
b1001000010 %
1"
#579
b1001000011 %
0"
#580
1&
1!
b1001000100 %
1"
#581
b1001000101 %
0"
#582
b1001000110 %
1"
#583
b1001000111 %
0"
#584
0$
b1001001000 %
1"
#585
b1001001001 %
0"
#586
0!
0&
b1001001010 %
1"
#587
b1001001011 %
0"
#588
b1001001100 %
1"
#589
b1001001101 %
0"
#590
b1001001110 %
1"
#591
b1001001111 %
0"
#592
b1001010000 %
1"
#593
b1001010001 %
0"
#594
b1001010010 %
1"
#595
b1001010011 %
0"
#596
1$
b1001010100 %
1"
#597
b1001010101 %
0"
#598
1!
1&
b1001010110 %
1"
#599
b1001010111 %
0"
#600
b1001011000 %
1"
#601
b1001011001 %
0"
#602
b1001011010 %
1"
#603
b1001011011 %
0"
#604
b1001011100 %
1"
#605
b1001011101 %
0"
#606
b1001011110 %
1"
#607
b1001011111 %
0"
#608
b1001100000 %
1"
#609
b1001100001 %
0"
#610
0$
b1001100010 %
1"
#611
b1001100011 %
0"
#612
0&
1$
0!
b1001100100 %
1"
#613
b1001100101 %
0"
#614
1!
1&
b1001100110 %
1"
#615
b1001100111 %
0"
#616
b1001101000 %
1"
#617
b1001101001 %
0"
#618
b1001101010 %
1"
#619
b1001101011 %
0"
#620
b1001101100 %
1"
#621
b1001101101 %
0"
#622
b1001101110 %
1"
#623
b1001101111 %
0"
#624
b1001110000 %
1"
#625
b1001110001 %
0"
#626
b1001110010 %
1"
#627
b1001110011 %
0"
#628
0$
b1001110100 %
1"
#629
b1001110101 %
0"
#630
0!
0&
b1001110110 %
1"
#631
b1001110111 %
0"
#632
1$
b1001111000 %
1"
#633
b1001111001 %
0"
#634
1!
1&
b1001111010 %
1"
#635
b1001111011 %
0"
#636
0$
b1001111100 %
1"
#637
b1001111101 %
0"
#638
0!
0&
b1001111110 %
1"
#639
b1001111111 %
0"
#640
b1010000000 %
1"
#641
b1010000001 %
0"
#642
b1010000010 %
1"
#643
b1010000011 %
0"
#644
1$
b1010000100 %
1"
#645
b1010000101 %
0"
#646
1!
0$
1&
b1010000110 %
1"
#647
b1010000111 %
0"
#648
0&
0!
b1010001000 %
1"
#649
b1010001001 %
0"
#650
b1010001010 %
1"
#651
b1010001011 %
0"
#652
b1010001100 %
1"
#653
b1010001101 %
0"
#654
b1010001110 %
1"
#655
b1010001111 %
0"
#656
b1010010000 %
1"
#657
b1010010001 %
0"
#658
1$
b1010010010 %
1"
#659
b1010010011 %
0"
#660
1&
0$
1!
b1010010100 %
1"
#661
b1010010101 %
0"
#662
0!
0&
b1010010110 %
1"
#663
b1010010111 %
0"
#664
1$
b1010011000 %
1"
#665
b1010011001 %
0"
#666
1!
0$
1&
b1010011010 %
1"
#667
b1010011011 %
0"
#668
0&
0!
b1010011100 %
1"
#669
b1010011101 %
0"
#670
b1010011110 %
1"
#671
b1010011111 %
0"
#672
b1010100000 %
1"
#673
b1010100001 %
0"
#674
1$
b1010100010 %
1"
#675
b1010100011 %
0"
#676
1&
1!
b1010100100 %
1"
#677
b1010100101 %
0"
#678
b1010100110 %
1"
#679
b1010100111 %
0"
#680
b1010101000 %
1"
#681
b1010101001 %
0"
#682
b1010101010 %
1"
#683
b1010101011 %
0"
#684
0$
b1010101100 %
1"
#685
b1010101101 %
0"
#686
0!
1$
0&
b1010101110 %
1"
#687
b1010101111 %
0"
#688
1&
1!
b1010110000 %
1"
#689
b1010110001 %
0"
#690
b1010110010 %
1"
#691
b1010110011 %
0"
#692
0$
b1010110100 %
1"
#693
b1010110101 %
0"
#694
0!
1$
0&
b1010110110 %
1"
#695
b1010110111 %
0"
#696
1&
0$
1!
b1010111000 %
1"
#697
b1010111001 %
0"
#698
0!
0&
b1010111010 %
1"
#699
b1010111011 %
0"
#700
1$
b1010111100 %
1"
#701
b1010111101 %
0"
#702
1!
1&
b1010111110 %
1"
#703
b1010111111 %
0"
#704
0$
b1011000000 %
1"
#705
b1011000001 %
0"
#706
0!
1$
0&
b1011000010 %
1"
#707
b1011000011 %
0"
#708
1&
0$
1!
b1011000100 %
1"
#709
b1011000101 %
0"
#710
0!
0&
b1011000110 %
1"
#711
b1011000111 %
0"
#712
1$
b1011001000 %
1"
#713
b1011001001 %
0"
#714
1!
0$
1&
b1011001010 %
1"
#715
b1011001011 %
0"
#716
0&
0!
b1011001100 %
1"
#717
b1011001101 %
0"
#718
b1011001110 %
1"
#719
b1011001111 %
0"
#720
b1011010000 %
1"
#721
b1011010001 %
0"
#722
1$
b1011010010 %
1"
#723
b1011010011 %
0"
#724
1&
1!
b1011010100 %
1"
#725
b1011010101 %
0"
#726
b1011010110 %
1"
#727
b1011010111 %
0"
#728
b1011011000 %
1"
#729
b1011011001 %
0"
#730
0$
b1011011010 %
1"
#731
b1011011011 %
0"
#732
0&
1$
0!
b1011011100 %
1"
#733
b1011011101 %
0"
#734
1!
1&
b1011011110 %
1"
#735
b1011011111 %
0"
#736
b1011100000 %
1"
#737
b1011100001 %
0"
#738
b1011100010 %
1"
#739
b1011100011 %
0"
#740
b1011100100 %
1"
#741
b1011100101 %
0"
#742
b1011100110 %
1"
#743
b1011100111 %
0"
#744
b1011101000 %
1"
#745
b1011101001 %
0"
#746
0$
b1011101010 %
1"
#747
b1011101011 %
0"
#748
0&
1$
0!
b1011101100 %
1"
#749
b1011101101 %
0"
#750
1!
0$
1&
b1011101110 %
1"
#751
b1011101111 %
0"
#752
0&
1$
0!
b1011110000 %
1"
#753
b1011110001 %
0"
#754
1!
0$
1&
b1011110010 %
1"
#755
b1011110011 %
0"
#756
0&
0!
b1011110100 %
1"
#757
b1011110101 %
0"
#758
1$
b1011110110 %
1"
#759
b1011110111 %
0"
#760
1&
0$
1!
b1011111000 %
1"
#761
b1011111001 %
0"
#762
0!
0&
b1011111010 %
1"
#763
b1011111011 %
0"
#764
b1011111100 %
1"
#765
b1011111101 %
0"
#766
b1011111110 %
1"
#767
b1011111111 %
0"
#768
b1100000000 %
1"
#769
b1100000001 %
0"
#770
1$
b1100000010 %
1"
#771
b1100000011 %
0"
#772
1&
0$
1!
b1100000100 %
1"
#773
b1100000101 %
0"
#774
0!
0&
b1100000110 %
1"
#775
b1100000111 %
0"
#776
b1100001000 %
1"
#777
b1100001001 %
0"
#778
b1100001010 %
1"
#779
b1100001011 %
0"
#780
b1100001100 %
1"
#781
b1100001101 %
0"
#782
b1100001110 %
1"
#783
b1100001111 %
0"
#784
1$
b1100010000 %
1"
#785
b1100010001 %
0"
#786
1!
0$
1&
b1100010010 %
1"
#787
b1100010011 %
0"
#788
0&
1$
0!
b1100010100 %
1"
#789
b1100010101 %
0"
#790
1!
0$
1&
b1100010110 %
1"
#791
b1100010111 %
0"
#792
0&
0!
b1100011000 %
1"
#793
b1100011001 %
0"
#794
1$
b1100011010 %
1"
#795
b1100011011 %
0"
#796
1&
0$
1!
b1100011100 %
1"
#797
b1100011101 %
0"
#798
0!
1$
0&
b1100011110 %
1"
#799
b1100011111 %
0"
#800
1&
1!
b1100100000 %
1"
#801
b1100100001 %
0"
#802
0$
b1100100010 %
1"
#803
b1100100011 %
0"
#804
0&
1$
0!
b1100100100 %
1"
#805
b1100100101 %
0"
#806
1!
0$
1&
b1100100110 %
1"
#807
b1100100111 %
0"
#808
0&
1$
0!
b1100101000 %
1"
#809
b1100101001 %
0"
#810
1!
0$
1&
b1100101010 %
1"
#811
b1100101011 %
0"
#812
0&
0!
b1100101100 %
1"
#813
b1100101101 %
0"
#814
b1100101110 %
1"
#815
b1100101111 %
0"
#816
b1100110000 %
1"
#817
b1100110001 %
0"
#818
1$
b1100110010 %
1"
#819
b1100110011 %
0"
#820
1&
0$
1!
b1100110100 %
1"
#821
b1100110101 %
0"
#822
0!
1$
0&
b1100110110 %
1"
#823
b1100110111 %
0"
#824
1&
0$
1!
b1100111000 %
1"
#825
b1100111001 %
0"
#826
0!
1$
0&
b1100111010 %
1"
#827
b1100111011 %
0"
#828
1&
1!
b1100111100 %
1"
#829
b1100111101 %
0"
#830
0$
b1100111110 %
1"
#831
b1100111111 %
0"
#832
0&
1$
0!
b1101000000 %
1"
#833
b1101000001 %
0"
#834
1!
0$
1&
b1101000010 %
1"
#835
b1101000011 %
0"
#836
0&
1$
0!
b1101000100 %
1"
#837
b1101000101 %
0"
#838
1!
1&
b1101000110 %
1"
#839
b1101000111 %
0"
#840
b1101001000 %
1"
#841
b1101001001 %
0"
#842
0$
b1101001010 %
1"
#843
b1101001011 %
0"
#844
0&
1$
0!
b1101001100 %
1"
#845
b1101001101 %
0"
#846
1!
1&
b1101001110 %
1"
#847
b1101001111 %
0"
#848
0$
b1101010000 %
1"
#849
b1101010001 %
0"
#850
0!
0&
b1101010010 %
1"
#851
b1101010011 %
0"
#852
1$
b1101010100 %
1"
#853
b1101010101 %
0"
#854
1!
1&
b1101010110 %
1"
#855
b1101010111 %
0"
#856
0$
b1101011000 %
1"
#857
b1101011001 %
0"
#858
0!
0&
b1101011010 %
1"
#859
b1101011011 %
0"
#860
1$
b1101011100 %
1"
#861
b1101011101 %
0"
#862
1!
1&
b1101011110 %
1"
#863
b1101011111 %
0"
#864
0$
b1101100000 %
1"
#865
b1101100001 %
0"
#866
0!
0&
b1101100010 %
1"
#867
b1101100011 %
0"
#868
1$
b1101100100 %
1"
#869
b1101100101 %
0"
#870
1!
0$
1&
b1101100110 %
1"
#871
b1101100111 %
0"
#872
0&
0!
b1101101000 %
1"
#873
b1101101001 %
0"
#874
1$
b1101101010 %
1"
#875
b1101101011 %
0"
#876
1&
1!
b1101101100 %
1"
#877
b1101101101 %
0"
#878
0$
b1101101110 %
1"
#879
b1101101111 %
0"
#880
0&
0!
b1101110000 %
1"
#881
b1101110001 %
0"
#882
1$
b1101110010 %
1"
#883
b1101110011 %
0"
#884
1&
0$
1!
b1101110100 %
1"
#885
b1101110101 %
0"
#886
0!
0&
b1101110110 %
1"
#887
b1101110111 %
0"
#888
1$
b1101111000 %
1"
#889
b1101111001 %
0"
#890
1!
1&
b1101111010 %
1"
#891
b1101111011 %
0"
#892
0$
b1101111100 %
1"
#893
b1101111101 %
0"
#894
0!
1$
0&
b1101111110 %
1"
#895
b1101111111 %
0"
#896
1&
0$
1!
b1110000000 %
1"
#897
b1110000001 %
0"
#898
0!
1$
0&
b1110000010 %
1"
#899
b1110000011 %
0"
#900
1&
1!
b1110000100 %
1"
#901
b1110000101 %
0"
#902
0$
b1110000110 %
1"
#903
b1110000111 %
0"
#904
0&
1$
0!
b1110001000 %
1"
#905
b1110001001 %
0"
#906
1!
1&
b1110001010 %
1"
#907
b1110001011 %
0"
#908
b1110001100 %
1"
#909
b1110001101 %
0"
#910
0$
b1110001110 %
1"
#911
b1110001111 %
0"
