01_Boolean_Logic/Mux.v
/** 
 * Multiplexor:
 * out = a if sel == 0
 *       b otherwise
 */

`default_nettype none
module Mux(
  input a,
  input b,
  input sel,
  output out
);

  assign out = sel ? b : a ;

endmodule

01_Boolean_Logic/Mux16.v
/**
 * 16-bit multiplexor: 
 * for i = 0..15 out[i] = a[i] if sel == 0 
 *                        b[i] if sel == 1
 */

`default_nettype none
module Mux16(
  input [15:0] a,
  input [15:0] b,
  input sel,
  output [15:0] out
);

  // assign out = sel ? b : a ;

  genvar i;
  generate
    for(i = 0; i < 16; i++) begin : gen_mux
      Mux mux_inst(.a(a[i]),.b(b[i]),.sel(sel),.out(out[i]));
    end
  endgenerate

endmodule

01_Boolean_Logic/Mux4Way16.v
/**
 * 16-bit multiplexor:
 * for i = 0..15 out[i] = a[i] if sel == 0
 *                        b[i] if sel == 1
 00 a
 01 b
 10 c
 11 d
 */

`default_nettype none
module Mux4Way16(
  input [15:0] a,
  input [15:0] b,
  input [15:0] c,
  input [15:0] d,
  input [1:0] sel,
  output [15:0] out
);

  wire [15:0] upper2,lower2;


  // assign out = sel == 2'b00 ? a : (sel == 2'b01 ? b : (sel == 2'b10 ? c : d));
  Mux16 m1(.a(a),.b(b),.sel(sel[0]),.out(upper2));
  Mux16 m2(.a(c),.b(d),.sel(sel[0]),.out(lower2));

  Mux16 m3(.a(upper2),.b(lower2),.sel(sel[1]),.out(out));

endmodule

01_Boolean_Logic/14_Mux4Way16/Mux4Way16_tb.v
`default_nettype none
module Mux4Way16_tb();

	// IN,OUT
	reg [15:0] a,b,c,d;
	reg [1:0] sel;
	wire [15:0] out;
	
	// Part
	Mux4Way16 MUX4WAY16(
		.a(a),
		.b(b),
		.c(c),
		.d(d),
		.sel(sel),
		.out(out)
	);

	// Compare
	wire [15:0] out_cmp;
	assign out_cmp = (sel[1]? (sel[0]?d:c):(sel[0]?b:a));
	
	reg fail = 0;
	reg [15:0] n = 0;
	task check;
		#1
			if (out != out_cmp)
			begin
				$display("FAIL: a=%16b, b=%16b, c=%16b, d=%16b, sel=%2b, out=%16b",a,b,c,d,sel,out);
				fail=1;
			end
	endtask
	 
	// Test 
  	initial begin
  		$dumpvars(0, Mux4Way16_tb);
		
		$display("------------------------");
		$display("Testbench: Mux4Way16");
		
		for (n=0; n<1000;n=n+1) 
			begin
				a=$random;
				b=$random;
				c=$random;
				d=$random;
				sel=0;check();
				sel=1;check();
				sel=2;check();
				sel=3;check();
			end
		
		if (fail==0) $display("passed");
		$display("------------------------");
		$finish;
	end

endmodule

01_Boolean_Logic/14_Mux4Way16/_build/default/Mux4Way16_tb.vcd
$date
	Wed Aug  5 02:32:49 2026
$end
$version
	Icarus Verilog
$end
$timescale
	1ps
$end
$scope module Mux4Way16_tb $end
$var wire 16 ! out_cmp [15:0] $end
$var wire 16 " out [15:0] $end
$var reg 16 # a [15:0] $end
$var reg 16 $ b [15:0] $end
$var reg 16 % c [15:0] $end
$var reg 16 & d [15:0] $end
$var reg 1 ' fail $end
$var reg 16 ( n [15:0] $end
$var reg 2 ) sel [1:0] $end
$scope module MUX4WAY16 $end
$var wire 16 * a [15:0] $end
$var wire 16 + b [15:0] $end
$var wire 16 , c [15:0] $end
$var wire 16 - d [15:0] $end
$var wire 2 . sel [1:0] $end
$var wire 16 / upper2 [15:0] $end
$var wire 16 0 out [15:0] $end
$var wire 16 1 lower2 [15:0] $end
$scope module m1 $end
$var wire 16 2 a [15:0] $end
$var wire 16 3 b [15:0] $end
$var wire 1 4 sel $end
$var wire 16 5 out [15:0] $end
$upscope $end
$scope module m2 $end
$var wire 16 6 a [15:0] $end
$var wire 16 7 b [15:0] $end
$var wire 1 8 sel $end
$var wire 16 9 out [15:0] $end
$upscope $end
$scope module m3 $end
$var wire 16 : a [15:0] $end
$var wire 16 ; b [15:0] $end
$var wire 1 < sel $end
$var wire 16 = out [15:0] $end
$upscope $end
$upscope $end
$scope task check $end
$upscope $end
$upscope $end
$enddefinitions $end
$comment Show the parameter values. $end
$dumpall
$end
#0
$dumpvars
b11010100100100 =
0<
b1101011000001001 ;
b11010100100100 :
b1101011000001001 9
08
b101011001100011 7
b1101011000001001 6
b11010100100100 5
04
b101111010000001 3
b11010100100100 2
b1101011000001001 1
b11010100100100 0
b11010100100100 /
b0 .
b101011001100011 -
b1101011000001001 ,
b101111010000001 +
b11010100100100 *
b0 )
b0 (
0'
b101011001100011 &
b1101011000001001 %
b101111010000001 $
b11010100100100 #
b11010100100100 "
b11010100100100 !
$end
#1
b101111010000001 !
b101111010000001 "
b101111010000001 0
b101111010000001 =
b101111010000001 /
b101111010000001 5
b101111010000001 :
b101011001100011 1
b101011001100011 9
b101011001100011 ;
14
18
b1 )
b1 .
#2
b1101011000001001 !
b11010100100100 /
b11010100100100 5
b11010100100100 :
b1101011000001001 1
b1101011000001001 9
b1101011000001001 ;
b1101011000001001 "
b1101011000001001 0
b1101011000001001 =
04
08
1<
b10 )
b10 .
#3
b101011001100011 !
b101011001100011 "
b101011001100011 0
b101011001100011 =
b101111010000001 /
b101111010000001 5
b101111010000001 :
b101011001100011 1
b101011001100011 9
b101011001100011 ;
14
18
b11 )
b11 .
#4
b111101100001101 !
b111101100001101 "
b111101100001101 0
b111101100001101 =
04
08
0<
b1000010001100101 1
b1000010001100101 9
b1000010001100101 ;
b111101100001101 /
b111101100001101 5
b111101100001101 :
b0 )
b0 .
b101001000010010 &
b101001000010010 -
b101001000010010 7
b1000010001100101 %
b1000010001100101 ,
b1000010001100101 6
b1001100110001101 $
b1001100110001101 +
b1001100110001101 3
b111101100001101 #
b111101100001101 *
b111101100001101 2
b1 (
#5
b1001100110001101 !
b1001100110001101 "
b1001100110001101 0
b1001100110001101 =
b1001100110001101 /
b1001100110001101 5
b1001100110001101 :
b101001000010010 1
b101001000010010 9
b101001000010010 ;
14
18
b1 )
b1 .
#6
b1000010001100101 !
b111101100001101 /
b111101100001101 5
b111101100001101 :
b1000010001100101 1
b1000010001100101 9
b1000010001100101 ;
b1000010001100101 "
b1000010001100101 0
b1000010001100101 =
04
08
1<
b10 )
b10 .
#7
b101001000010010 !
b101001000010010 "
b101001000010010 0
b101001000010010 =
b1001100110001101 /
b1001100110001101 5
b1001100110001101 :
b101001000010010 1
b101001000010010 9
b101001000010010 ;
14
18
b11 )
b11 .
#8
b1110001100000001 !
b1110001100000001 "
b1110001100000001 0
b1110001100000001 =
04
08
0<
b1111000101110110 1
b1111000101110110 9
b1111000101110110 ;
b1110001100000001 /
b1110001100000001 5
b1110001100000001 :
b0 )
b0 .
b1100110100111101 &
b1100110100111101 -
b1100110100111101 7
b1111000101110110 %
b1111000101110110 ,
b1111000101110110 6
b1100110100001101 $
b1100110100001101 +
b1100110100001101 3
b1110001100000001 #
b1110001100000001 *
b1110001100000001 2
b10 (
#9
b1100110100001101 !
b1100110100001101 "
b1100110100001101 0
b1100110100001101 =
b1100110100001101 /
b1100110100001101 5
b1100110100001101 :
b1100110100111101 1
b1100110100111101 9
b1100110100111101 ;
14
18
b1 )
b1 .
#10
b1111000101110110 !
b1110001100000001 /
b1110001100000001 5
b1110001100000001 :
b1111000101110110 1
b1111000101110110 9
b1111000101110110 ;
b1111000101110110 "
b1111000101110110 0
b1111000101110110 =
04
08
1<
b10 )
b10 .
#11
b1100110100111101 !
b1100110100111101 "
b1100110100111101 0
b1100110100111101 =
b1100110100001101 /
b1100110100001101 5
b1100110100001101 :
b1100110100111101 1
b1100110100111101 9
b1100110100111101 ;
14
18
b11 )
b11 .
#12
b101011111101101 !
b101011111101101 "
b101011111101101 0
b101011111101101 =
04
08
0<
b1110100111111001 1
b1110100111111001 9
b1110100111111001 ;
b101011111101101 /
b101011111101101 5
b101011111101101 :
b0 )
b0 .
b10010011000110 &
b10010011000110 -
b10010011000110 7
b1110100111111001 %
b1110100111111001 ,
b1110100111111001 6
b1111011110001100 $
b1111011110001100 +
b1111011110001100 3
b101011111101101 #
b101011111101101 *
b101011111101101 2
b11 (
#13
b1111011110001100 !
b1111011110001100 "
b1111011110001100 0
b1111011110001100 =
b1111011110001100 /
b1111011110001100 5
b1111011110001100 :
b10010011000110 1
b10010011000110 9
b10010011000110 ;
14
18
b1 )
b1 .
#14
b1110100111111001 !
b101011111101101 /
b101011111101101 5
b101011111101101 :
b1110100111111001 1
b1110100111111001 9
b1110100111111001 ;
b1110100111111001 "
b1110100111111001 0
b1110100111111001 =
04
08
1<
b10 )
b10 .
#15
b10010011000110 !
b10010011000110 "
b10010011000110 0
b10010011000110 =
b1111011110001100 /
b1111011110001100 5
b1111011110001100 :
b10010011000110 1
b10010011000110 9
b10010011000110 ;
14
18
b11 )
b11 .
#16
b1000010011000101 !
b1000010011000101 "
b1000010011000101 0
b1000010011000101 =
04
08
0<
b1111011111100101 1
b1111011111100101 9
b1111011111100101 ;
b1000010011000101 /
b1000010011000101 5
b1000010011000101 :
b0 )
b0 .
b111001001110111 &
b111001001110111 -
b111001001110111 7
b1111011111100101 %
b1111011111100101 ,
b1111011111100101 6
b1101001010101010 $
b1101001010101010 +
b1101001010101010 3
b1000010011000101 #
b1000010011000101 *
b1000010011000101 2
b100 (
#17
b1101001010101010 !
b1101001010101010 "
b1101001010101010 0
b1101001010101010 =
b1101001010101010 /
b1101001010101010 5
b1101001010101010 :
b111001001110111 1
b111001001110111 9
b111001001110111 ;
14
18
b1 )
b1 .
#18
b1111011111100101 !
b1000010011000101 /
b1000010011000101 5
b1000010011000101 :
b1111011111100101 1
b1111011111100101 9
b1111011111100101 ;
b1111011111100101 "
b1111011111100101 0
b1111011111100101 =
04
08
1<
b10 )
b10 .
#19
b111001001110111 !
b111001001110111 "
b111001001110111 0
b111001001110111 =
b1101001010101010 /
b1101001010101010 5
b1101001010101010 :
b111001001110111 1
b111001001110111 9
b111001001110111 ;
14
18
b11 )
b11 .
#20
b1101011000010010 !
b1101011000010010 "
b1101011000010010 0
b1101011000010010 =
04
08
0<
b110100111110010 1
b110100111110010 9
b110100111110010 ;
b1101011000010010 /
b1101011000010010 5
b1101011000010010 :
b0 )
b0 .
b1001011011001110 &
b1001011011001110 -
b1001011011001110 7
b110100111110010 %
b110100111110010 ,
b110100111110010 6
b1101101110001111 $
b1101101110001111 +
b1101101110001111 3
b1101011000010010 #
b1101011000010010 *
b1101011000010010 2
b101 (
#21
b1101101110001111 !
b1101101110001111 "
b1101101110001111 0
b1101101110001111 =
b1101101110001111 /
b1101101110001111 5
b1101101110001111 :
b1001011011001110 1
b1001011011001110 9
b1001011011001110 ;
14
18
b1 )
b1 .
#22
b110100111110010 !
b1101011000010010 /
b1101011000010010 5
b1101011000010010 :
b110100111110010 1
b110100111110010 9
b110100111110010 ;
b110100111110010 "
b110100111110010 0
b110100111110010 =
04
08
1<
b10 )
b10 .
#23
b1001011011001110 !
b1001011011001110 "
b1001011011001110 0
b1001011011001110 =
b1101101110001111 /
b1101101110001111 5
b1101101110001111 :
b1001011011001110 1
b1001011011001110 9
b1001011011001110 ;
14
18
b11 )
b11 .
#24
b111101011101000 !
b111101011101000 "
b111101011101000 0
b111101011101000 =
04
08
0<
b100100101011100 1
b100100101011100 9
b100100101011100 ;
b111101011101000 /
b111101011101000 5
b111101011101000 :
b0 )
b0 .
b10100010111101 &
b10100010111101 -
b10100010111101 7
b100100101011100 %
b100100101011100 ,
b100100101011100 6
b100111011000101 $
b100111011000101 +
b100111011000101 3
b111101011101000 #
b111101011101000 *
b111101011101000 2
b110 (
#25
b100111011000101 !
b100111011000101 "
b100111011000101 0
b100111011000101 =
b100111011000101 /
b100111011000101 5
b100111011000101 :
b10100010111101 1
b10100010111101 9
b10100010111101 ;
14
18
b1 )
b1 .
#26
b100100101011100 !
b111101011101000 /
b111101011101000 5
b111101011101000 :
b100100101011100 1
b100100101011100 9
b100100101011100 ;
b100100101011100 "
b100100101011100 0
b100100101011100 =
04
08
1<
b10 )
b10 .
#27
b10100010111101 !
b10100010111101 "
b10100010111101 0
b10100010111101 =
b100111011000101 /
b100111011000101 5
b100111011000101 :
b10100010111101 1
b10100010111101 9
b10100010111101 ;
14
18
b11 )
b11 .
#28
b101100000101101 !
b101100000101101 "
b101100000101101 0
b101100000101101 =
04
08
0<
b110001001100011 1
b110001001100011 9
b110001001100011 ;
b101100000101101 /
b101100000101101 5
b101100000101101 :
b0 )
b0 .
b1000011100001010 &
b1000011100001010 -
b1000011100001010 7
b110001001100011 %
b110001001100011 ,
b110001001100011 6
b10011001100101 $
b10011001100101 +
b10011001100101 3
b101100000101101 #
b101100000101101 *
b101100000101101 2
b111 (
#29
b10011001100101 !
b10011001100101 "
b10011001100101 0
b10011001100101 =
b10011001100101 /
b10011001100101 5
b10011001100101 :
b1000011100001010 1
b1000011100001010 9
b1000011100001010 ;
14
18
b1 )
b1 .
#30
b110001001100011 !
b101100000101101 /
b101100000101101 5
b101100000101101 :
b110001001100011 1
b110001001100011 9
b110001001100011 ;
b110001001100011 "
b110001001100011 0
b110001001100011 =
04
08
1<
b10 )
b10 .
#31
b1000011100001010 !
b1000011100001010 "
b1000011100001010 0
b1000011100001010 =
b10011001100101 /
b10011001100101 5
b10011001100101 :
b1000011100001010 1
b1000011100001010 9
b1000011100001010 ;
14
18
b11 )
b11 .
#32
b10001010000000 !
b10001010000000 "
b10001010000000 0
b10001010000000 =
04
08
0<
b100010110101010 1
b100010110101010 9
b100010110101010 ;
b10001010000000 /
b10001010000000 5
b10001010000000 :
b0 )
b0 .
b1100110010011101 &
b1100110010011101 -
b1100110010011101 7
b100010110101010 %
b100010110101010 ,
b100010110101010 6
b10000100100000 $
b10000100100000 +
b10000100100000 3
b10001010000000 #
b10001010000000 *
b10001010000000 2
b1000 (
#33
b10000100100000 !
b10000100100000 "
b10000100100000 0
b10000100100000 =
b10000100100000 /
b10000100100000 5
b10000100100000 :
b1100110010011101 1
b1100110010011101 9
b1100110010011101 ;
14
18
b1 )
b1 .
#34
b100010110101010 !
b10001010000000 /
b10001010000000 5
b10001010000000 :
b100010110101010 1
b100010110101010 9
b100010110101010 ;
b100010110101010 "
b100010110101010 0
b100010110101010 =
04
08
1<
b10 )
b10 .
#35
b1100110010011101 !
b1100110010011101 "
b1100110010011101 0
b1100110010011101 =
b10000100100000 /
b10000100100000 5
b10000100100000 :
b1100110010011101 1
b1100110010011101 9
b1100110010011101 ;
14
18
b11 )
b11 .
#36
b11111010010110 !
b11111010010110 "
b11111010010110 0
b11111010010110 =
04
08
0<
b11100000001101 1
b11100000001101 9
b11100000001101 ;
b11111010010110 /
b11111010010110 5
b11111010010110 :
b0 )
b0 .
b1101011001010011 &
b1101011001010011 -
b1101011001010011 7
b11100000001101 %
b11100000001101 ,
b11100000001101 6
b1011100000010011 $
b1011100000010011 +
b1011100000010011 3
b11111010010110 #
b11111010010110 *
b11111010010110 2
b1001 (
#37
b1011100000010011 !
b1011100000010011 "
b1011100000010011 0
b1011100000010011 =
b1011100000010011 /
b1011100000010011 5
b1011100000010011 :
b1101011001010011 1
b1101011001010011 9
b1101011001010011 ;
14
18
b1 )
b1 .
#38
b11100000001101 !
b11111010010110 /
b11111010010110 5
b11111010010110 :
b11100000001101 1
b11100000001101 9
b11100000001101 ;
b11100000001101 "
b11100000001101 0
b11100000001101 =
04
08
1<
b10 )
b10 .
#39
b1101011001010011 !
b1101011001010011 "
b1101011001010011 0
b1101011001010011 =
b1011100000010011 /
b1011100000010011 5
b1011100000010011 :
b1101011001010011 1
b1101011001010011 9
b1101011001010011 ;
14
18
b11 )
b11 .
#40
b1101110101101011 !
b1101110101101011 "
b1101110101101011 0
b1101110101101011 =
04
08
0<
b100101000000010 1
b100101000000010 9
b100101000000010 ;
b1101110101101011 /
b1101110101101011 5
b1101110101101011 :
b0 )
b0 .
b11111010101110 &
b11111010101110 -
b11111010101110 7
b100101000000010 %
b100101000000010 ,
b100101000000010 6
b10101011010101 $
b10101011010101 +
b10101011010101 3
b1101110101101011 #
b1101110101101011 *
b1101110101101011 2
b1010 (
#41
b10101011010101 !
b10101011010101 "
b10101011010101 0
b10101011010101 =
b10101011010101 /
b10101011010101 5
b10101011010101 :
b11111010101110 1
b11111010101110 9
b11111010101110 ;
14
18
b1 )
b1 .
#42
b100101000000010 !
b1101110101101011 /
b1101110101101011 5
b1101110101101011 :
b100101000000010 1
b100101000000010 9
b100101000000010 ;
b100101000000010 "
b100101000000010 0
b100101000000010 =
04
08
1<
b10 )
b10 .
#43
b11111010101110 !
b11111010101110 "
b11111010101110 0
b11111010101110 =
b10101011010101 /
b10101011010101 5
b10101011010101 :
b11111010101110 1
b11111010101110 9
b11111010101110 ;
14
18
b11 )
b11 .
#44
b1110100100011101 !
b1110100100011101 "
b1110100100011101 0
b1110100100011101 =
04
08
0<
b100100100100011 1
b100100100100011 9
b100100100100011 ;
b1110100100011101 /
b1110100100011101 5
b1110100100011101 :
b0 )
b0 .
b110010100001010 &
b110010100001010 -
b110010100001010 7
b100100100100011 %
b100100100100011 ,
b100100100100011 6
b111001011001111 $
b111001011001111 +
b111001011001111 3
b1110100100011101 #
b1110100100011101 *
b1110100100011101 2
b1011 (
#45
b111001011001111 !
b111001011001111 "
b111001011001111 0
b111001011001111 =
b111001011001111 /
b111001011001111 5
b111001011001111 :
b110010100001010 1
b110010100001010 9
b110010100001010 ;
14
18
b1 )
b1 .
#46
b100100100100011 !
b1110100100011101 /
b1110100100011101 5
b1110100100011101 :
b100100100100011 1
b100100100100011 9
b100100100100011 ;
b100100100100011 "
b100100100100011 0
b100100100100011 =
04
08
1<
b10 )
b10 .
#47
b110010100001010 !
b110010100001010 "
b110010100001010 0
b110010100001010 =
b111001011001111 /
b111001011001111 5
b111001011001111 :
b110010100001010 1
b110010100001010 9
b110010100001010 ;
14
18
b11 )
b11 .
#48
b101011001010 !
b101011001010 "
b101011001010 0
b101011001010 =
04
08
0<
b1011110111110010 1
b1011110111110010 9
b1011110111110010 ;
b101011001010 /
b101011001010 5
b101011001010 :
b0 )
b0 .
b110000110001010 &
b110000110001010 -
b110000110001010 7
b1011110111110010 %
b1011110111110010 ,
b1011110111110010 6
b100110000111100 $
b100110000111100 +
b100110000111100 3
b101011001010 #
b101011001010 *
b101011001010 2
b1100 (
#49
b100110000111100 !
b100110000111100 "
b100110000111100 0
b100110000111100 =
b100110000111100 /
b100110000111100 5
b100110000111100 :
b110000110001010 1
b110000110001010 9
b110000110001010 ;
14
18
b1 )
b1 .
#50
b1011110111110010 !
b101011001010 /
b101011001010 5
b101011001010 :
b1011110111110010 1
b1011110111110010 9
b1011110111110010 ;
b1011110111110010 "
b1011110111110010 0
b1011110111110010 =
04
08
1<
b10 )
b10 .
#51
b110000110001010 !
b110000110001010 "
b110000110001010 0
b110000110001010 =
b100110000111100 /
b100110000111100 5
b100110000111100 :
b110000110001010 1
b110000110001010 9
b110000110001010 ;
14
18
b11 )
b11 .
#52
b1011001101000001 !
b1011001101000001 "
b1011001101000001 0
b1011001101000001 =
04
08
0<
b1111001101111000 1
b1111001101111000 9
b1111001101111000 ;
b1011001101000001 /
b1011001101000001 5
b1011001101000001 :
b0 )
b0 .
b1001010001001 &
b1001010001001 -
b1001010001001 7
b1111001101111000 %
b1111001101111000 ,
b1111001101111000 6
b11010011011000 $
b11010011011000 +
b11010011011000 3
b1011001101000001 #
b1011001101000001 *
b1011001101000001 2
b1101 (
#53
b11010011011000 !
b11010011011000 "
b11010011011000 0
b11010011011000 =
b11010011011000 /
b11010011011000 5
b11010011011000 :
b1001010001001 1
b1001010001001 9
b1001010001001 ;
14
18
b1 )
b1 .
#54
b1111001101111000 !
b1011001101000001 /
b1011001101000001 5
b1011001101000001 :
b1111001101111000 1
b1111001101111000 9
b1111001101111000 ;
b1111001101111000 "
b1111001101111000 0
b1111001101111000 =
04
08
1<
b10 )
b10 .
#55
b1001010001001 !
b1001010001001 "
b1001010001001 0
b1001010001001 =
b11010011011000 /
b11010011011000 5
b11010011011000 :
b1001010001001 1
b1001010001001 9
b1001010001001 ;
14
18
b11 )
b11 .
#56
b110111101011 !
b110111101011 "
b110111101011 0
b110111101011 =
04
08
0<
b1111100111000110 1
b1111100111000110 9
b1111100111000110 ;
b110111101011 /
b110111101011 5
b110111101011 :
b0 )
b0 .
b1001110101110 &
b1001110101110 -
b1001110101110 7
b1111100111000110 %
b1111100111000110 ,
b1111100111000110 6
b110010110110110 $
b110010110110110 +
b110010110110110 3
b110111101011 #
b110111101011 *
b110111101011 2
b1110 (
#57
b110010110110110 !
b110010110110110 "
b110010110110110 0
b110010110110110 =
b110010110110110 /
b110010110110110 5
b110010110110110 :
b1001110101110 1
b1001110101110 9
b1001110101110 ;
14
18
b1 )
b1 .
#58
b1111100111000110 !
b110111101011 /
b110111101011 5
b110111101011 :
b1111100111000110 1
b1111100111000110 9
b1111100111000110 ;
b1111100111000110 "
b1111100111000110 0
b1111100111000110 =
04
08
1<
b10 )
b10 .
#59
b1001110101110 !
b1001110101110 "
b1001110101110 0
b1001110101110 =
b110010110110110 /
b110010110110110 5
b110010110110110 :
b1001110101110 1
b1001110101110 9
b1001110101110 ;
14
18
b11 )
b11 .
#60
b1010111100 !
b1010111100 "
b1010111100 0
b1010111100 =
04
08
0<
b1001101000001011 1
b1001101000001011 9
b1001101000001011 ;
b1010111100 /
b1010111100 5
b1010111100 :
b0 )
b0 .
b1011111001110001 &
b1011111001110001 -
b1011111001110001 7
b1001101000001011 %
b1001101000001011 ,
b1001101000001011 6
b1101110100101010 $
b1101110100101010 +
b1101110100101010 3
b1010111100 #
b1010111100 *
b1010111100 2
b1111 (
#61
b1101110100101010 !
b1101110100101010 "
b1101110100101010 0
b1101110100101010 =
b1101110100101010 /
b1101110100101010 5
b1101110100101010 :
b1011111001110001 1
b1011111001110001 9
b1011111001110001 ;
14
18
b1 )
b1 .
#62
b1001101000001011 !
b1010111100 /
b1010111100 5
b1010111100 :
b1001101000001011 1
b1001101000001011 9
b1001101000001011 ;
b1001101000001011 "
b1001101000001011 0
b1001101000001011 =
04
08
1<
b10 )
b10 .
#63
b1011111001110001 !
b1011111001110001 "
b1011111001110001 0
b1011111001110001 =
b1101110100101010 /
b1101110100101010 5
b1101110100101010 :
b1011111001110001 1
b1011111001110001 9
b1011111001110001 ;
14
18
b11 )
b11 .
#64
b100000110000101 !
b100000110000101 "
b100000110000101 0
b100000110000101 =
04
08
0<
b110000000111011 1
b110000000111011 9
b110000000111011 ;
b100000110000101 /
b100000110000101 5
b100000110000101 :
b0 )
b0 .
b11001100111010 &
b11001100111010 -
b11001100111010 7
b110000000111011 %
b110000000111011 ,
b110000000111011 6
b101010101001111 $
b101010101001111 +
b101010101001111 3
b100000110000101 #
b100000110000101 *
b100000110000101 2
b10000 (
#65
b101010101001111 !
b101010101001111 "
b101010101001111 0
b101010101001111 =
b101010101001111 /
b101010101001111 5
b101010101001111 :
b11001100111010 1
b11001100111010 9
b11001100111010 ;
14
18
b1 )
b1 .
#66
b110000000111011 !
b100000110000101 /
b100000110000101 5
b100000110000101 :
b110000000111011 1
b110000000111011 9
b110000000111011 ;
b110000000111011 "
b110000000111011 0
b110000000111011 =
04
08
1<
b10 )
b10 .
#67
b11001100111010 !
b11001100111010 "
b11001100111010 0
b11001100111010 =
b101010101001111 /
b101010101001111 5
b101010101001111 :
b11001100111010 1
b11001100111010 9
b11001100111010 ;
14
18
b11 )
b11 .
#68
b11001001111110 !
b11001001111110 "
b11001001111110 0
b11001001111110 =
04
08
0<
b1001101111110001 1
b1001101111110001 9
b1001101111110001 ;
b11001001111110 /
b11001001111110 5
b11001001111110 :
b0 )
b0 .
b100101111011001 &
b100101111011001 -
b100101111011001 7
b1001101111110001 %
b1001101111110001 ,
b1001101111110001 6
b100101100010101 $
b100101100010101 +
b100101100010101 3
b11001001111110 #
b11001001111110 *
b11001001111110 2
b10001 (
#69
b100101100010101 !
b100101100010101 "
b100101100010101 0
b100101100010101 =
b100101100010101 /
b100101100010101 5
b100101100010101 :
b100101111011001 1
b100101111011001 9
b100101111011001 ;
14
18
b1 )
b1 .
#70
b1001101111110001 !
b11001001111110 /
b11001001111110 5
b11001001111110 :
b1001101111110001 1
b1001101111110001 9
b1001101111110001 ;
b1001101111110001 "
b1001101111110001 0
b1001101111110001 =
04
08
1<
b10 )
b10 .
#71
b100101111011001 !
b100101111011001 "
b100101111011001 0
b100101111011001 =
b100101100010101 /
b100101100010101 5
b100101100010101 :
b100101111011001 1
b100101111011001 9
b100101111011001 ;
14
18
b11 )
b11 .
#72
b11101100010 !
b11101100010 "
b11101100010 0
b11101100010 =
04
08
0<
b101010110011111 1
b101010110011111 9
b101010110011111 ;
b11101100010 /
b11101100010 5
b11101100010 :
b0 )
b0 .
b1010000110001111 &
b1010000110001111 -
b1010000110001111 7
b101010110011111 %
b101010110011111 ,
b101010110011111 6
b1111101101001100 $
b1111101101001100 +
b1111101101001100 3
b11101100010 #
b11101100010 *
b11101100010 2
b10010 (
#73
b1111101101001100 !
b1111101101001100 "
b1111101101001100 0
b1111101101001100 =
b1111101101001100 /
b1111101101001100 5
b1111101101001100 :
b1010000110001111 1
b1010000110001111 9
b1010000110001111 ;
14
18
b1 )
b1 .
#74
b101010110011111 !
b11101100010 /
b11101100010 5
b11101100010 :
b101010110011111 1
b101010110011111 9
b101010110011111 ;
b101010110011111 "
b101010110011111 0
b101010110011111 =
04
08
1<
b10 )
b10 .
#75
b1010000110001111 !
b1010000110001111 "
b1010000110001111 0
b1010000110001111 =
b1111101101001100 /
b1111101101001100 5
b1111101101001100 :
b1010000110001111 1
b1010000110001111 9
b1010000110001111 ;
14
18
b11 )
b11 .
#76
b1010100111111000 !
b1010100111111000 "
b1010100111111000 0
b1010100111111000 =
04
08
0<
b101011010011111 1
b101011010011111 9
b101011010011111 ;
b1010100111111000 /
b1010100111111000 5
b1010100111111000 :
b0 )
b0 .
b1001010001011100 &
b1001010001011100 -
b1001010001011100 7
b101011010011111 %
b101011010011111 ,
b101011010011111 6
b110000010110111 $
b110000010110111 +
b110000010110111 3
b1010100111111000 #
b1010100111111000 *
b1010100111111000 2
b10011 (
#77
b110000010110111 !
b110000010110111 "
b110000010110111 0
b110000010110111 =
b110000010110111 /
b110000010110111 5
b110000010110111 :
b1001010001011100 1
b1001010001011100 9
b1001010001011100 ;
14
18
b1 )
b1 .
#78
b101011010011111 !
b1010100111111000 /
b1010100111111000 5
b1010100111111000 :
b101011010011111 1
b101011010011111 9
b101011010011111 ;
b101011010011111 "
b101011010011111 0
b101011010011111 =
04
08
1<
b10 )
b10 .
#79
b1001010001011100 !
b1001010001011100 "
b1001010001011100 0
b1001010001011100 =
b110000010110111 /
b110000010110111 5
b110000010110111 :
b1001010001011100 1
b1001010001011100 9
b1001010001011100 ;
14
18
b11 )
b11 .
#80
b1100000001011011 !
b1100000001011011 "
b1100000001011011 0
b1100000001011011 =
04
08
0<
b11001001001001 1
b11001001001001 9
b11001001001001 ;
b1100000001011011 /
b1100000001011011 5
b1100000001011011 :
b0 )
b0 .
b11111011010000 &
b11111011010000 -
b11111011010000 7
b11001001001001 %
b11001001001001 ,
b11001001001001 6
b11011110001001 $
b11011110001001 +
b11011110001001 3
b1100000001011011 #
b1100000001011011 *
b1100000001011011 2
b10100 (
#81
b11011110001001 !
b11011110001001 "
b11011110001001 0
b11011110001001 =
b11011110001001 /
b11011110001001 5
b11011110001001 :
b11111011010000 1
b11111011010000 9
b11111011010000 ;
14
18
b1 )
b1 .
#82
b11001001001001 !
b1100000001011011 /
b1100000001011011 5
b1100000001011011 :
b11001001001001 1
b11001001001001 9
b11001001001001 ;
b11001001001001 "
b11001001001001 0
b11001001001001 =
04
08
1<
b10 )
b10 .
#83
b11111011010000 !
b11111011010000 "
b11111011010000 0
b11111011010000 =
b11011110001001 /
b11011110001001 5
b11011110001001 :
b11111011010000 1
b11111011010000 9
b11111011010000 ;
14
18
b11 )
b11 .
#84
b1100000011010111 !
b1100000011010111 "
b1100000011010111 0
b1100000011010111 =
04
08
0<
b10111110010110 1
b10111110010110 9
b10111110010110 ;
b1100000011010111 /
b1100000011010111 5
b1100000011010111 :
b0 )
b0 .
b111111100001100 &
b111111100001100 -
b111111100001100 7
b10111110010110 %
b10111110010110 ,
b10111110010110 6
b1111110001010001 $
b1111110001010001 +
b1111110001010001 3
b1100000011010111 #
b1100000011010111 *
b1100000011010111 2
b10101 (
#85
b1111110001010001 !
b1111110001010001 "
b1111110001010001 0
b1111110001010001 =
b1111110001010001 /
b1111110001010001 5
b1111110001010001 :
b111111100001100 1
b111111100001100 9
b111111100001100 ;
14
18
b1 )
b1 .
#86
b10111110010110 !
b1100000011010111 /
b1100000011010111 5
b1100000011010111 :
b10111110010110 1
b10111110010110 9
b10111110010110 ;
b10111110010110 "
b10111110010110 0
b10111110010110 =
04
08
1<
b10 )
b10 .
#87
b111111100001100 !
b111111100001100 "
b111111100001100 0
b111111100001100 =
b1111110001010001 /
b1111110001010001 5
b1111110001010001 :
b111111100001100 1
b111111100001100 9
b111111100001100 ;
14
18
b11 )
b11 .
#88
b1100111011000010 !
b1100111011000010 "
b1100111011000010 0
b1100111011000010 =
04
08
0<
b101101001110111 1
b101101001110111 9
b101101001110111 ;
b1100111011000010 /
b1100111011000010 5
b1100111011000010 :
b0 )
b0 .
b1110110100111101 &
b1110110100111101 -
b1110110100111101 7
b101101001110111 %
b101101001110111 ,
b101101001110111 6
b1110110111001000 $
b1110110111001000 +
b1110110111001000 3
b1100111011000010 #
b1100111011000010 *
b1100111011000010 2
b10110 (
#89
b1110110111001000 !
b1110110111001000 "
b1110110111001000 0
b1110110111001000 =
b1110110111001000 /
b1110110111001000 5
b1110110111001000 :
b1110110100111101 1
b1110110100111101 9
b1110110100111101 ;
14
18
b1 )
b1 .
