02_Boolean_Arithmetic/Add16.v
/**
 * Adds two 16-bit values.
 * The most significant carry bit is ignored.
 * out = a + b (16 bit)
 */

`default_nettype none
module Add16(
	input [15:0] a,
	input [15:0] b,
	output [15:0] out
);

	wire carry0 = a[0] & b[0];
	wire carry1 = ( a[1] & b[1] ) | (carry0 & ( a[1] ^ b[1] ));
	wire carry2 = ( a[2] & b[2] ) | (carry1 & ( a[2] ^ b[2] ));
	wire carry3 = ( a[3] & b[3] ) | (carry2 & ( a[3] ^ b[3] ));
	wire carry4 = ( a[4] & b[4] ) | (carry3 & ( a[4] ^ b[4] ));
	wire carry5 = ( a[5] & b[5] ) | (carry4 & ( a[5] ^ b[5] ));
	wire carry6 = ( a[6] & b[6] ) | (carry5 & ( a[6] ^ b[6] ));
	wire carry7 = ( a[7] & b[7] ) | (carry6 & ( a[7] ^ b[7] ));
	wire carry8 = ( a[8] & b[8] ) | (carry7 & ( a[8] ^ b[8] ));
	wire carry9 = ( a[9] & b[9] ) | (carry8 & ( a[9] ^ b[9] ));
	wire carry10 = ( a[10] & b[10] ) | (carry9 & ( a[10] ^ b[10] ));
	wire carry11 = ( a[11] & b[11] ) | (carry10 & ( a[11] ^ b[11] ));
	wire carry12 = ( a[12] & b[12] ) | (carry11 & ( a[12] ^ b[12] ));
	wire carry13 = ( a[13] & b[13] ) | (carry12 & ( a[13] ^ b[13] ));
	wire carry14 = ( a[14] & b[14] ) | (carry13 & ( a[14] ^ b[14] ));
	wire carry15 = ( a[15] & b[15] ) | (carry14 & ( a[15] ^ b[15] ));

	assign out[0] = a[0] ^ b[0];
	assign out[1] = ( a[1] ^ b[1] ) ^ carry0;
	assign out[2] = ( a[2] ^ b[2] ) ^ carry1;
	assign out[3]  = (a[3]  ^ b[3])  ^ carry2;
	assign out[4]  = (a[4]  ^ b[4])  ^ carry3;
	assign out[5]  = (a[5]  ^ b[5])  ^ carry4;
	assign out[6]  = (a[6]  ^ b[6])  ^ carry5;
	assign out[7]  = (a[7]  ^ b[7])  ^ carry6;
	assign out[8]  = (a[8]  ^ b[8])  ^ carry7;
	assign out[9]  = (a[9]  ^ b[9])  ^ carry8;
	assign out[10] = (a[10] ^ b[10]) ^ carry9;
	assign out[11] = (a[11] ^ b[11]) ^ carry10;
	assign out[12] = (a[12] ^ b[12]) ^ carry11;
	assign out[13] = (a[13] ^ b[13]) ^ carry12;
	assign out[14] = (a[14] ^ b[14]) ^ carry13;
	assign out[15] = (a[15] ^ b[15]) ^ carry14;

endmodule

02_Boolean_Arithmetic/03_Add16/Add16_tb.v
`default_nettype none
module Add16_tb();

	// IN,OUT
	reg [15:0] a,b;
	wire [15:0] out;

	// Part
	Add16 ADD16(
		.a(a),
		.b(b),
		.out(out)
	);

	// Compare
	wire [15:0] out_cmp;
	assign out_cmp = a+b;

	reg fail = 0;
	reg [15:0] n=0;
	task check;
		#1
		if (out != out_cmp) 
			begin
				$display("FAIL: a=%16b, b=%16b, out=%16b",a,b,out);
				fail=1;
			end
	endtask
	  
  	initial begin
  		$dumpvars(0, Add16_tb);
		
		$display("------------------------");
		$display("Testbench: Add16");
		
		for (n=0; n<1000;n=n+1) 
			begin
				a=$random;
				b=$random;
				check();
			end
		
		if (fail==0) $display("passed");
		$display("------------------------");
		$finish;
	end

endmodule

02_Boolean_Arithmetic/03_Add16/_build/default/Add16_tb.vcd
$date
	Sat Apr 18 23:14:24 2026
$end
$version
	Icarus Verilog
$end
$timescale
	1ps
$end
$scope module Add16_tb $end
$var wire 16 ! out_cmp [15:0] $end
$var wire 16 " out [15:0] $end
$var reg 16 # a [15:0] $end
$var reg 16 $ b [15:0] $end
$var reg 1 % fail $end
$var reg 16 & n [15:0] $end
$scope module ADD16 $end
$var wire 16 ' a [15:0] $end
$var wire 16 ( b [15:0] $end
$var wire 1 ) carry0 $end
$var wire 1 * carry1 $end
$var wire 1 + carry10 $end
$var wire 1 , carry11 $end
$var wire 1 - carry12 $end
$var wire 1 . carry13 $end
$var wire 1 / carry14 $end
$var wire 1 0 carry2 $end
$var wire 1 1 carry3 $end
$var wire 1 2 carry4 $end
$var wire 1 3 carry5 $end
$var wire 1 4 carry6 $end
$var wire 1 5 carry7 $end
$var wire 1 6 carry8 $end
$var wire 1 7 carry9 $end
$var wire 16 8 out [15:0] $end
$upscope $end
$scope task check $end
$upscope $end
$upscope $end
$enddefinitions $end
$comment Show the parameter values. $end
$dumpall
$end
#0
$dumpvars
b1001001110100101 8
07
06
05
04
03
02
01
00
1/
1.
1-
1,
1+
0*
0)
b101111010000001 (
b11010100100100 '
b0 &
0%
b101111010000001 $
b11010100100100 #
b1001001110100101 "
b1001001110100101 !
$end
#1
0,
1*
0.
b10110001101100 "
b10110001101100 8
17
1)
b101011001100011 $
b101011001100011 (
b10110001101100 !
b1101011000001001 #
b1101011000001001 '
b1 &
#2
b1010010011010 "
b1010010011010 8
0*
1.
11
1/
10
16
0+
1,
b1001100110001101 $
b1001100110001101 (
b1010010011010 !
b111101100001101 #
b111101100001101 '
b10 &
#3
0/
07
0-
b1101011001110111 "
b1101011001110111 8
0+
0.
00
01
06
0,
0)
b101001000010010 $
b101001000010010 (
b1101011001110111 !
b1000010001100101 #
b1000010001100101 '
b11 &
#4
1,
1+
17
b1011000000001110 "
b1011000000001110 8
16
1/
1)
b1100110100001101 $
b1100110100001101 (
b1011000000001110 !
b1110001100000001 #
b1110001100000001 '
b100 &
#5
0,
0+
0.
11
14
07
0-
b1011111010110011 "
b1011111010110011 8
10
12
13
0)
b1100110100111101 $
b1100110100111101 (
b1011111010110011 !
b1111000101110110 #
b1111000101110110 '
b101 &
#6
04
1.
b100111101111001 "
b100111101111001 8
03
1-
02
15
17
1+
b1111011110001100 $
b1111011110001100 (
b100111101111001 !
b101011111101101 #
b101011111101101 '
b110 &
#7
03
0+
b111010111111 "
b111010111111 8
02
0,
01
14
00
07
0-
b10010011000110 $
b10010011000110 (
b111010111111 !
b1110100111111001 #
b1110100111111001 '
b111 &
#8
0+
0/
b101011101101111 "
b101011101101111 8
07
06
04
0.
b1101001010101010 $
b1101001010101010 (
b101011101101111 !
b1000010011000101 #
b1000010011000101 '
b1000 &
#9
1+
1*
b110101001011100 "
b110101001011100 8
16
10
14
15
13
17
1-
1.
1/
1)
b111001001110111 $
b111001001110111 (
b110101001011100 !
b1111011111100101 #
b1111011111100101 '
b1001 &
#10
06
12
05
11
1,
b1011000110100001 "
b1011000110100001 8
03
04
0.
0)
b1101101110001111 $
b1101101110001111 (
b1011000110100001 !
b1101011000010010 #
b1101011000010010 '
b1010 &
#11
1-
1,
16
1+
b11000000 "
b11000000 8
13
1.
1/
14
15
17
b1001011011001110 $
b1001011011001110 (
b11000000 !
b110100111110010 #
b110100111110010 '
b1011 &
#12
01
03
00
b1100100110101101 "
b1100100110101101 8
02
06
0*
b100111011000101 $
b100111011000101 (
b1100100110101101 !
b111101011101000 #
b111101011101000 '
b1100 &
#13
0/
0.
15
13
b111001000011001 "
b111001000011001 8
0+
16
0-
11
14
10
12
07
b10100010111101 $
b10100010111101 (
b111001000011001 !
b100100101011100 #
b100100101011100 '
b1101 &
#14
0/
0+
0.
05
07
06
0-
b111111010010010 "
b111111010010010 8
0,
02
1)
b10011001100101 $
b10011001100101 (
b111111010010010 !
b101100000101101 #
b101100000101101 '
b1110 &
#15
04
01
1+
b1110100101101101 "
b1110100101101101 8
03
1*
00
17
0)
b1000011100001010 $
b1000011100001010 (
b1110100101101101 !
b110001001100011 #
b110001001100011 '
b1111 &
#16
0+
b100001110100000 "
b100001110100000 8
07
1.
0*
b10000100100000 $
b10000100100000 (
b100001110100000 !
b10001010000000 #
b10001010000000 '
b10000 &
#17
13
16
12
1,
b1001001000111 "
b1001001000111 8
15
11
1+
0.
1/
b1100110010011101 $
b1100110010011101 (
b1001001000111 !
b100010110101010 #
b100010110101010 '
b10001 &
#18
10
b1111011010101001 "
b1111011010101001 8
03
06
07
1*
05
0+
01
1-
1.
0/
b1011100000010011 $
b1011100000010011 (
b1111011010101001 !
b11111010010110 #
b11111010010110 '
b10010 &
#19
1/
11
b111001100000 "
b111001100000 8
0,
12
1)
b1101011001010011 $
b1101011001010011 (
b111001100000 !
b11100000001101 #
b11100000001101 '
b10011 &
#20
1+
17
1/
16
1.
b100001000000 "
b100001000000 8
15
13
1,
1-
14
b10101011010101 $
b10101011010101 (
b100001000000 !
b1101110101101011 #
b1101110101101011 '
b10100 &
#21
03
05
b1000100010110000 "
b1000100010110000 8
02
06
04
0)
b11111010101110 $
b11111010101110 (
b1000100010110000 !
b100101000000010 #
b100101000000010 '
b10101 &
#22
0-
0,
b101101111101100 "
b101101111101100 8
0+
12
07
1)
b111001011001111 $
b111001011001111 (
b101101111101100 !
b1110100100011101 #
b1110100100011101 '
b10110 &
#23
01
b1010111000101101 "
b1010111000101101 8
02
03
16
00
0.
0)
b110010100001010 $
b110010100001010 (
b1010111000101101 !
b100100100100011 #
b100100100100011 '
b10111 &
#24
15
14
13
0+
00
12
07
b101011100000110 "
b101011100000110 8
0*
1,
11
06
0/
b100110000111100 $
b100110000111100 (
b101011100000110 !
b101011001010 #
b101011001010 '
b11000 &
#25
04
03
02
1/
b1111101111100 "
b1111101111100 8
0-
1*
0,
01
16
1.
b110000110001010 $
b110000110001010 (
b1111101111100 !
b1011110111110010 #
b1011110111110010 '
b11001 &
#26
1+
0/
17
b1110100000011001 "
b1110100000011001 8
14
16
1-
0*
15
b11010011011000 $
b11010011011000 (
b1110100000011001 !
b1011001101000001 #
b1011001101000001 '
b11010 &
#27
16
13
15
12
b11000000001 "
b11000000001 8
0+
1/
14
11
b1001010001001 $
b1001010001001 (
b11000000001 !
b1111001101111000 #
b1111001101111000 '
b11011 &
#28
0/
12
1,
0.
b111001110100001 "
b111001110100001 8
10
11
1*
07
1+
0-
b110010110110110 $
b110010110110110 (
b111001110100001 !
b110111101011 #
b110111101011 '
b11100 &
#29
04
1/
03
0,
1.
02
17
b110101110100 "
b110101110100 8
0+
1-
b1001110101110 $
b1001110101110 (
b110101110100 !
b1111100111000110 #
b1111100111000110 '
b11101 &
#30
07
0,
0/
06
b1101111111100110 "
b1101111111100110 8
0+
12
0.
00
05
0*
13
0-
b1101110100101010 $
b1101110100101010 (
b1101111111100110 !
b1010111100 #
b1010111100 '
b11110 &
#31
03
02
1+
b101100001111100 "
b101100001111100 8
04
1.
1*
01
17
1,
1-
1)
b1011111001110001 $
b1011111001110001 (
b101100001111100 !
b1001101000001011 #
b1001101000001011 '
b11111 &
#32
11
0+
0-
b1001011011010100 "
b1001011011010100 8
0.
10
16
07
0,
1/
b101010101001111 $
b101010101001111 (
b1001011011010100 !
b100000110000101 #
b100000110000101 '
b100000 &
#33
b1001001101110101 "
b1001001101110101 8
00
12
13
06
1.
0)
b11001100111010 $
b11001100111010 (
b1001001101110101 !
b110000000111011 #
b110000000111011 '
b100001 &
#34
0/
b111110110010011 "
b111110110010011 8
14
0*
0.
10
17
b100101100010101 $
b100101100010101 (
b111110110010011 !
b11001001111110 #
b11001001111110 '
b100010 &
#35
01
1-
b1110011111001010 "
b1110011111001010 8
00
15
16
1,
1)
b100101111011001 $
b100101111011001 (
b1110011111001010 !
b1001101111110001 #
b1001101111110001 '
b100011 &
#36
1/
03
1-
b1010101110 "
b1010101110 8
1.
1+
02
05
1,
0)
b1111101101001100 $
b1111101101001100 (
b1010101110 !
b11101100010 #
b11101100010 '
b100100 &
#37
0/
0.
0-
12
0+
b1111011100101110 "
b1111011100101110 8
0,
1*
10
11
04
15
07
1)
b1010000110001111 $
b1010000110001111 (
b1111011100101110 !
b101010110011111 #
b101010110011111 '
b100101 &
#38
01
00
14
1/
b101010101111 "
b101010101111 8
0*
13
1.
0)
b110000010110111 $
b110000010110111 (
b101010101111 !
b1010100111111000 #
b1010100111111000 '
b100110 &
#39
05
04
0/
b1110101011111011 "
b1110101011111011 8
06
07
11
10
03
1+
1-
0.
b1001010001011100 $
b1001010001011100 (
b1110101011111011 !
b101011010011111 #
b101011010011111 '
b100111 &
#40
1*
b1111011111100100 "
b1111011111100100 8
00
0+
0-
1)
b11011110001001 $
b11011110001001 (
b1111011111100100 !
b1100000001011011 #
b1100000001011011 '
b101000 &
#41
1,
02
15
1+
b111000100011001 "
b111000100011001 8
0*
01
14
17
1-
1.
0)
b11111011010000 $
b11111011010000 (
b111000100011001 !
b11001001001001 #
b11001001001001 '
b101001 &
#42
0.
0-
0,
10
0+
b1011110100101000 "
b1011110100101000 8
1*
12
07
1/
1)
b1111110001010001 $
b1111110001010001 (
b1011110100101000 !
b1100000011010111 #
b1100000011010111 '
b101010 &
#43
05
1-
b1010111010100010 "
b1010111010100010 8
11
0*
12
04
16
17
1+
1,
1.
1/
0)
b111111100001100 $
b111111100001100 (
b1010111010100010 !
b10111110010110 #
b10111110010110 '
b101011 &
#44
0.
01
b1011110010001010 "
b1011110010001010 8
0-
02
15
17
00
14
16
b1110110111001000 $
b1110110111001000 (
b1011110010001010 !
b1100111011000010 #
b1100111011000010 '
b101100 &
#45
0+
07
1.
11
06
b100011110110100 "
b100011110110100 8
1*
1-
10
12
13
05
1)
b1110110100111101 $
b1110110100111101 (
b100011110110100 !
b101101001110111 #
b101101001110111 '
b101101 &
#46
0/
0-
b1101101110010000 "
b1101101110010000 8
0.
0,
0)
b1111110 $
b1111110 (
b1101101110010000 !
b1101101100010010 #
b1101101100010010 '
b101110 &
#47
1+
17
00
b110100010100110 "
b110100010100110 8
16
0*
1)
b1110011100111001 $
b1110011100111001 (
b110100010100110 !
b1000000101101101 #
b1000000101101101 '
b101111 &
#48
1/
1.
1-
10
04
b1000010111110010 "
b1000010111110010 8
05
1,
11
06
1*
03
b1111011011010011 $
b1111011011010011 (
b1000010111110010 !
b1000111100011111 #
b1000111100011111 '
b110000 &
#49
06
02
05
01
04
0.
0+
00
03
0-
0/
b1011011111111101 "
b1011011111111101 8
07
0*
0)
b1000100001111000 $
b1000100001111000 (
b1011011111111101 !
b10111110000101 #
b10111110000101 '
b110001 &
#50
17
12
b1010010010100100 "
b1010010010100100 8
1*
1-
16
11
14
1/
1)
b100101101001001 $
b100101101001001 (
b1010010010100100 !
b101100101011011 #
b101100101011011 '
b110010 &
#51
b101110101101001 "
b101110101101001 8
10
0-
13
04
06
1+
1.
0/
0)
b1010111100101010 $
b1010111100101010 (
b101110101101001 !
b1010111000111111 #
b1010111000111111 '
b110011 &
#52
02
06
01
05
00
0,
0-
04
1/
b1001101111011110 "
b1001101111011110 8
07
0*
03
0+
b11100010000110 $
b11100010000110 (
b1001101111011110 !
b110001101011000 #
b110001101011000 '
b110100 &
#53
12
0/
b1111111100101010 "
b1111111100101010 8
11
10
15
0.
b1111001010011100 $
b1111001010011100 (
b1111111100101010 !
b110010001110 #
b110010001110 '
b110101 &
#54
12
14
1.
b101011000100000 "
b101011000100000 8
16
1*
11
15
1,
10
13
1-
b1011110000100110 $
b1011110000100110 (
b101011000100000 !
b1001100111111010 #
b1001100111111010 '
b110110 &
#55
02
b1100110000010110 "
b1100110000010110 8
00
01
17
1+
0,
1)
b1011010010100011 $
b1011010010100011 (
b1100110000010110 !
b1011101110011 #
b1011101110011 '
b110111 &
#56
12
11
05
07
0.
b11101011100010 "
b11101011100010 8
10
04
06
0,
0+
0-
b1001001010110011 $
b1001001010110011 (
b11101011100010 !
b1010100000101111 #
b1010100000101111 '
b111000 &
#57
1-
1,
b110001110100011 "
b110001110100011 8
0*
03
14
1+
0)
b110101000100 $
b110101000100 (
b110001110100011 !
b101011001011111 #
b101011001011111 '
b111001 &
#58
12
17
11
16
1/
b11010011000010 "
b11010011000010 8
13
1*
10
15
1.
1)
b11011011001011 $
b11011011001011 (
b11010011000010 !
b1111110111110111 #
b1111110111110111 '
b111010 &
#59
0/
b1111011001000000 "
b1111011001000000 8
0+
0.
0)
b1101101101011010 $
b1101101101011010 (
b1111011001000000 !
b1101011100110 #
b1101011100110 '
b111011 &
#60
00
b1010010000010110 "
b1010010000010110 8
02
0*
0,
0-
1/
1)
b1110001011101101 $
b1110001011101101 (
b1010010000010110 !
b1100000100101001 #
b1100000100101001 '
b111100 &
#61
1-
07
1,
02
06
b10001100111111 "
b10001100111111 8
01
03
1+
1.
0)
b1011011001100101 $
b1011011001100101 (
b10001100111111 !
b110110011011010 #
b110110011011010 '
b111101 &
#62
0/
0.
0-
13
11
1*
0,
b111011110010100 "
b111011110010100 8
12
10
14
0+
1)
b1001010011011111 $
b1001010011011111 (
b111011110010100 !
b1110001010110101 #
b1110001010110101 '
b111110 &
#63
03
02
01
1+
1/
00
17
1.
0*
b1100010111101 "
b1100010111101 8
05
16
1,
1-
0)
b1111111101000100 $
b1111111101000100 (
b1100010111101 !
b1100101111001 #
b1100101111001 '
b111111 &
#64
0+
07
0.
0/
05
b1011111111010 "
b1011111111010 8
04
06
0-
b101100101010 $
b101100101010 (
b1011111111010 !
b110011010000 #
b110011010000 '
b1000000 &
#65
17
10
b111110010111001 "
b111110010111001 8
1+
1*
11
16
b1100111100001110 $
b1100111100001110 (
b111110010111001 !
b1010110110101011 #
b1010110110101011 '
b1000001 &
#66
00
07
1-
b110101001110110 "
b110101001110110 8
15
16
1.
0*
12
b1011110010011010 $
b1011110010011010 (
b110101001110110 !
b1010110111011100 #
b1010110111011100 '
b1000010 &
#67
0.
10
12
0-
b111010111000000 "
b111010111000000 8
1*
13
06
0/
11
14
17
0+
0,
1)
b1011000011 $
b1011000011 (
b111010111000000 !
b111001011111101 #
b111001011111101 '
b1000011 &
#68
b1101011010100100 "
b1101011010100100 8
03
0+
1.
1/
05
16
07
1,
0)
b1110100101001110 $
b1110100101001110 (
b1101011010100100 !
b1110110101010110 #
b1110110101010110 '
b1000100 &
#69
02
03
07
b1010101001110001 "
b1010101001110001 8
04
1+
06
0,
1-
b11010000001010 $
b11010000001010 (
b1010101001110001 !
b111011001100111 #
b111011001100111 '
b1000101 &
#70
01
00
0/
b100001111101110 "
b100001111101110 8
0*
13
12
0+
1,
b1000101000111000 $
b1000101000111000 (
b100001111101110 !
b1011100110110110 #
b1011100110110110 '
b1000110 &
#71
17
16
15
0/
14
0-
0.
b100110000110001 "
b100110000110001 8
11
1+
0,
b1100010010111000 $
b1100010010111000 (
b100110000110001 !
b1000011101111001 #
b1000011101111001 '
b1000111 &
#72
1/
1.
b1110100100111 "
b1110100100111 8
04
01
03
1,
1-
b101110110010011 $
b101110110010011 (
b1110100100111 !
b1011111110010100 #
b1011111110010100 '
b1001000 &
#73
0+
0/
07
0.
b1111011001011101 "
b1111011001011101 8
02
05
06
0-
b1100101001011001 $
b1100101001011001 (
b1111011001011101 !
b10110000000100 #
b10110000000100 '
b1001001 &
#74
1+
17
16
1.
10
12
15
1-
1*
b100100000101000 "
b100100000101000 8
11
14
1/
1)
b1101111001001101 $
b1101111001001101 (
b100100000101000 !
b110100111011011 #
b110100111011011 '
b1001010 &
#75
00
0-
b1101111001000110 "
b1101111001000110 8
13
0*
0,
0/
b10011001101101 $
b10011001101101 (
b1101111001000110 !
b1011011111011001 #
b1011011111011001 '
b1001011 &
#76
13
10
12
b10110001000000 "
b10110001000000 8
0.
1*
11
0+
1/
0)
b100100111001010 $
b100100111001010 (
b10110001000000 !
b1110001001110110 #
b1110001001110110 '
b1001100 &
#77
0-
0,
01
b1001111101001011 "
b1001111101001011 8
07
0+
0*
1.
04
1/
b111000110010101 $
b111000110010101 (
b1001111101001011 !
b10110110110110 #
b10110110110110 '
b1001101 &
#78
06
0/
b1011010101001010 "
b1011010101001010 8
03
04
1,
02
05
17
1-
0.
b1001101100000100 $
b1001101100000100 (
b1011010101001010 !
b1101001000110 #
b1101001000110 '
b1001110 &
#79
1+
12
0/
15
b110100101100000 "
b110100101100000 8
11
1*
0.
10
14
13
16
17
0,
0-
1)
b11101101001 $
b11101101001 (
b110100101100000 !
b110000111110111 #
b110000111110111 '
b1001111 &
#80
03
02
01
1.
00
1-
b100100000111100 "
b100100000111100 8
0*
04
1,
0)
b1000110110001000 $
b1000110110001000 (
b100100000111100 !
b1011101010110100 #
b1011101010110100 '
b1010000 &
#81
0-
0,
0+
06
b1101110101010101 "
b1101110101010101 8
07
0.
0/
13
11
05
b10000101101 $
b10000101101 (
b1101110101010101 !
b1101100100101000 #
b1101100100101000 '
b1010001 &
#82
05
1.
b1100110011110101 "
b1100110011110101 8
04
1-
1*
10
11
03
b1001110000101110 $
b1001110000101110 (
b1100110011110101 !
b11000011000111 #
b11000011000111 '
b1010010 &
#83
00
0.
12
b10100100100100 "
b10100100100100 8
0*
1+
0-
1/
b100010100011100 $
b100010100011100 (
b10100100100100 !
b1110010000001000 #
b1110010000001000 '
b1010011 &
#84
16
15
14
b1010111000100110 "
b1010111000100110 8
13
17
0/
1)
b11100101001 $
b11100101001 (
b1010111000100110 !
b1010011011111101 #
b1010011011111101 '
b1010100 &
#85
0+
07
06
05
12
b1111011110100010 "
b1111011110100010 8
04
10
11
03
0)
b110011110000110 $
b110011110000110 (
b1111011110100010 !
b1001000000011100 #
b1001000000011100 '
b1010101 &
#86
15
14
13
b1100111100010111 "
b1100111100010111 8
00
b1100011000111101 $
b1100011000111101 (
b1100111100010111 !
b100011011010 #
b100011011010 '
b1010110 &
#87
07
02
b110101111010110 "
b110101111010110 8
05
06
01
1+
b1100010001110000 $
b1100010001110000 (
b110101111010110 !
b1010011101100110 #
b1010011101100110 '
b1010111 &
#88
16
0-
15
0,
b1001111000101101 "
b1001111000101101 8
1*
0+
12
b1001100110111010 $
b1001100110111010 (
b1001111000101101 !
b10001110011 #
b10001110011 '
b1011000 &
#89
1/
10
17
b10110101011000 "
b10110101011000 8
11
1-
1.
b111100111111010 $
b111100111111010 (
b10110101011000 !
b1011001101011110 #
b1011001101011110 '
b1011001 &
#90
07
06
05
01
0/
04
00
0.
03
b1111101111101111 "
b1111101111101111 8
0*
1+
0-
b1111011000011010 $
b1111011000011010 (
b1111101111101111 !
b10111010101 #
b10111010101 '
b1011010 &
#91
11
10
1*
b110000111110000 "
b110000111110000 8
13
0+
1)
b110000100110111 $
b110000100110111 (
b110000111110000 !
b10111001 #
b10111001 '
b1011011 &
#92
1+
00
02
17
b101100101010110 "
b101100101010110 8
0*
01
15
03
16
1.
0)
b10000111000000 $
b10000111000000 (
b101100101010110 !
b11011110010110 #
b11011110010110 '
b1011100 &
#93
b1011100111011100 "
b1011100111011100 8
1*
10
06
1-
13
05
1,
0.
b1101010110110 $
b1101010110110 (
b1011100111011100 !
b1001111100100110 #
b1001111100100110 '
b1011101 &
#94
15
b1001001101011001 "
b1001001101011001 8
16
0*
11
12
14
0-
b111111011100 $
b111111011100 (
b1001001101011001 !
b1000001101111101 #
b1000001101111101 '
b1011110 &
#95
05
04
03
02
01
1.
b101011011111110 "
b101011011111110 8
00
1-
1/
b1111111101111000 $
b1111111101111000 (
b101011011111110 !
b101011110000110 #
b101011110000110 '
b1011111 &
#96
0-
10
17
13
15
0,
0.
b1110001011001 "
b1110001011001 8
1*
16
11
12
14
0+
0/
b1000000011011011 $
b1000000011011011 (
b1110001011001 !
b1001101101111110 #
b1001101101111110 '
b1100000 &
#97
1-
1,
1+
b1110001001001000 "
b1110001001001000 8
1.
1)
b10101101111001 $
b10101101111001 (
b1110001001001000 !
b1011011011001111 #
b1011011011001111 '
b1100001 &
#98
02
07
01
06
0*
00
0-
b1101001101011011 "
b1101001101011011 8
1/
0)
b1110111001100001 $
b1110111001100001 (
b1101001101011011 !
b1110010011111010 #
b1110010011111010 '
b1100010 &
#99
10
05
1/
1-
1*
06
b1000000110111000 "
b1000000110111000 8
03
04
0+
1.
1)
b111100010100001 $
b111100010100001 (
b1000000110111000 !
b100100010111 #
b100100010111 '
b1100011 &
#100
00
b10011111010110 "
b10011111010110 8
0.
0/
0*
0,
0)
b1001011001010000 $
b1001011001010000 (
b10011111010110 !
b1001000110000110 #
b1001000110000110 '
b1100100 &
#101
16
15
14
b1110001000101010 "
b1110001000101010 8
10
12
13
1,
1)
b1000100000110101 $
b1000100000110101 (
b1110001000101010 !
b101100111110101 #
b101100111110101 '
b1100101 &
#102
06
05
0/
0+
04
0-
b1111111111101010 "
b1111111111101010 8
0.
01
07
03
0,
00
02
b111010111000001 $
b111010111000001 (
b1111111111101010 !
b1000101000101001 #
b1000101000101001 '
b1100110 &
#103
1/
b10100101011101 "
b10100101011101 8
15
1+
1-
1.
0)
b1011010010011000 $
b1011010010011000 (
b10100101011101 !
b111010011000101 #
b111010011000101 '
b1100111 &
#104
0.
b1011110110111110 "
b1011110110111110 8
06
0,
14
0-
1*
05
17
0+
1)
b100001001110011 $
b100001001110011 (
b1011110110111110 !
b111101101001011 #
b111101101001011 '
b1101000 &
#105
b1111110101110110 "
b1111110101110110 8
00
11
04
0/
0*
15
1+
0)
b1011010001010 $
b1011010001010 (
b1111110101110110 !
b1110011011101100 #
b1110011011101100 '
b1101001 &
#106
b101000111110110 "
b101000111110110 8
06
05
07
0+
b1000000010101000 $
b1000000010101000 (
b101000111110110 !
b1101000101001110 #
b1101000101001110 '
b1101010 &
#107
1/
1.
16
1-
b1000101001001010 "
b1000101001001010 8
01
13
15
1+
1,
1)
b1000110010100001 $
b1000110010100001 (
b1000101001001010 !
b1111110110101001 #
b1111110110101001 '
b1101011 &
#108
0-
11
06
b1111111110100 "
b1111111110100 8
07
0,
1*
10
03
05
0+
0)
b110011011100110 $
b110011011100110 (
b1111111110100 !
b1011100100001110 #
b1011100100001110 '
b1101100 &
#109
13
0/
12
b111010111001001 "
b111010111001001 8
0.
b1011010100101010 $
b1011010100101010 (
b111010111001001 !
b1100000010011111 #
b1100000010011111 '
b1101101 &
#110
1/
03
00
1,
1.
b1000110110111 "
b1000110110111 8
02
0*
1+
1-
b1111010010001101 $
b1111010010001101 (
b1000110110111 !
b1110100101010 #
b1110100101010 '
b1101110 &
#111
13
b1110010111010110 "
b1110010111010110 8
12
17
b1110011000111000 $
b1110011000111000 (
b1110010111010110 !
b1111111110011110 #
b1111111110011110 '
b1101111 &
#112
16
15
0,
0-
b1000110001000001 "
b1000110001000001 8
14
17
0+
b1110001111001000 $
b1110001111001000 (
b1000110001000001 !
b1010100001111001 #
b1010100001111001 '
b1110000 &
#113
05
04
02
b1000011011011101 "
b1000011011011101 8
07
03
0+
01
1*
0.
b100000100010011 $
b100000100010011 (
b1000011011011101 !
b100010111001010 #
b100010111001010 '
b1110001 &
#114
11
1+
15
10
17
b111100000110010 "
b111100000110010 8
14
16
0/
1,
1)
b1010111011000111 $
b1010111011000111 (
b111100000110010 !
b1100100101101011 #
b1100100101101011 '
b1110010 &
#115
b111101101110000 "
b111101101110000 8
07
13
12
04
1-
0)
b1001110110111010 $
b1001110110111010 (
b111101101110000 !
b1101110110110110 #
b1101110110110110 '
b1110011 &
#116
03
02
01
1-
00
b100000101111101 "
b100000101111101 8
04
17
1.
1,
0*
1+
b1001010110111001 $
b1001010110111001 (
b100000101111101 !
b1010101111000100 #
b1010101111000100 '
b1110100 &
#117
0,
13
0+
b110111001000110 "
b110111001000110 8
0.
0/
12
b1001101010110100 $
b1001101010110100 (
b110111001000110 !
b1101001110010010 #
b1101001110010010 '
b1110101 &
#118
17
13
11
16
14
1.
b1100110000000101 "
b1100110000000101 8
1*
12
10
15
b1001000010000110 $
b1001000010000110 (
b1100110000000101 !
b11101101111111 #
b11101101111111 '
b1110110 &
#119
01
07
1/
b1000101011101100 "
b1000101011101100 8
00
1+
b1001010011110010 $
b1001010011110010 (
b1000101011101100 !
b1111010111111010 #
b1111010111111010 '
b1110111 &
#120
0,
06
0/
01
05
0.
00
07
b111111111101111 "
b111111111101111 8
0*
04
0+
0-
b101111010111101 $
b101111010111101 (
b111111111101111 !
b10000100110010 #
b10000100110010 '
b1111000 &
#121
03
16
1,
04
b111001001101000 "
b111001001101000 8
10
02
15
1+
b1010010011100100 $
b1010010011100100 (
b111001001101000 !
b1100110110000100 #
b1100110110000100 '
b1111001 &
#122
1.
1-
b100100101110011 "
b100100101110011 8
17
1+
1/
00
11
b111100110101001 $
b111100110101001 (
b100100101110011 !
b1100111111001010 #
b1100111111001010 '
b1111010 &
#123
b101001000101111 "
b101001000101111 8
0-
07
0+
01
0/
b1010100110001110 $
b1010100110001110 (
b101001000101111 !
b1010100010100001 #
b1010100010100001 '
b1111011 &
#124
14
13
12
06
1+
1-
b1000100100000110 "
b1000100100000110 8
1/
15
1.
1*
11
17
1)
b1111000001011 $
b1111000001011 (
b1000100100000110 !
b110101011111011 #
b110101011111011 '
b1111100 &
#125
0,
03
0+
b1100111010111000 "
b1100111010111000 8
16
10
02
0/
07
b11110111001001 $
b11110111001001 (
b1100111010111000 !
b1001000011101111 #
b1001000011101111 '
b1111101 &
#126
06
0.
0*
b10110110101011 "
b10110110101011 8
13
01
12
14
05
0-
1/
0)
b100100001110101 $
b100100001110101 (
b10110110101011 !
b1110010100110110 #
b1110010100110110 '
b1111110 &
#127
04
06
1,
03
1.
05
b1010111111010 "
b1010111111010 8
1*
10
1+
1/
11
02
17
1-
1)
b1011111101101011 $
b1011111101101011 (
b1010111111010 !
b101011010001111 #
b101011010001111 '
b1111111 &
#128
0-
16
00
b1001110000110110 "
b1001110000110110 8
0,
15
17
0*
0)
b1011010010101110 $
b1011010010101110 (
b1001110000110110 !
b1110011110001000 #
b1110011110001000 '
b10000000 &
#129
0+
0/
07
b1100011100101101 "
b1100011100101101 8
01
1*
12
0.
b100010110010010 $
b100010110010010 (
b1100011100101101 !
b1000000110011011 #
b1000000110011011 '
b10000001 &
#130
0.
0-
0,
0+
b1011111101010101 "
b1011111101010101 8
07
11
06
0*
02
13
05
1/
b1110000000101101 $
b1110000000101101 (
b1011111101010101 !
b1101111100101000 #
b1101111100101000 '
b10000010 &
