01_Boolean_Logic/DMux.v
/**
 * Demultiplexor:
 * {a, b} = {in, 0} if sel == 0
 *          {0, in} if sel == 1
 */

`default_nettype none
module DMux(
  input in,
  input sel,
    output a,
  output b
);

  assign a = sel ? 1'b0 : in;
  assign b = sel ? in : 1'b0;

endmodule

01_Boolean_Logic/DMux4Way.v
/**
 * 4-way demultiplexor:
 * {a, b, c, d} = {in, 0, 0, 0} if sel == 00
 *                {0, in, 0, 0} if sel == 01
 *                {0, 0, in, 0} if sel == 10
 *                {0, 0, 0, in} if sel == 11
 */

`default_nettype none
module DMux4Way(
	input in,
	input [1:0] sel,
    output a,
	output b,
	output c,
	output d
);
/*
	assign a = sel == 2'b00 ? in : 1'b0 ;
	assign b = sel == 2'b01 ? in : 1'b0 ;
	assign c = sel == 2'b10 ? in : 1'b0 ;
	assign d = sel == 2'b11 ? in : 1'b0 ;
*/
    wire ch1,ch2;

    DMux d1(in,sel[1],ch1,ch2);
    DMux d2(ch1,sel[0],a,b);
    DMux d3(ch2,sel[0],c,d);


endmodule

01_Boolean_Logic/16_DMux4Way/DMux4Way_tb.v
`default_nettype none
module DMux4Way_tb();

	// IN,OUT
	reg in;
	reg [1:0] sel;
	wire a,b,c,d;
	
	// Part
	DMux4Way DMUX4WAY(
		.in(in),
		.sel(sel),
		.a(a),
		.b(b),
		.c(c),
		.d(d)
	);

	// Compare
	wire a_cmp,b_cmp,c_cmp,d_cmp;
	assign a_cmp = (sel==0)?in:0;
	assign b_cmp = (sel==1)?in:0;
	assign c_cmp = (sel==2)?in:0;
	assign d_cmp = (sel==3)?in:0;

	reg fail = 0;
	task check;
		#1
		if ((a != a_cmp) || (b != b_cmp) || (c != c_cmp) || (d != d_cmp)) 
			begin
				$display("FAIL: in=%1b, sel=%1b, a=%1b, b=%1b, c=%1b, d=%1b",in,sel,a,b,c,d);
				fail=1;
			end
	endtask
	  
  	initial begin
  		$dumpvars(0, DMux4Way_tb);
		
		$display("------------------------");
		$display("Testbench: DMux4Way");
		
		in=0;sel=0;check();
		in=0;sel=1;check();
		in=0;sel=2;check();
		in=0;sel=3;check();
		in=1;sel=0;check();
		in=1;sel=1;check();
		in=1;sel=2;check();
		in=1;sel=3;check();
		
		if (fail==0) $display("passed");
		$display("------------------------");
		$finish;
	end

endmodule

01_Boolean_Logic/16_DMux4Way/_build/default/DMux4Way_tb.vcd
$date
	Wed Apr  1 22:18:51 2026
$end
$version
	Icarus Verilog
$end
$timescale
	1ps
$end
$scope module DMux4Way_tb $end
$var wire 1 ! d_cmp $end
$var wire 1 " d $end
$var wire 1 # c_cmp $end
$var wire 1 $ c $end
$var wire 1 % b_cmp $end
$var wire 1 & b $end
$var wire 1 ' a_cmp $end
$var wire 1 ( a $end
$var reg 1 ) fail $end
$var reg 1 * in $end
$var reg 2 + sel [1:0] $end
$scope module DMUX4WAY $end
$var wire 1 * in $end
$var wire 2 , sel [1:0] $end
$var wire 1 " d $end
$var wire 1 - ch2 $end
$var wire 1 . ch1 $end
$var wire 1 $ c $end
$var wire 1 & b $end
$var wire 1 ( a $end
$scope module d1 $end
$var wire 1 * in $end
$var wire 1 / sel $end
$var wire 1 - b $end
$var wire 1 . a $end
$upscope $end
$scope module d2 $end
$var wire 1 . in $end
$var wire 1 0 sel $end
$var wire 1 & b $end
$var wire 1 ( a $end
$upscope $end
$scope module d3 $end
$var wire 1 - in $end
$var wire 1 1 sel $end
$var wire 1 " b $end
$var wire 1 $ a $end
$upscope $end
$upscope $end
$scope task check $end
$upscope $end
$upscope $end
$enddefinitions $end
$comment Show the parameter values. $end
$dumpall
$end
#0
$dumpvars
01
00
0/
0.
0-
b0 ,
b0 +
0*
0)
0(
0'
0&
0%
0$
0#
0"
0!
$end
#1
10
11
b1 +
b1 ,
#2
1/
00
01
b10 +
b10 ,
#3
10
11
b11 +
b11 ,
#4
1(
1'
1.
0$
0/
00
01
0!
0-
b0 +
b0 ,
1*
#5
0'
1%
0(
1&
10
11
b1 +
b1 ,
#6
1$
0%
1#
0.
1-
0(
0&
1/
00
01
b10 +
b10 ,
#7
0#
1!
0$
1"
10
11
b11 +
b11 ,
